Workbook

Sheet Property Summary
I2: Property Summary
B3: =C8&", "&C9 -> Phoenix, AZ | I3: Wind River Group
B5: Property Description | C5: CoStar Properties: Summary | E5: Property Size | F5: CoStar Properties: Summary | H5: Purchase Metrics | I5: OM / T12 Financials
B6: Property Name | C6: Serafina | E6: Total Units | F6: 183 | H6: Trailing 12 Revenue | I6: 3412780.9
B7: Street Address | C7: 11025 S 51st St | E7: Avg Unit Size | F7: 863 | H7: Trailing 12 Expenses | I7: 1245455.1
B8: City | C8: Phoenix | E8: Current Vacancy | F8: 0.055 | H8: Trailing 12 Net Operating Income | I8: =I6-I7 -> 2167325.8
B9: State | C9: AZ | E9: Building(s) | F9: 15
B10: County | C10: Maricopa | E10: Floors | F10: 2 | H10: Guidance Price | I10: 38000000
B11: Zip Code | C11: 85044 | H11: Implied Cap Rate | I11: =iferror(I8/I10,"") -> 0.057034889
B12: Land Area | C12: 8.15 | H12: Price per Unit | I12: =iferror(I10/F6,"") -> 207650.27
B13: Year Built | C13: 1985 | H13: Call for Offers Date
B14: Year Renovated
B15: Management Type | C15: 3rd Party Management
B16: Management Company | C16: Western Wealth Communities
B18: Seller Information
B19: Seller Name | C19: Western Wealth Capital
B20: How Long Have They Owned? | C20: 6
B21: Last Sold Price | C21: 27450000
B22: Why Are They Selling? | C22: "They want to take some chips off of the table", Brett Polachek
B23: What Improvements Have They Made? | C23: Classic – original 1980’s décor – 60 units Prior Upgrade (PU) - stainless or black appliances, dark grey cabinets, some with hardware, formica, no backsplash, new carpet & vinyl – 10 units Upgrade - backsplash, stainless steel appliances, hardware on cabinets, white cabinets, resurfaced counter tops, new vinyl & carpet, full paint – 111 units Elite - matte black accents/hardware, hardsurface, back splash, farmers sink, stainless steel appliances, full paint, new carpet & vinyl – 2 units
B24: What Matters Most to Them? | C24: Broker is not sure but they are firm on the $40 million, had offers for less and didn't take them.
B25: Brokers Name | C25: Brett Polachek
B26: Brokerage | C26: Newmark
B27: Broker's Email | C27: Brett.Polachek@nmrk.com
B28: Broker's Phone Number | C28: 602-952-3833

Sheet Demos
B2: Demos | G2: Property Rating Scorecard
B5: CoStar Properties: Demographics | C5: 1 Mile | D5: 3 Mile | E5: 5 Mile | G5: Multifamily Rating Scale | H5: Figure | I5: Score | J5: Weighting | K5: Increments | L5: 10 | M5: 9 | N5: 8 | O5: 7 | P5: 6 | Q5: 5 | R5: 4
B6: Population | C6: 9393 | D6: 100969 | E6: 250903 | G6: Population | H6: =D6 -> 100969 | I6: =ifs(H6>=L6,$L$5,and(H6<L6,H6>=M6),$M$5,and(H6<M6,H6>=N6),$N$5,and(H6<N6,H6>=O6),$O$5,and(H6<O6,H6>=P6),$P$5,and(H6<P6,H6>=Q6),$Q$5,H6<Q6,$R$5) -> 10 | J6: 0.075 | K6: 5000 | L6: =M6+$K6 -> 70000 | M6: =N6+$K6 -> 65000 | N6: 60000 | O6: =N6-$K6 -> 55000 | P6: =O6-$K6 -> 50000 | Q6: =P6-$K6 -> 45000
B7: Population Growth | C7: -0.003 | D7: -0.003 | E7: -0.003 | G7: Population Growth | H7: =D7 -> -0.003 | I7: =ifs(H7>=L7,$L$5,and(H7<L7,H7>=M7),$M$5,and(H7<M7,H7>=N7),$N$5,and(H7<N7,H7>=O7),$O$5,and(H7<O7,H7>=P7),$P$5,and(H7<P7,H7>=Q7),$Q$5,H7<Q7,$R$5) -> 4 | J7: 0.1 | K7: 0.0025 | L7: =M7+$K7 -> 0.01 | M7: =N7+$K7 -> 0.0075 | N7: 0.005 | O7: =N7-$K7 -> 0.0025 | P7: =O7-$K7 -> 0 | Q7: =P7-$K7 -> -0.0025
B8: Median HH Income | C8: 75362 | D8: 80544 | E8: 84222 | G8: Median HH Income | H8: =D8 -> 80544 | I8: =ifs(H8>=L8,$L$5,and(H8<L8,H8>=M8),$M$5,and(H8<M8,H8>=N8),$N$5,and(H8<N8,H8>=O8),$O$5,and(H8<O8,H8>=P8),$P$5,and(H8<P8,H8>=Q8),$Q$5,H8<Q8,$R$5) -> 10 | J8: 0.1 | K8: 5000 | L8: =M8+$K8 -> 70000 | M8: =N8+$K8 -> 65000 | N8: 60000 | O8: =N8-$K8 -> 55000 | P8: =O8-$K8 -> 50000 | Q8: =P8-$K8 -> 45000
B9: Median Home Value | C9: 345268 | D9: 386764 | E9: 389488 | G9: Median Home Value | H9: =D9 -> 386764 | I9: =ifs(H9>=L9,$L$5,and(H9<L9,H9>=M9),$M$5,and(H9<M9,H9>=N9),$N$5,and(H9<N9,H9>=O9),$O$5,and(H9<O9,H9>=P9),$P$5,and(H9<P9,H9>=Q9),$Q$5,H9<Q9,$R$5) -> 7 | J9: 0.075 | K9: 50000 | L9: =M9+$K9 -> 525000 | M9: =N9+$K9 -> 475000 | N9: 425000 | O9: =N9-$K9 -> 375000 | P9: =O9-$K9 -> 325000 | Q9: =P9-$K9 -> 275000
B10: Renter Households % | C10: 0.43 | D10: 0.48 | E10: 0.43 | G10: Renter Households % | H10: =D10 -> 0.48 | I10: =ifs(H10>=L10,$L$5,and(H10<L10,H10>=M10),$M$5,and(H10<M10,H10>=N10),$N$5,and(H10<N10,H10>=O10),$O$5,and(H10<O10,H10>=P10),$P$5,and(H10<P10,H10>=Q10),$Q$5,H10<Q10,$R$5) -> 9 | J10: 0.05 | K10: 0.05 | L10: =M10+$K10 -> 0.5 | M10: =N10+$K10 -> 0.45 | N10: 0.4 | O10: =N10-$K10 -> 0.35 | P10: =O10-$K10 -> 0.3 | Q10: =P10-$K10 -> 0.25
B11: Best Places | C11: Zip Code | D11: National Average | G11: Violent Crime Rate | H11: =C12 -> 37.5 | I11: =ifs(H11<=L11,$L$5,and(H11>L11,H11<=M11),$M$5,and(H11>M11,H11<=N11),$N$5,and(H11>N11,H11<=O11),$O$5,and(H11>O11,H11<=P11),$P$5,and(H11>P11,H11<=Q11),$Q$5,H11>Q11,$R$5) -> 6 | J11: 0.05 | K11: 5 | L11: =M11-$K11 -> 20 | M11: =N11-$K11 -> 25 | N11: 30 | O11: =N11+$K11 -> 35 | P11: =O11+$K11 -> 40 | Q11: =P11+$K11 -> 45
B12: Violent Crime Rate | C12: 37.5 | D12: 22.7 | G12: Property Crime Rate | H12: =C13 -> 52.8 | I12: =ifs(H12<=L12,$L$5,and(H12>L12,H12<=M12),$M$5,and(H12>M12,H12<=N12),$N$5,and(H12>N12,H12<=O12),$O$5,and(H12>O12,H12<=P12),$P$5,and(H12>P12,H12<=Q12),$Q$5,H12>Q12,$R$5) -> 5 | J12: 0.05 | K12: 5 | L12: =M12-$K12 -> 30 | M12: =N12-$K12 -> 35 | N12: 40 | O12: =N12+$K12 -> 45 | P12: =O12+$K12 -> 50 | Q12: =P12+$K12 -> 55
B13: Property Crime Rate | C13: 52.8 | D13: 35.4 | G13: School Ratings | H13: =E15 -> 4 | I13: =ifs(H13>=L13,$L$5,and(H13<L13,H13>=M13),$M$5,and(H13<M13,H13>=N13),$N$5,and(H13<N13,H13>=O13),$O$5,and(H13<O13,H13>=P13),$P$5,and(H13<P13,H13>=Q13),$Q$5,H13<Q13,$R$5) -> 5 | J13: 0.075 | K13: 1 | L13: =M13+$K13 -> 9 | M13: =N13+$K13 -> 8 | N13: 7 | O13: =N13-$K13 -> 6 | P13: =O13-$K13 -> 5 | Q13: =P13-$K13 -> 4
B14: Great Schools | C14: Elementary | D14: High School | G14: Walk Score | H14: =C17 -> 43 | I14: =ifs(H14>=L14,$L$5,and(H14<L14,H14>=M14),$M$5,and(H14<M14,H14>=N14),$N$5,and(H14<N14,H14>=O14),$O$5,and(H14<O14,H14>=P14),$P$5,and(H14<P14,H14>=Q14),$Q$5,H14<Q14,$R$5) -> 6 | J14: 0.075 | K14: 10 | L14: =M14+$K$14 -> 80 | M14: =N14+$K$14 -> 70 | N14: 60 | O14: =N14-$K$14 -> 50 | P14: =O14-$K$14 -> 40 | Q14: =P14-$K$14 -> 30
B15: School Ratings | C15: 4 | D15: 4 | E15: =iferror(average(C15:D15),"") -> 4 | G15: Transit Score | H15: =C18 -> 38 | I15: =ifs(H15>=L15,$L$5,and(H15<L15,H15>=M15),$M$5,and(H15<M15,H15>=N15),$N$5,and(H15<N15,H15>=O15),$O$5,and(H15<O15,H15>=P15),$P$5,and(H15<P15,H15>=Q15),$Q$5,H15<Q15,$R$5) -> 5 | J15: 0.075 | K15: 10 | L15: =M15+$K$15 -> 80 | M15: =N15+$K$15 -> 70 | N15: 60 | O15: =N15-$K$15 -> 50 | P15: =O15-$K$15 -> 40 | Q15: =P15-$K$15 -> 30
B16: CoStar Properties: Summary | G16: Submarket Vacancy | H16: =C20 -> 0.086 | I16: =ifs(H16<=L16,$L$5,and(H16>L16,H16<=M16),$M$5,and(H16>M16,H16<=N16),$N$5,and(H16>N16,H16<=O16),$O$5,and(H16>O16,H16<=P16),$P$5,and(H16>P16,H16<=Q16),$Q$5,H16>Q16,$R$5) -> 7 | J16: 0.1 | K16: 0.01 | L16: =M16-$K$16 -> 0.06 | M16: =N16-$K$16 -> 0.07 | N16: 0.08 | O16: =N16+$K$16 -> 0.09 | P16: =O16+$K$16 -> 0.1 | Q16: =P16+$K$16 -> 0.11
B17: Walk Score | C17: 43 | G17: Submarket Delivered % of Inventory | H17: =C23 -> 0.034245928 | I17: =ifs(H17<=L17,$L$5,and(H17>L17,H17<=M17),$M$5,and(H17>M17,H17<=N17),$N$5,and(H17>N17,H17<=O17),$O$5,and(H17>O17,H17<=P17),$P$5,and(H17>P17,H17<=Q17),$Q$5,H17>Q17,$R$5) -> 8 | J17: 0.1 | K17: 0.005 | L17: =M17-$K$17 -> 0.025 | M17: =N17-$K$17 -> 0.03 | N17: 0.035 | O17: =N17+$K17 -> 0.04 | P17: =O17+$K17 -> 0.045 | Q17: =P17+$K17 -> 0.05
B18: Transit Score | C18: 38 | G18: Submarket Construction % of Inventory | H18: =C25 -> 0.015973032 | I18: =ifs(H18<=L18,$L$5,and(H18>L18,H18<=M18),$M$5,and(H18>M18,H18<=N18),$N$5,and(H18>N18,H18<=O18),$O$5,and(H18>O18,H18<=P18),$P$5,and(H18>P18,H18<=Q18),$Q$5,H18>Q18,$R$5) -> 10 | J18: 0.075 | K18: 0.005 | L18: =M18-$K$18 -> 0.025 | M18: =N18-$K$18 -> 0.03 | N18: 0.035 | O18: =N18+$K18 -> 0.04 | P18: =O18+$K18 -> 0.045 | Q18: =P18+$K18 -> 0.05
B19: CoStar Properties: Analytics - Submarket | G19: Total | I19: =sumproduct(I6:I18,J6:J18) -> 7.125 | J19: =sum(J6:J18) -> 1
B20: Submarket Vacancy | C20: 0.086 | G20: Property Rating Decision | H20: =ifs(I19>=H22,G22,and(I19<H22,I19>=H23),G23,I19<H23,G24) -> Move Forward
B21: Submarket Inventory Units | C21: 31741
B22: Submarket 12 Mo Delivered Units | C22: 1087 | G22: Move Forward | H22: 7
B23: Submarket Delivered % of Inventory | C23: =iferror(C22/C21,"") -> 0.034245928 | G23: Quick Check with Team | H23: 5.5
B24: Submarket Under Construction Units | C24: 507 | G24: Don't Move Forward
B25: Submarket Construction % of Inventory | C25: =iferror(C24/C21,"") -> 0.015973032
B26: Submarket Cap Rate | C26: 0.047
B27: Submarket Sale Price / Unit | C27: 233000
B28: CoStar Properties: Analytics - Market
B29: Market Vacancy | C29: 0.115
B30: Market Inventory Units | C30: 408282
B31: Market 12 Mo Delivered Units | C31: 2450
B32: Market Delivered % of Inventory | C32: =iferror(C31/C30,"") -> 0.0060007544
B33: Market Under Construction Units | C33: 27188
B34: Market Construction % of Inventory | C34: =iferror(C33/C30,"") -> 0.066591229
B35: Market Cap Rate | C35: 0.049
B36: Market Sale Price / Unit | C36: 263000

Sheet Text Overview

Sheet Historical Financials
H2: Historical Financials
B3: ='Property Summary'!B3 -> Phoenix, AZ | H3: ='Property Summary'!I3 -> Wind River Group
B5: Total Units | C5: ='Unit Mix & Comps'!D34 -> 184
B6: Occupied Units | C6: ='Unit Mix & Comps'!E34 -> 169
B7: Occupancy % | C7: ='Unit Mix & Comps'!E35 -> 0.91847826
B9: Rental Income | C9: Trailing 12 | D9: Per Unit | E9: Trailing 6 | F9: Per Unit | G9: Trailing 3 | H9: Per Unit
B10: Potential Rental Income | C10: 3425241 | D10: =iferror(C10/$C$5,"") -> 18615.44 | E10: 0 | F10: =iferror(E10/$C$5,"") -> 0 | G10: 0 | H10: =iferror(G10/$C$5,"") -> 0
B11: Loss to Lease | C11: -246212 | D11: =iferror(-C11/C$10,"") -> 0.071881657 | E11: 0 | F11: =iferror(-E11/E$10,"") | G11: 0 | H11: =iferror(-G11/G$10,"")
A12: - | B12: Vacancy Loss | C12: -255589.29 | D12: =iferror(-C12/sum(C$10:C$11),"") -> 0.08039854 | E12: 0 | F12: =iferror(-E12/sum(E$10:E$11),"") | G12: 0 | H12: =iferror(-G12/sum(G$10:G$11),"")
A13: - | B13: Bad Debt Expense | C13: -42218.63 | D13: =iferror(-C13/sum(C$10:C$12),"") -> 0.014441423 | E13: 0 | F13: =iferror(-E13/sum(E$10:E$12),"") | G13: 0 | H13: =iferror(-G13/sum(G$10:G$12),"")
A14: - | B14: Concessions | C14: -53858.32 | D14: =iferror(-C14/sum(C$10:C$12),"") -> 0.018422928 | E14: 0 | F14: =iferror(-E14/sum(E$10:E$12),"") | G14: 0 | H14: =iferror(-G14/sum(G$10:G$12),"")
B15: Total Rental Income | C15: =sum(C10:C14) -> 2827362.8 | D15: =iferror(C15/$C$5,"") -> 15366.102 | E15: =sum(E10:E14) -> 0 | F15: =iferror(E15/$C$5,"") -> 0 | G15: =sum(G10:G14) -> 0 | H15: =iferror(G15/$C$5,"") -> 0
B16: Total RUBS Income | C16: 184233.56 | D16: =iferror(C16/$C$5,"") -> 1001.2693 | E16: 0 | F16: =iferror(E16/$C$5,"") -> 0 | G16: 0 | H16: =iferror(G16/$C$5,"") -> 0
B17: Total Other Income | C17: =508261.79-C16+1921.68+6459.85+11499.37+57275.42 -> 401184.55 | D17: =iferror(C17/$C$5,"") -> 2180.3508 | E17: 0 | F17: =iferror(E17/$C$5,"") -> 0 | G17: 0 | H17: =iferror(G17/$C$5,"") -> 0
B18: Total Revenue | C18: =sum(C15:C17) -> 3412780.9 | D18: =iferror(C18/$C$5,"") -> 18547.722 | E18: =sum(E15:E17) -> 0 | F18: =iferror(E18/$C$5,"") -> 0 | G18: =sum(G15:G17) -> 0 | H18: =iferror(G18/$C$5,"") -> 0
B20: Operating Expenses
B21: Total General & Admin | C21: 126768.37 | D21: =iferror(C21/$C$5,"") -> 688.95853 | E21: 0 | F21: =iferror(E21/$C$5,"") -> 0 | G21: 0 | H21: =iferror(G21/$C$5,"") -> 0
B22: Total Payroll | C22: 324615.54 | D22: =iferror(C22/$C$5,"") -> 1764.2149 | E22: 0 | F22: =iferror(E22/$C$5,"") -> 0 | G22: 0 | H22: =iferror(G22/$C$5,"") -> 0
B23: Total Leasing & Marketing | C23: 86807.36 | D23: =iferror(C23/$C$5,"") -> 471.77913 | E23: 0 | F23: =iferror(E23/$C$5,"") -> 0 | G23: 0 | H23: =iferror(G23/$C$5,"") -> 0
B24: Total Utilities | C24: 262578.11 | D24: =iferror(C24/$C$5,"") -> 1427.0549 | E24: 0 | F24: =iferror(E24/$C$5,"") -> 0 | G24: 0 | H24: =iferror(G24/$C$5,"") -> 0
B25: Total Repairs & Maintenance | C25: 55342.64 | D25: =iferror(C25/$C$5,"") -> 300.77522 | E25: 0 | F25: =iferror(E25/$C$5,"") -> 0 | G25: 0 | H25: =iferror(G25/$C$5,"") -> 0
B26: Total HOA Assessments | C26: 20329.82 | D26: =iferror(C26/$C$5,"") -> 110.48815 | E26: 0 | F26: =iferror(E26/$C$5,"") -> 0 | G26: 0 | H26: =iferror(G26/$C$5,"") -> 0
B27: Total Turnover Expense | C27: 22404.11 | D27: =iferror(C27/$C$5,"") -> 121.76147 | E27: 0 | F27: =iferror(E27/$C$5,"") -> 0 | G27: 0 | H27: =iferror(G27/$C$5,"") -> 0
B28: Total Contract Services | C28: =101374.9-55342.64 -> 46032.26 | D28: =iferror(C28/$C$5,"") -> 250.17533 | E28: 0 | F28: =iferror(E28/$C$5,"") -> 0 | G28: 0 | H28: =iferror(G28/$C$5,"") -> 0
B29: Total Insurance Expense | C29: 53468.94 | D29: =iferror(C29/$C$5,"") -> 290.59207 | E29: 0 | F29: =iferror(E29/$C$5,"") -> 0 | G29: 0 | H29: =iferror(G29/$C$5,"") -> 0
B30: Total Property Taxes | C30: 142164.14 | D30: =iferror(C30/$C$5,"") -> 772.6312 | E30: 0 | F30: =iferror(E30/$C$5,"") -> 0 | G30: 0 | H30: =iferror(G30/$C$5,"") -> 0
B31: Total Management Fees | C31: 104943.81 | D31: =iferror(C31/C18,"") -> 0.030750234 | E31: 0 | F31: =iferror(E31/$C$5,"") -> 0 | G31: 0 | H31: =iferror(G31/$C$5,"") -> 0
B32: Total Operating Expenses | C32: =sum(C21:C31) -> 1245455.1 | D32: =iferror(C32/$C$5,"") -> 6768.7777 | E32: =sum(E21:E31) -> 0 | F32: =iferror(E32/$C$5,"") -> 0 | G32: =sum(G21:G31) -> 0 | H32: =iferror(G32/$C$5,"") -> 0
B33: Expense Ratio | C33: =iferror(C32/C18,"") -> 0.36493849 | E33: =iferror(E32/E18,"") | G33: =iferror(G32/G18,"")
B35: Net Operating Income | C35: =C18-C32 -> 2167325.8 | D35: =iferror(C35/$C$5,"") -> 11778.944 | E35: =E18-E32 -> 0 | F35: =iferror(E35/$C$5,"") -> 0 | G35: =G18-G32 -> 0 | H35: =iferror(G35/$C$5,"") -> 0

Sheet Unit Mix & Comps
R2: Unit Mix | V2: Competitor Rate Analysis | AP2: Competitor Analysis
B3: ='Property Summary'!B3 -> Phoenix, AZ | R3: ='Property Summary'!I3 -> Wind River Group
B4: Rent Roll 2.10.25 | L4: Full Comps
H5: Current | I5: Gap in | J5: Average | L5: Market Average | O5: Market High | T5: Quick Look | Y5: =AP7 -> Allure at Tempe | AA5: =AP8 -> Carlyle at South Mtn | AC5: =AP9 -> Pointe at South Mtn | AE5: =AP10 -> Vista Sureno | AG5: =AP11 -> Strada Apartments | AI5: =AP12 -> Lore South Mtn | AK5: =AP13 -> Array South Mtn | AM5: =AP14 -> 505 West Apts. | AP5: Link property names to property websites
B6: Unit Mix | C6: Square Footage | D6: Units | E6: Occupied Units | F6: Renovation Units | G6: Unit Mix Percentage | H6: Advertised Rent | I6: Advertised to Achieved | J6: Achieved Rent | K6: Current Price Per SF | L6: Asking Rent | M6: Market Price Per SF | N6: Current - Market Price Per SF | O6: Asking Rent | P6: Renovated Rent | Q6: Renovated Rent Premium | R6: Premium % | T6: Market Rents | V6: Market Average SF | W6: Market Avg Rent | X6: Market Avg Price Per SF | Y6: =AQ7 -> 1.0 miles | Z6: Sqft | AA6: =AQ8 -> 1.5 | AB6: Sqft | AC6: =AQ9 -> 1.5 | AD6: Sqft | AE6: =AQ10 -> 1.3 | AF6: Sqft | AG6: =AQ11 -> 1.9 | AH6: Sqft | AI6: =AQ12 -> 1.4 | AJ6: Sqft | AK6: =AQ13 -> 1.5 | AL6: Sqft | AM6: =AQ14 -> 3.8 | AN6: Sqft | AP6: Property Name | AQ6: Distance | AR6: Year Built | AS6: Year Renovated | AT6: Units | AU6: Occupancy | AV6: Google Review Rating | AW6: Finish / Amenities / Condition
B7: 1 Bed- Classic | C7: 678 | D7: 16 | E7: 16 | F7: 10 | G7: =IFERROR(D7/$D$34,"") -> 0.086956522 | H7: 1245 | I7: =iferror((H7-J7)/H7,"") -> 0.11566265 | J7: 1101 | K7: =iferror(J7/$C7,"") -> 1.6238938 | L7: =ifs($L$4="Full Comps",W7,$L$4="Quick Look",T7) -> 1295 | M7: =iferror(if($L$4="Quick Look",L7/C7,X7),"") -> 1.9444444 | N7: =iferror(if(M7="","",(K7-M7)/K7),"") -> -0.19739631 | O7: 1357 | P7: =Q7+J7 -> 1325 | Q7: 224 | R7: =iferror(Q7/J7,"") -> 0.20345141 | T7: 1323 | V7: =iferror(AVERAGE(Z7,AB7,AD7,AF7,AH7,AJ7,AL7,AN7),"") -> 666 | W7: =iferror(average(Y7,AA7,AC7,AE7,AG7,AI7,AK7,AM7),"") -> 1295 | X7: =iferror(W7/V7,"") -> 1.9444444 | AG7: 1233 | AH7: 600 | AK7: 1357 | AL7: 732 | AP7: Allure at Tempe | AQ7: 1.0 miles | AR7: 1995 | AT7: 216 | AU7: 0.903 | AW7: Similar finish
B8: 1 Bed PU | C8: 678 | D8: 2 | E8: 1 | G8: =IFERROR(D8/$D$34,"") -> 0.010869565 | H8: 1430 | I8: =iferror((H8-J8)/H8,"") -> 0.083916084 | J8: 1310 | K8: =iferror(J8/$C8,"") -> 1.9321534 | L8: =ifs($L$4="Full Comps",W8,$L$4="Quick Look",T8) -> 1295 | M8: =iferror(if($L$4="Quick Look",L8/C8,X8),"") -> 1.9444444 | N8: =iferror(if(M8="","",(K8-M8)/K8),"") -> -0.0063613232 | P8: =Q8+J8 -> 1310 | R8: =iferror(Q8/J8,"") -> 0 | T8: 1323 | V8: =iferror(AVERAGE(Z8,AB8,AD8,AF8,AH8,AJ8,AL8,AN8),"") -> 666 | W8: =iferror(average(Y8,AA8,AC8,AE8,AG8,AI8,AK8,AM8),"") -> 1295 | X8: =iferror(W8/V8,"") -> 1.9444444 | AG8: 1233 | AH8: 600 | AK8: 1357 | AL8: 732 | AP8: Carlyle at South Mtn | AQ8: 1.5 | AR8: 1995 | AT8: 360 | AU8: 0.865
B9: 1 Bed U | C9: 678 | D9: 30 | E9: 29 | G9: =IFERROR(D9/$D$34,"") -> 0.16304348 | H9: 1422.76 | I9: =iferror((H9-J9)/H9,"") -> 0.1070806 | J9: 1270.41 | K9: =iferror(J9/$C9,"") -> 1.8737611 | L9: =ifs($L$4="Full Comps",W9,$L$4="Quick Look",T9) -> 1295 | M9: =iferror(if($L$4="Quick Look",L9/C9,X9),"") -> 1.9444444 | N9: =iferror(if(M9="","",(K9-M9)/K9),"") -> -0.03772273 | P9: =Q9+J9 -> 1270.41 | R9: =iferror(Q9/J9,"") -> 0 | T9: 1323 | V9: =iferror(AVERAGE(Z9,AB9,AD9,AF9,AH9,AJ9,AL9,AN9),"") -> 666 | W9: =iferror(average(Y9,AA9,AC9,AE9,AG9,AI9,AK9,AM9),"") -> 1295 | X9: =iferror(W9/V9,"") -> 1.9444444 | AG9: 1233 | AH9: 600 | AK9: 1357 | AL9: 732 | AP9: Pointe at South Mtn | AQ9: 1.5 | AR9: 1988 | AT9: 364 | AU9: 0.945
B10: 1 Bed Classic | C10: 734 | D10: 9 | E10: 9 | F10: 9 | G10: =IFERROR(D10/$D$34,"") -> 0.048913043 | H10: 1373.89 | I10: =iferror((H10-J10)/H10,"") -> 0.10150012 | J10: 1234.44 | K10: =iferror(J10/$C10,"") -> 1.6817984 | L10: =ifs($L$4="Full Comps",W10,$L$4="Quick Look",T10) -> 1305.2 | M10: =iferror(if($L$4="Quick Look",L10/C10,X10),"") -> 1.789416 | N10: =iferror(if(M10="","",(K10-M10)/K10),"") -> -0.063989593 | O10: 1389 | P10: =Q10+J10 -> 1385.44 | Q10: 151 | R10: =iferror(Q10/J10,"") -> 0.12232267 | T10: 1323 | V10: =iferror(AVERAGE(Z10,AB10,AD10,AF10,AH10,AJ10,AL10,AN10),"") -> 729.4 | W10: =iferror(average(Y10,AA10,AC10,AE10,AG10,AI10,AK10,AM10),"") -> 1305.2 | X10: =iferror(W10/V10,"") -> 1.789416 | AE10: 1328 | AF10: 740 | AG10: 1304 | AH10: 700 | AI10: 1319 | AJ10: 730 | AK10: 1389 | AL10: 757 | AM10: 1186 | AN10: 720 | AP10: Vista Sureno | AQ10: 1.3 | AR10: 1985 | AT10: 186 | AU10: 0.944
B11: 1 Bed PU | C11: 734 | D11: 1 | E11: 1 | G11: =IFERROR(D11/$D$34,"") -> 0.0054347826 | H11: 1480 | I11: =iferror((H11-J11)/H11,"") -> -0.23783784 | J11: 1832 | K11: =iferror(J11/$C11,"") -> 2.4959128 | L11: =ifs($L$4="Full Comps",W11,$L$4="Quick Look",T11) | M11: =iferror(if($L$4="Quick Look",L11/C11,X11),"") | N11: =iferror(if(M11="","",(K11-M11)/K11),"") | P11: =Q11+J11 -> 1832 | R11: =iferror(Q11/J11,"") -> 0 | T11: 1323 | V11: =iferror(AVERAGE(Z11,AB11,AD11,AF11,AH11,AJ11,AL11,AN11),"") | W11: =iferror(average(Y11,AA11,AC11,AE11,AG11,AI11,AK11,AM11),"") | X11: =iferror(W11/V11,"") | AP11: Strada Apartments | AQ11: 1.9 | AR11: 1987 | AT11: 495 | AU11: 0.945
B12: 1 Bed U | C12: 734 | D12: 14 | E12: 13 | G12: =IFERROR(D12/$D$34,"") -> 0.076086957 | H12: 1488.46 | I12: =iferror((H12-J12)/H12,"") -> 0.074781989 | J12: 1377.15 | K12: =iferror(J12/$C12,"") -> 1.8762262 | L12: =ifs($L$4="Full Comps",W12,$L$4="Quick Look",T12) | M12: =iferror(if($L$4="Quick Look",L12/C12,X12),"") | N12: =iferror(if(M12="","",(K12-M12)/K12),"") | P12: =Q12+J12 -> 1377.15 | R12: =iferror(Q12/J12,"") -> 0 | T12: 1323 | V12: =iferror(AVERAGE(Z12,AB12,AD12,AF12,AH12,AJ12,AL12,AN12),"") | W12: =iferror(average(Y12,AA12,AC12,AE12,AG12,AI12,AK12,AM12),"") | X12: =iferror(W12/V12,"") | AP12: Lore South Mtn | AQ12: 1.4 | AR12: 1987 | AT12: 242 | AU12: 0.905
B13: 1 Bed C | C13: 771 | D13: 13 | E13: 12 | F13: 10 | G13: =IFERROR(D13/$D$34,"") -> 0.070652174 | H13: 1377.92 | I13: =iferror((H13-J13)/H13,"") -> 0.079590978 | J13: 1268.25 | K13: =iferror(J13/$C13,"") -> 1.6449416 | L13: =ifs($L$4="Full Comps",W13,$L$4="Quick Look",T13) -> 1357.3333 | M13: =iferror(if($L$4="Quick Look",L13/C13,X13),"") -> 1.7239627 | N13: =iferror(if(M13="","",(K13-M13)/K13),"") -> -0.048038853 | P13: =Q13+J13 -> 1400.25 | Q13: 132 | R13: =iferror(Q13/J13,"") -> 0.10408043 | T13: 1323 | V13: =iferror(AVERAGE(Z13,AB13,AD13,AF13,AH13,AJ13,AL13,AN13),"") -> 787.33333 | W13: =iferror(average(Y13,AA13,AC13,AE13,AG13,AI13,AK13,AM13),"") -> 1357.3333 | X13: =iferror(W13/V13,"") -> 1.7239627 | AA13: 1403 | AB13: 786 | AC13: 1347 | AD13: 751 | AG13: 1322 | AH13: 825 | AP13: Array South Mtn | AQ13: 1.5 | AR13: 1991 | AT13: 600 | AU13: 0.897
B14: 1 Bed PU | C14: 771 | D14: 1 | E14: 1 | G14: =IFERROR(D14/$D$34,"") -> 0.0054347826 | H14: 1485 | I14: =iferror((H14-J14)/H14,"") -> 0.05993266 | J14: 1396 | K14: =iferror(J14/$C14,"") -> 1.8106355 | L14: =ifs($L$4="Full Comps",W14,$L$4="Quick Look",T14) | M14: =iferror(if($L$4="Quick Look",L14/C14,X14),"") | N14: =iferror(if(M14="","",(K14-M14)/K14),"") | P14: =Q14+J14 -> 1396 | R14: =iferror(Q14/J14,"") -> 0 | T14: 1323 | V14: =iferror(AVERAGE(Z14,AB14,AD14,AF14,AH14,AJ14,AL14,AN14),"") | W14: =iferror(average(Y14,AA14,AC14,AE14,AG14,AI14,AK14,AM14),"") | X14: =iferror(W14/V14,"") | AP14: 505 West Apts. | AQ14: 3.8 | AR14: 1981 | AT14: 334 | AU14: 0.955
B15: 1 Bed U | C15: 771 | D15: 9 | E15: 9 | G15: =IFERROR(D15/$D$34,"") -> 0.048913043 | H15: 1513.33 | I15: =iferror((H15-J15)/H15,"") -> 0.083550845 | J15: 1386.89 | K15: =iferror(J15/$C15,"") -> 1.7988197 | L15: =ifs($L$4="Full Comps",W15,$L$4="Quick Look",T15) | M15: =iferror(if($L$4="Quick Look",L15/C15,X15),"") | N15: =iferror(if(M15="","",(K15-M15)/K15),"") | P15: =Q15+J15 -> 1386.89 | R15: =iferror(Q15/J15,"") -> 0 | T15: 1323 | V15: =iferror(AVERAGE(Z15,AB15,AD15,AF15,AH15,AJ15,AL15,AN15),"") | W15: =iferror(average(Y15,AA15,AC15,AE15,AG15,AI15,AK15,AM15),"") | X15: =iferror(W15/V15,"") | AP15: Average | AQ15: =iferror(average(AQ7:AQ14),"") -> 1.8428571 | AR15: =iferror(average(AR7:AR14),"") -> 1988.625 | AS15: =iferror(average(AS7:AS14),"") | AT15: =iferror(average(AT7:AT14),"") -> 349.625 | AU15: =iferror(average(AU7:AU14),"") -> 0.919875 | AV15: =iferror(average(AV7:AV14),"")
B16: 2B / 1B -C | C16: 863 | D16: 9 | E16: 9 | F16: 10 | G16: =IFERROR(D16/$D$34,"") -> 0.048913043 | H16: 1514 | I16: =iferror((H16-J16)/H16,"") -> 0.18949141 | J16: 1227.11 | K16: =iferror(J16/$C16,"") -> 1.4219119 | L16: =ifs($L$4="Full Comps",W16,$L$4="Quick Look",T16) -> 1417 | M16: =iferror(if($L$4="Quick Look",L16/C16,X16),"") -> 1.6749409 | N16: =iferror(if(M16="","",(K16-M16)/K16),"") -> -0.17794981 | O16: 1417 | P16: =Q16+J16 -> 1475.11 | Q16: 248 | R16: =iferror(Q16/J16,"") -> 0.20210087 | T16: 1553 | V16: =iferror(AVERAGE(Z16,AB16,AD16,AF16,AH16,AJ16,AL16,AN16),"") -> 846 | W16: =iferror(average(Y16,AA16,AC16,AE16,AG16,AI16,AK16,AM16),"") -> 1417 | X16: =iferror(W16/V16,"") -> 1.6749409 | AM16: 1417 | AN16: 846
B17: 2B / 1B -E | C17: 863 | D17: 1 | E17: 1 | G17: =IFERROR(D17/$D$34,"") -> 0.0054347826 | H17: 1654 | I17: =iferror((H17-J17)/H17,"") -> 0.066505441 | J17: 1544 | K17: =iferror(J17/$C17,"") -> 1.7891078 | L17: =ifs($L$4="Full Comps",W17,$L$4="Quick Look",T17) | M17: =iferror(if($L$4="Quick Look",L17/C17,X17),"") | N17: =iferror(if(M17="","",(K17-M17)/K17),"") | P17: =Q17+J17 -> 1544 | R17: =iferror(Q17/J17,"") -> 0 | T17: 1553 | V17: =iferror(AVERAGE(Z17,AB17,AD17,AF17,AH17,AJ17,AL17,AN17),"") | W17: =iferror(average(Y17,AA17,AC17,AE17,AG17,AI17,AK17,AM17),"") | X17: =iferror(W17/V17,"")
B18: 2B / 1B -U | C18: 863 | D18: 14 | E18: 13 | G18: =IFERROR(D18/$D$34,"") -> 0.076086957 | H18: 1629 | I18: =iferror((H18-J18)/H18,"") -> 0.09704113 | J18: 1470.92 | K18: =iferror(J18/$C18,"") -> 1.7044264 | L18: =ifs($L$4="Full Comps",W18,$L$4="Quick Look",T18) | M18: =iferror(if($L$4="Quick Look",L18/C18,X18),"") | N18: =iferror(if(M18="","",(K18-M18)/K18),"") | P18: =Q18+J18 -> 1470.92 | R18: =iferror(Q18/J18,"") -> 0 | T18: 1553 | V18: =iferror(AVERAGE(Z18,AB18,AD18,AF18,AH18,AJ18,AL18,AN18),"") | W18: =iferror(average(Y18,AA18,AC18,AE18,AG18,AI18,AK18,AM18),"") | X18: =iferror(W18/V18,"")
B19: 2B/ 2B- C | C19: 958 | D19: 4 | E19: 4 | G19: =IFERROR(D19/$D$34,"") -> 0.02173913 | H19: 1611.75 | I19: =iferror((H19-J19)/H19,"") -> 0.026058632 | J19: 1569.75 | K19: =iferror(J19/$C19,"") -> 1.6385699 | L19: =ifs($L$4="Full Comps",W19,$L$4="Quick Look",T19) -> 1535.8571 | M19: =iferror(if($L$4="Quick Look",L19/C19,X19),"") -> 1.5683443 | N19: =iferror(if(M19="","",(K19-M19)/K19),"") -> 0.042857898 | O19: 1650 | P19: =Q19+J19 -> 1569.75 | R19: =iferror(Q19/J19,"") -> 0 | T19: 1553 | V19: =iferror(AVERAGE(Z19,AB19,AD19,AF19,AH19,AJ19,AL19,AN19),"") -> 979.28571 | W19: =iferror(average(Y19,AA19,AC19,AE19,AG19,AI19,AK19,AM19),"") -> 1535.8571 | X19: =iferror(W19/V19,"") -> 1.5683443 | Y19: 1554 | Z19: 948 | AC19: 1613 | AD19: 983 | AE19: 1556 | AF19: 924 | AG19: 1546 | AH19: 1010 | AI19: 1398 | AJ19: 960 | AK19: 1582 | AL19: 1024 | AM19: 1502 | AN19: 1006
B20: 2B/ 2B- PU | C20: 958 | D20: 3 | E20: 3 | G20: =IFERROR(D20/$D$34,"") -> 0.016304348 | H20: 1764.67 | I20: =iferror((H20-J20)/H20,"") -> 0.2079709 | J20: 1397.67 | K20: =iferror(J20/$C20,"") -> 1.4589457 | L20: =ifs($L$4="Full Comps",W20,$L$4="Quick Look",T20) | M20: =iferror(if($L$4="Quick Look",L20/C20,X20),"") | N20: =iferror(if(M20="","",(K20-M20)/K20),"") | P20: =Q20+J20 -> 1397.67 | R20: =iferror(Q20/J20,"") -> 0 | T20: 1553 | V20: =iferror(AVERAGE(Z20,AB20,AD20,AF20,AH20,AJ20,AL20,AN20),"") | W20: =iferror(average(Y20,AA20,AC20,AE20,AG20,AI20,AK20,AM20),"") | X20: =iferror(W20/V20,"")
B21: 2B/ 2B- U | C21: 958 | D21: 9 | E21: 6 | G21: =IFERROR(D21/$D$34,"") -> 0.048913043 | H21: 1753.56 | I21: =iferror((H21-J21)/H21,"") -> 0.097932206 | J21: 1581.83 | K21: =iferror(J21/$C21,"") -> 1.6511795 | L21: =ifs($L$4="Full Comps",W21,$L$4="Quick Look",T21) | M21: =iferror(if($L$4="Quick Look",L21/C21,X21),"") | N21: =iferror(if(M21="","",(K21-M21)/K21),"") | P21: =Q21+J21 -> 1581.83 | R21: =iferror(Q21/J21,"") -> 0 | T21: 1553 | V21: =iferror(AVERAGE(Z21,AB21,AD21,AF21,AH21,AJ21,AL21,AN21),"") | W21: =iferror(average(Y21,AA21,AC21,AE21,AG21,AI21,AK21,AM21),"") | X21: =iferror(W21/V21,"")
B22: 2B/2B C | C22: 1000 | D22: 7 | E22: 7 | F22: 7 | G22: =IFERROR(D22/$D$34,"") -> 0.038043478 | H22: 1679.29 | I22: =iferror((H22-J22)/H22,"") -> 0.15432117 | J22: 1420.14 | K22: =iferror(J22/$C22,"") -> 1.42014 | L22: =ifs($L$4="Full Comps",W22,$L$4="Quick Look",T22) -> 1630.6667 | M22: =iferror(if($L$4="Quick Look",L22/C22,X22),"") -> 1.5345044 | N22: =iferror(if(M22="","",(K22-M22)/K22),"") -> -0.080530364 | O22: 1671 | P22: =Q22+J22 -> 1650.14 | Q22: 230 | R22: =iferror(Q22/J22,"") -> 0.16195586 | T22: 1553 | V22: =iferror(AVERAGE(Z22,AB22,AD22,AF22,AH22,AJ22,AL22,AN22),"") -> 1062.6667 | W22: =iferror(average(Y22,AA22,AC22,AE22,AG22,AI22,AK22,AM22),"") -> 1630.6667 | X22: =iferror(W22/V22,"") -> 1.5345044 | AA22: 1630 | AB22: 1068 | AG22: 1671 | AH22: 1076 | AK22: 1591 | AL22: 1044
B23: 2B/ 2B- PU | C23: 1000 | D23: 3 | E23: 3 | G23: =IFERROR(D23/$D$34,"") -> 0.016304348 | H23: 1788.33 | I23: =iferror((H23-J23)/H23,"") -> 0.11761252 | J23: 1578 | K23: =iferror(J23/$C23,"") -> 1.578 | L23: =ifs($L$4="Full Comps",W23,$L$4="Quick Look",T23) | M23: =iferror(if($L$4="Quick Look",L23/C23,X23),"") | N23: =iferror(if(M23="","",(K23-M23)/K23),"") | P23: =Q23+J23 -> 1578 | R23: =iferror(Q23/J23,"") -> 0 | T23: 1553 | V23: =iferror(AVERAGE(Z23,AB23,AD23,AF23,AH23,AJ23,AL23,AN23),"") | W23: =iferror(average(Y23,AA23,AC23,AE23,AG23,AI23,AK23,AM23),"") | X23: =iferror(W23/V23,"")
B24: 2B/ 2B- U | C24: 1000 | D24: 22 | E24: 18 | G24: =IFERROR(D24/$D$34,"") -> 0.11956522 | H24: 1803.18 | I24: =iferror((H24-J24)/H24,"") -> 0.10608481 | J24: 1611.89 | K24: =iferror(J24/$C24,"") -> 1.61189 | L24: =ifs($L$4="Full Comps",W24,$L$4="Quick Look",T24) | M24: =iferror(if($L$4="Quick Look",L24/C24,X24),"") | N24: =iferror(if(M24="","",(K24-M24)/K24),"") | P24: =Q24+J24 -> 1611.89 | R24: =iferror(Q24/J24,"") -> 0 | T24: 1553 | V24: =iferror(AVERAGE(Z24,AB24,AD24,AF24,AH24,AJ24,AL24,AN24),"") | W24: =iferror(average(Y24,AA24,AC24,AE24,AG24,AI24,AK24,AM24),"") | X24: =iferror(W24/V24,"")
B25: 2B/2B C | C25: 1040 | D25: 3 | E25: 3 | F25: 3 | G25: =IFERROR(D25/$D$34,"") -> 0.016304348 | H25: 1696 | I25: =iferror((H25-J25)/H25,"") -> 0.14091981 | J25: 1457 | K25: =iferror(J25/$C25,"") -> 1.4009615 | L25: =ifs($L$4="Full Comps",W25,$L$4="Quick Look",T25) | M25: =iferror(if($L$4="Quick Look",L25/C25,X25),"") | N25: =iferror(if(M25="","",(K25-M25)/K25),"") | P25: =Q25+J25 -> 1655 | Q25: 198 | R25: =iferror(Q25/J25,"") -> 0.13589568 | T25: 1553 | V25: =iferror(AVERAGE(Z25,AB25,AD25,AF25,AH25,AJ25,AL25,AN25),"") | W25: =iferror(average(Y25,AA25,AC25,AE25,AG25,AI25,AK25,AM25),"") | X25: =iferror(W25/V25,"")
B26: 2B/ 2B- PU | C26: 1040 | D26: 1 | E26: 1 | G26: =IFERROR(D26/$D$34,"") -> 0.0054347826 | H26: 1829 | I26: =iferror((H26-J26)/H26,"") -> 0.13395298 | J26: 1584 | K26: =iferror(J26/$C26,"") -> 1.5230769 | L26: =ifs($L$4="Full Comps",W26,$L$4="Quick Look",T26) | M26: =iferror(if($L$4="Quick Look",L26/C26,X26),"") | N26: =iferror(if(M26="","",(K26-M26)/K26),"") | P26: =Q26+J26 -> 1584 | R26: =iferror(Q26/J26,"") -> 0 | T26: 1553 | V26: =iferror(AVERAGE(Z26,AB26,AD26,AF26,AH26,AJ26,AL26,AN26),"") | W26: =iferror(average(Y26,AA26,AC26,AE26,AG26,AI26,AK26,AM26),"") | X26: =iferror(W26/V26,"")
B27: 2B/ 2B- U | C27: 1040 | D27: 13 | E27: 10 | G27: =IFERROR(D27/$D$34,"") -> 0.070652174 | H27: 1825.15 | I27: =iferror((H27-J27)/H27,"") -> 0.10555297 | J27: 1632.5 | K27: =iferror(J27/$C27,"") -> 1.5697115 | L27: =ifs($L$4="Full Comps",W27,$L$4="Quick Look",T27) | M27: =iferror(if($L$4="Quick Look",L27/C27,X27),"") | N27: =iferror(if(M27="","",(K27-M27)/K27),"") | P27: =Q27+J27 -> 1632.5 | R27: =iferror(Q27/J27,"") -> 0 | T27: 1553 | V27: =iferror(AVERAGE(Z27,AB27,AD27,AF27,AH27,AJ27,AL27,AN27),"") | W27: =iferror(average(Y27,AA27,AC27,AE27,AG27,AI27,AK27,AM27),"") | X27: =iferror(W27/V27,"")
G28: =IFERROR(D28/$D$34,"") -> 0 | I28: =iferror((H28-J28)/H28,"") | K28: =iferror(J28/$C28,"") | L28: =ifs($L$4="Full Comps",W28,$L$4="Quick Look",T28) | M28: =iferror(if($L$4="Quick Look",L28/C28,X28),"") | N28: =iferror(if(M28="","",(K28-M28)/K28),"") | P28: =Q28+J28 -> 0 | R28: =iferror(Q28/J28,"") | V28: =iferror(AVERAGE(Z28,AB28,AD28,AF28,AH28,AJ28,AL28,AN28),"") | W28: =iferror(average(Y28,AA28,AC28,AE28,AG28,AI28,AK28,AM28),"") | X28: =iferror(W28/V28,"")
G29: =IFERROR(D29/$D$34,"") -> 0 | I29: =iferror((H29-J29)/H29,"") | K29: =iferror(J29/$C29,"") | L29: =ifs($L$4="Full Comps",W29,$L$4="Quick Look",T29) | M29: =iferror(if($L$4="Quick Look",L29/C29,X29),"") | N29: =iferror(if(M29="","",(K29-M29)/K29),"") | P29: =Q29+J29 -> 0 | R29: =iferror(Q29/J29,"") | V29: =iferror(AVERAGE(Z29,AB29,AD29,AF29,AH29,AJ29,AL29,AN29),"") | W29: =iferror(average(Y29,AA29,AC29,AE29,AG29,AI29,AK29,AM29),"") | X29: =iferror(W29/V29,"")
G30: =IFERROR(D30/$D$34,"") -> 0 | I30: =iferror((H30-J30)/H30,"") | K30: =iferror(J30/$C30,"") | L30: =ifs($L$4="Full Comps",W30,$L$4="Quick Look",T30) | M30: =iferror(if($L$4="Quick Look",L30/C30,X30),"") | N30: =iferror(if(M30="","",(K30-M30)/K30),"") | P30: =Q30+J30 -> 0 | R30: =iferror(Q30/J30,"") | V30: =iferror(AVERAGE(Z30,AB30,AD30,AF30,AH30,AJ30,AL30,AN30),"") | W30: =iferror(average(Y30,AA30,AC30,AE30,AG30,AI30,AK30,AM30),"") | X30: =iferror(W30/V30,"")
G31: =IFERROR(D31/$D$34,"") -> 0 | I31: =iferror((H31-J31)/H31,"") | K31: =iferror(J31/$C31,"") | L31: =ifs($L$4="Full Comps",W31,$L$4="Quick Look",T31) | M31: =iferror(if($L$4="Quick Look",L31/C31,X31),"") | N31: =iferror(if(M31="","",(K31-M31)/K31),"") | P31: =Q31+J31 -> 0 | R31: =iferror(Q31/J31,"") | V31: =iferror(AVERAGE(Z31,AB31,AD31,AF31,AH31,AJ31,AL31,AN31),"") | W31: =iferror(average(Y31,AA31,AC31,AE31,AG31,AI31,AK31,AM31),"") | X31: =iferror(W31/V31,"")
G32: =IFERROR(D32/$D$34,"") -> 0 | I32: =iferror((H32-J32)/H32,"") | K32: =iferror(J32/$C32,"") | L32: =ifs($L$4="Full Comps",W32,$L$4="Quick Look",T32) | M32: =iferror(if($L$4="Quick Look",L32/C32,X32),"") | N32: =iferror(if(M32="","",(K32-M32)/K32),"") | P32: =Q32+J32 -> 0 | R32: =iferror(Q32/J32,"") | V32: =iferror(AVERAGE(Z32,AB32,AD32,AF32,AH32,AJ32,AL32,AN32),"") | W32: =iferror(average(Y32,AA32,AC32,AE32,AG32,AI32,AK32,AM32),"") | X32: =iferror(W32/V32,"")
G33: =IFERROR(D33/$D$34,"") -> 0 | I33: =iferror((H33-J33)/H33,"") | K33: =iferror(J33/$C33,"") | L33: =ifs($L$4="Full Comps",W33,$L$4="Quick Look",T33) | M33: =iferror(if($L$4="Quick Look",L33/C33,X33),"") | N33: =iferror(if(M33="","",(K33-M33)/K33),"") | P33: =Q33+J33 -> 0 | R33: =iferror(Q33/J33,"") | V33: =iferror(AVERAGE(Z33,AB33,AD33,AF33,AH33,AJ33,AL33,AN33),"") | W33: =iferror(average(Y33,AA33,AC33,AE33,AG33,AI33,AK33,AM33),"") | X33: =iferror(W33/V33,"")
B34: Total | C34: =iferror(SUMPRODUCT(C7:C33,D7:D33),"") -> 153613 | D34: =IFERROR(SUM(D7:D33),"") -> 184 | E34: =IFERROR(SUM(E7:E33),"") -> 169 | F34: =IFERROR(SUM(F7:F33),"") -> 49 | G34: =IFERROR(D34/$D$34,"") -> 1 | J34: =iferror(sumproduct(D7:D33,J7:J33),"") -> 256139.03 | W34: Average Price Per SF | X34: =iferror(average(X7:X33),"") -> 1.7655627
B35: Avg SF Per Unit | C35: =iferror(C34/D34,"") -> 834.85326 | D35: Current Occupancy | E35: =iferror(E34/D34,"") -> 0.91847826 | F35: =F34/D34 -> 0.26630435 | G35: Avg | I35: =iferror(average(I7:I33),"") -> 0.091029622 | J35: =iferror(J34/$D$34,"") -> 1392.0599 | N35: =iferror(average(N7:N33),"") -> -0.071141386 | Q35: =iferror(sumproduct(Q7:Q33,F7:F33)/F34,"") -> 195.97959
B38: Classic (no letter)
B39: Prior Upgrade- pu
B40: Upgrade- u
B41: Elite-e
B42: Prior Upgrade (PU) - stainless or black appliances, dark grey cabinets, some with hardware, formica, no backsplash, new carpet & vinyl – 10 units
B45: Upgrade(u) - backsplash, stainless steel appliances, hardware on cabinets, white cabinets, resurfaced counter tops, new vinyl & carpet, full paint – 111 units
B48: Elite(e) - matte black accents/hardware, hardsurface, back splash, farmers sink, stainless steel appliances, full paint, new carpet & vinyl – 2 units

Sheet Revenue
M2: Property Revenue
B3: ='Property Summary'!B3 -> Phoenix, AZ | M3: ='Property Summary'!I3 -> Wind River Group
B5: Anticipated RUBS Income | H5: Unit Renovations
B6: Water/Sewer | C6: 92 | D6: RUBS Collection % | E6: 1 | H6: Renovation Start Month | I6: 4
B7: Trash | C7: 0 | H7: Units Per Month | I7: 3
B8: Pest Control | C8: 0 | H8: Total Renovation Units | I8: ='Unit Mix & Comps'!F34 -> 49
B9: Package Hub | C9: 0 | H9: Unit Type / SF | I9: Renovation Units | J9: Current Rent | K9: Rent Premium
B10: Valet Trash | C10: 0 | H10: ='Unit Mix & Comps'!B7&", "&'Unit Mix & Comps'!C7&" SF" -> 1 Bed- Classic, 678 SF | I10: ='Unit Mix & Comps'!F7 -> 10 | J10: ='Unit Mix & Comps'!J7 -> 1101 | K10: ='Unit Mix & Comps'!Q7 -> 224
B11: Year 1 RUBS Per Unit | C11: =sum(C6:C10) -> 92 | H11: ='Unit Mix & Comps'!B10&", "&'Unit Mix & Comps'!C10&" SF" -> 1 Bed Classic, 734 SF | I11: ='Unit Mix & Comps'!F10 -> 9 | J11: ='Unit Mix & Comps'!J10 -> 1234.44 | K11: ='Unit Mix & Comps'!Q10 -> 151
H12: ='Unit Mix & Comps'!B13&", "&'Unit Mix & Comps'!C13&" SF" -> 1 Bed C, 771 SF | I12: ='Unit Mix & Comps'!F13 -> 10 | J12: ='Unit Mix & Comps'!J13 -> 1268.25 | K12: ='Unit Mix & Comps'!Q13 -> 132
B13: Anticipated Other Income | C13: T-12 | D13: Unit / Month | E13: Year 1 Proforma | F13: Proforma / Unit | H13: ='Unit Mix & Comps'!B16&", "&'Unit Mix & Comps'!C16&" SF" -> 2B / 1B -C, 863 SF | I13: ='Unit Mix & Comps'!F16 -> 10 | J13: ='Unit Mix & Comps'!J16 -> 1227.11 | K13: ='Unit Mix & Comps'!Q16 -> 248
B14: Total Other Income (-RUBS) | C14: 401185 | D14: =iferror(C14/'Unit Mix & Comps'!$D$34/12,"") -> 181.69611 | E14: 405000 | F14: =iferror(E14/'Unit Mix & Comps'!$D$34/12,"") -> 183.42391 | H14: ='Unit Mix & Comps'!B19&", "&'Unit Mix & Comps'!C19&" SF" -> 2B/ 2B- C, 958 SF | I14: ='Unit Mix & Comps'!F19 | J14: ='Unit Mix & Comps'!J19 -> 1569.75 | K14: ='Unit Mix & Comps'!Q19
H15: ='Unit Mix & Comps'!B22&", "&'Unit Mix & Comps'!C22&" SF" -> 2B/2B C, 1000 SF | I15: ='Unit Mix & Comps'!F22 -> 7 | J15: ='Unit Mix & Comps'!J22 -> 1420.14 | K15: ='Unit Mix & Comps'!Q22 -> 230
B16: Gross Potential Rents | C16: Monthly | D16: Annual | E16: Avg Price Per Unit | F16: Above/Below Market | H16: ='Unit Mix & Comps'!B25&", "&'Unit Mix & Comps'!C25&" SF" -> 2B/2B C, 1040 SF | I16: ='Unit Mix & Comps'!F25 -> 3 | J16: ='Unit Mix & Comps'!J25 -> 1457 | K16: ='Unit Mix & Comps'!Q25 -> 198
B17: Current Rent | C17: =iferror('Unit Mix & Comps'!J34,"") -> 256139.03 | D17: =C17*12 -> 3073668.4 | E17: ='Unit Mix & Comps'!J35 -> 1392.0599 | F17: ='Unit Mix & Comps'!N35 -> -0.071141386 | H17: ='Unit Mix & Comps'!B26&", "&'Unit Mix & Comps'!C26&" SF" -> 2B/ 2B- PU, 1040 SF | I17: ='Unit Mix & Comps'!F26 | J17: ='Unit Mix & Comps'!J26 -> 1584 | K17: ='Unit Mix & Comps'!Q26
B18: Market Rent | C18: =E18*'Unit Mix & Comps'!D34 -> 274361.12 | D18: =C18*12 -> 3292333.4 | E18: =iferror(E17*(1-F17),"") -> 1491.093 | H18: ='Unit Mix & Comps'!B27&", "&'Unit Mix & Comps'!C27&" SF" -> 2B/ 2B- U, 1040 SF | I18: ='Unit Mix & Comps'!F27 | J18: ='Unit Mix & Comps'!J27 -> 1632.5 | K18: ='Unit Mix & Comps'!Q27
B19: Renovated Rent Premium | C19: =iferror(sumproduct('Unit Mix & Comps'!F7:F33,'Unit Mix & Comps'!Q7:Q33),"") -> 9603 | D19: =C19*12 -> 115236 | E19: ='Unit Mix & Comps'!Q35 -> 195.97959 | H19: ='Unit Mix & Comps'!B28&", "&'Unit Mix & Comps'!C28&" SF" -> , SF | I19: ='Unit Mix & Comps'!F28 | J19: ='Unit Mix & Comps'!J28 | K19: ='Unit Mix & Comps'!Q28
B20: Avg Market Rent Growth | C20: 0.035 | H20: ='Unit Mix & Comps'!B29&", "&'Unit Mix & Comps'!C29&" SF" -> , SF | I20: ='Unit Mix & Comps'!F29 | J20: ='Unit Mix & Comps'!J29 | K20: ='Unit Mix & Comps'!Q29
H21: ='Unit Mix & Comps'!B30&", "&'Unit Mix & Comps'!C30&" SF" -> , SF | I21: ='Unit Mix & Comps'!F30 | J21: ='Unit Mix & Comps'!J30 | K21: ='Unit Mix & Comps'!Q30
H22: ='Unit Mix & Comps'!B31&", "&'Unit Mix & Comps'!C31&" SF" -> , SF | I22: ='Unit Mix & Comps'!F31 | J22: ='Unit Mix & Comps'!J31 | K22: ='Unit Mix & Comps'!Q31
H23: ='Unit Mix & Comps'!B32&", "&'Unit Mix & Comps'!C32&" SF" -> , SF | I23: ='Unit Mix & Comps'!F32 | J23: ='Unit Mix & Comps'!J32 | K23: ='Unit Mix & Comps'!Q32
H24: ='Unit Mix & Comps'!B33&", "&'Unit Mix & Comps'!C33&" SF" -> , SF | I24: ='Unit Mix & Comps'!F33 | J24: ='Unit Mix & Comps'!J33 | K24: ='Unit Mix & Comps'!Q33
B26: Income Growth Assumptions | C26: 1 | D26: 2 | E26: 3 | F26: 4 | G26: 5 | H26: 6 | I26: 7 | J26: 8 | K26: 9 | L26: 10
B27: RUBS Income Growth | C27: 0 | D27: 0.02 | E27: =$D$27 -> 0.02 | F27: =$D$27 -> 0.02 | G27: =$D$27 -> 0.02 | H27: =$D$27 -> 0.02 | I27: =$D$27 -> 0.02 | J27: =$D$27 -> 0.02 | K27: =$D$27 -> 0.02 | L27: =$D$27 -> 0.02
B28: Monthly RUBS Income Per Unit | C28: =iferror(C11*(1+C27),"") -> 92 | D28: =iferror(C28*(1+D$27),"") -> 93.84 | E28: =iferror(D28*(1+E$27),"") -> 95.7168 | F28: =iferror(E28*(1+F$27),"") -> 97.631136 | G28: =iferror(F28*(1+G$27),"") -> 99.583759 | H28: =iferror(G28*(1+H$27),"") -> 101.57543 | I28: =iferror(H28*(1+I$27),"") -> 103.60694 | J28: =iferror(I28*(1+J$27),"") -> 105.67908 | K28: =iferror(J28*(1+K$27),"") -> 107.79266 | L28: =iferror(K28*(1+L$27),"") -> 109.94852
B29: Other Income Growth | C29: 0 | D29: 0.02 | E29: =$D$29 -> 0.02 | F29: =$D$29 -> 0.02 | G29: =$D$29 -> 0.02 | H29: =$D$29 -> 0.02 | I29: =$D$29 -> 0.02 | J29: =$D$29 -> 0.02 | K29: =$D$29 -> 0.02 | L29: =$D$29 -> 0.02
B30: Rental Income Growth | C30: 0.035 | D30: 0.035 | E30: 0.035 | F30: 0.035 | G30: =$C$20 -> 0.035 | H30: =$C$20 -> 0.035 | I30: =$C$20 -> 0.035 | J30: =$C$20 -> 0.035 | K30: =$C$20 -> 0.035 | L30: =$C$20 -> 0.035
B31: Avg Current Rent | C31: =iferror(E17*(1+C30),"") -> 1440.782 | D31: =iferror(C31*(1+D$30),"") -> 1491.2094 | E31: =iferror(D31*(1+E$30),"") -> 1543.4017 | F31: =iferror(E31*(1+F$30),"") -> 1597.4208 | G31: =iferror(F31*(1+G$30),"") -> 1653.3305 | H31: =iferror(G31*(1+H$30),"") -> 1711.1971 | I31: =iferror(H31*(1+I$30),"") -> 1771.089 | J31: =iferror(I31*(1+J$30),"") -> 1833.0771 | K31: =iferror(J31*(1+K$30),"") -> 1897.2348 | L31: =iferror(K31*(1+L$30),"") -> 1963.638
B32: Avg Monthly Market Rent | C32: =iferror(E18*(1+C20),"") -> 1543.2813 | D32: =iferror(C32*(1+$C$20),"") -> 1597.2961 | E32: =iferror(D32*(1+$C$20),"") -> 1653.2015 | F32: =iferror(E32*(1+$C$20),"") -> 1711.0635 | G32: =iferror(F32*(1+$C$20),"") -> 1770.9508 | H32: =iferror(G32*(1+$C$20),"") -> 1832.934 | I32: =iferror(H32*(1+$C$20),"") -> 1897.0867 | J32: =iferror(I32*(1+$C$20),"") -> 1963.4848 | K32: =iferror(J32*(1+$C$20),"") -> 2032.2067 | L32: =iferror(K32*(1+$C$20),"") -> 2103.334
B33: Avg Monthly Renovated Rent | C33: =iferror(sum(E17,E19),"") -> 1588.0395 | D33: =iferror(C33*(1+$C$20),"") -> 1643.6209 | E33: =iferror(D33*(1+$C$20),"") -> 1701.1477 | F33: =iferror(E33*(1+$C$20),"") -> 1760.6878 | G33: =iferror(F33*(1+$C$20),"") -> 1822.3119 | H33: =iferror(G33*(1+$C$20),"") -> 1886.0928 | I33: =iferror(H33*(1+$C$20),"") -> 1952.1061 | J33: =iferror(I33*(1+$C$20),"") -> 2020.4298 | K33: =iferror(J33*(1+$C$20),"") -> 2091.1448 | L33: =iferror(K33*(1+$C$20),"") -> 2164.3349
B34: Vacancy Loss | C34: 0.08 | D34: 0.08 | E34: 0.07 | F34: 0.07 | G34: =$F$34 -> 0.07 | H34: =$F$34 -> 0.07 | I34: =$F$34 -> 0.07 | J34: =$F$34 -> 0.07 | K34: =$F$34 -> 0.07 | L34: =$F$34 -> 0.07
B35: Bad Debt Expense | C35: 0.015 | D35: 0.0125 | E35: =$D$35 -> 0.0125 | F35: =$E$35 -> 0.0125 | G35: =$E$35 -> 0.0125 | H35: =$E$35 -> 0.0125 | I35: =$E$35 -> 0.0125 | J35: =$E$35 -> 0.0125 | K35: =$E$35 -> 0.0125 | L35: =$E$35 -> 0.0125
B36: Concessions | C36: 0.0125 | D36: =$C$36 -> 0.0125 | E36: =$C$36 -> 0.0125 | F36: =$C$36 -> 0.0125 | G36: =$C$36 -> 0.0125 | H36: =$C$36 -> 0.0125 | I36: =$C$36 -> 0.0125 | J36: =$C$36 -> 0.0125 | K36: =$C$36 -> 0.0125 | L36: =$C$36 -> 0.0125
B38: Projected Annual Revenue
C41: T-12 | D41: 1 | E41: 2 | F41: 3 | G41: 4 | H41: 5 | I41: 6 | J41: 7 | K41: 8 | L41: 9 | M41: 10
B42: Year End Total Units | C42: ='Historical Financials'!C5 -> 184 | D42: =iferror(lookup(D$41*12,$D$61:$DS$61,$D$63:$DS$63),"") -> 184 | E42: =iferror(lookup(E$41*12,$D$61:$DS$61,$D$63:$DS$63),"") -> 184 | F42: =iferror(lookup(F$41*12,$D$61:$DS$61,$D$63:$DS$63),"") -> 184 | G42: =iferror(lookup(G$41*12,$D$61:$DS$61,$D$63:$DS$63),"") -> 184 | H42: =iferror(lookup(H$41*12,$D$61:$DS$61,$D$63:$DS$63),"") -> 184 | I42: =iferror(lookup(I$41*12,$D$61:$DS$61,$D$63:$DS$63),"") -> 184 | J42: =iferror(lookup(J$41*12,$D$61:$DS$61,$D$63:$DS$63),"") -> 184 | K42: =iferror(lookup(K$41*12,$D$61:$DS$61,$D$63:$DS$63),"") -> 184 | ... M42: =iferror(lookup(M$41*12,$D$61:$DS$61,$D$63:$DS$63),"") -> 184
B43: Year End Offline Units | C43: 0 | D43: =iferror(lookup(D$41*12,$D$61:$DS$61,$D$64:$DS$64),"") -> 3 | E43: =iferror(lookup(E$41*12,$D$61:$DS$61,$D$64:$DS$64),"") -> 0 | F43: =iferror(lookup(F$41*12,$D$61:$DS$61,$D$64:$DS$64),"") -> 0 | G43: =iferror(lookup(G$41*12,$D$61:$DS$61,$D$64:$DS$64),"") -> 0 | H43: =iferror(lookup(H$41*12,$D$61:$DS$61,$D$64:$DS$64),"") -> 0 | I43: =iferror(lookup(I$41*12,$D$61:$DS$61,$D$64:$DS$64),"") -> 0 | J43: =iferror(lookup(J$41*12,$D$61:$DS$61,$D$64:$DS$64),"") -> 0 | K43: =iferror(lookup(K$41*12,$D$61:$DS$61,$D$64:$DS$64),"") -> 0 | ... M43: =iferror(lookup(M$41*12,$D$61:$DS$61,$D$64:$DS$64),"") -> 0
B44: Total Renovated Units | C44: 0 | D44: =iferror(lookup(D$41*12,$D$61:$DS$61,$D$65:$DS$65),"") -> 24 | E44: =iferror(lookup(E$41*12,$D$61:$DS$61,$D$65:$DS$65),"") -> 49 | F44: =iferror(lookup(F$41*12,$D$61:$DS$61,$D$65:$DS$65),"") -> 49 | G44: =iferror(lookup(G$41*12,$D$61:$DS$61,$D$65:$DS$65),"") -> 49 | H44: =iferror(lookup(H$41*12,$D$61:$DS$61,$D$65:$DS$65),"") -> 49 | I44: =iferror(lookup(I$41*12,$D$61:$DS$61,$D$65:$DS$65),"") -> 49 | J44: =iferror(lookup(J$41*12,$D$61:$DS$61,$D$65:$DS$65),"") -> 49 | K44: =iferror(lookup(K$41*12,$D$61:$DS$61,$D$65:$DS$65),"") -> 49 | ... M44: =iferror(lookup(M$41*12,$D$61:$DS$61,$D$65:$DS$65),"") -> 49
B45: Year End Occupancy % (Excl Offline Units) | C45: ='Historical Financials'!C7 -> 0.91847826 | D45: =iferror(lookup(D$41*12,$D$61:$DS$61,$D$66:$DS$66),"") -> 0.92 | E45: =iferror(lookup(E$41*12,$D$61:$DS$61,$D$66:$DS$66),"") -> 0.92 | F45: =iferror(lookup(F$41*12,$D$61:$DS$61,$D$66:$DS$66),"") -> 0.93 | G45: =iferror(lookup(G$41*12,$D$61:$DS$61,$D$66:$DS$66),"") -> 0.93 | H45: =iferror(lookup(H$41*12,$D$61:$DS$61,$D$66:$DS$66),"") -> 0.93 | I45: =iferror(lookup(I$41*12,$D$61:$DS$61,$D$66:$DS$66),"") -> 0.93 | J45: =iferror(lookup(J$41*12,$D$61:$DS$61,$D$66:$DS$66),"") -> 0.93 | K45: =iferror(lookup(K$41*12,$D$61:$DS$61,$D$66:$DS$66),"") -> 0.93 | ... M45: =iferror(lookup(M$41*12,$D$61:$DS$61,$D$66:$DS$66),"") -> 0.93
B46: Loss to Lease % | C46: =iferror(-C50/C49,"") -> 0.071881657 | D46: =iferror(-D50/D49,"") -> 0.061749222 | E46: =iferror(-E50/E49,"") -> 0.044981851 | F46: =iferror(-F50/F49,"") -> 0.041006083 | G46: =iferror(-G50/G49,"") -> 0.041006083 | H46: =iferror(-H50/H49,"") -> 0.041006083 | I46: =iferror(-I50/I49,"") -> 0.041006083 | J46: =iferror(-J50/J49,"") -> 0.041006083 | ... M46: =iferror(-M50/M49,"") -> 0.041006083
B48: Total Revenue
B49: Potential Rental Income | C49: ='Historical Financials'!C10 -> 3425241 | D49: =iferror(sumif($D$60:$DS$60,D$41,$D$70:$DS$70),"") -> 3407565.1 | E49: =iferror(sumif($D$60:$DS$60,E$41,$D$70:$DS$70),"") -> 3526829.8 | F49: =iferror(sumif($D$60:$DS$60,F$41,$D$70:$DS$70),"") -> 3650268.9 | G49: =iferror(sumif($D$60:$DS$60,G$41,$D$70:$DS$70),"") -> 3778028.3 | H49: =iferror(sumif($D$60:$DS$60,H$41,$D$70:$DS$70),"") -> 3910259.3 | I49: =iferror(sumif($D$60:$DS$60,I$41,$D$70:$DS$70),"") -> 4047118.4 | J49: =iferror(sumif($D$60:$DS$60,J$41,$D$70:$DS$70),"") -> 4188767.5 | K49: =iferror(sumif($D$60:$DS$60,K$41,$D$70:$DS$70),"") -> 4335374.4 | ... M49: =iferror(sumif($D$60:$DS$60,M$41,$D$70:$DS$70),"") -> 4644161.4
B50: Loss to Lease | C50: ='Historical Financials'!C11 -> -246212 | D50: =iferror(sumif($D$60:$DS$60,D$41,$D$71:$DS$71),"") -> -210414.49 | E50: =iferror(sumif($D$60:$DS$60,E$41,$D$71:$DS$71),"") -> -158643.34 | F50: =iferror(sumif($D$60:$DS$60,F$41,$D$71:$DS$71),"") -> -149683.23 | G50: =iferror(sumif($D$60:$DS$60,G$41,$D$71:$DS$71),"") -> -154922.14 | H50: =iferror(sumif($D$60:$DS$60,H$41,$D$71:$DS$71),"") -> -160344.42 | I50: =iferror(sumif($D$60:$DS$60,I$41,$D$71:$DS$71),"") -> -165956.47 | J50: =iferror(sumif($D$60:$DS$60,J$41,$D$71:$DS$71),"") -> -171764.95 | K50: =iferror(sumif($D$60:$DS$60,K$41,$D$71:$DS$71),"") -> -177776.72 | ... M50: =iferror(sumif($D$60:$DS$60,M$41,$D$71:$DS$71),"") -> -190438.87
B51: Vacancy Loss | C51: ='Historical Financials'!C12 -> -255589.29 | D51: =iferror(sumif($D$60:$DS$60,D$41,$D$72:$DS$72),"") -> -255772.05 | E51: =iferror(sumif($D$60:$DS$60,E$41,$D$72:$DS$72),"") -> -269454.92 | F51: =iferror(sumif($D$60:$DS$60,F$41,$D$72:$DS$72),"") -> -245041 | G51: =iferror(sumif($D$60:$DS$60,G$41,$D$72:$DS$72),"") -> -253617.43 | H51: =iferror(sumif($D$60:$DS$60,H$41,$D$72:$DS$72),"") -> -262494.04 | I51: =iferror(sumif($D$60:$DS$60,I$41,$D$72:$DS$72),"") -> -271681.33 | J51: =iferror(sumif($D$60:$DS$60,J$41,$D$72:$DS$72),"") -> -281190.18 | K51: =iferror(sumif($D$60:$DS$60,K$41,$D$72:$DS$72),"") -> -291031.83 | ... M51: =iferror(sumif($D$60:$DS$60,M$41,$D$72:$DS$72),"") -> -311760.58
B52: Offline Renovation Loss | C52: 0 | D52: =iferror(sumif($D$60:$DS$60,D$41,$D$73:$DS$73),"") -> -41668.594 | E52: =iferror(sumif($D$60:$DS$60,E$41,$D$73:$DS$73),"") -> -35140.515 | F52: =iferror(sumif($D$60:$DS$60,F$41,$D$73:$DS$73),"") -> 0 | G52: =iferror(sumif($D$60:$DS$60,G$41,$D$73:$DS$73),"") -> 0 | H52: =iferror(sumif($D$60:$DS$60,H$41,$D$73:$DS$73),"") -> 0 | I52: =iferror(sumif($D$60:$DS$60,I$41,$D$73:$DS$73),"") -> 0 | J52: =iferror(sumif($D$60:$DS$60,J$41,$D$73:$DS$73),"") -> 0 | K52: =iferror(sumif($D$60:$DS$60,K$41,$D$73:$DS$73),"") -> 0 | ... M52: =iferror(sumif($D$60:$DS$60,M$41,$D$73:$DS$73),"") -> 0
B53: Bad Debt Expense | C53: ='Historical Financials'!C13 -> -42218.63 | D53: =iferror(sumif($D$60:$DS$60,D$41,$D$74:$DS$74),"") -> -43495.649 | E53: =iferror(sumif($D$60:$DS$60,E$41,$D$74:$DS$74),"") -> -38294.888 | F53: =iferror(sumif($D$60:$DS$60,F$41,$D$74:$DS$74),"") -> -40694.308 | G53: =iferror(sumif($D$60:$DS$60,G$41,$D$74:$DS$74),"") -> -42118.609 | H53: =iferror(sumif($D$60:$DS$60,H$41,$D$74:$DS$74),"") -> -43592.76 | I53: =iferror(sumif($D$60:$DS$60,I$41,$D$74:$DS$74),"") -> -45118.507 | J53: =iferror(sumif($D$60:$DS$60,J$41,$D$74:$DS$74),"") -> -46697.655 | K53: =iferror(sumif($D$60:$DS$60,K$41,$D$74:$DS$74),"") -> -48332.073 | ... M53: =iferror(sumif($D$60:$DS$60,M$41,$D$74:$DS$74),"") -> -51774.524
B54: Concessions | C54: ='Historical Financials'!C14 -> -53858.32 | D54: =iferror(sumif($D$60:$DS$60,D$41,$D$75:$DS$75),"") -> -36246.374 | E54: =iferror(sumif($D$60:$DS$60,E$41,$D$75:$DS$75),"") -> -38294.888 | F54: =iferror(sumif($D$60:$DS$60,F$41,$D$75:$DS$75),"") -> -40694.308 | G54: =iferror(sumif($D$60:$DS$60,G$41,$D$75:$DS$75),"") -> -42118.609 | H54: =iferror(sumif($D$60:$DS$60,H$41,$D$75:$DS$75),"") -> -43592.76 | I54: =iferror(sumif($D$60:$DS$60,I$41,$D$75:$DS$75),"") -> -45118.507 | J54: =iferror(sumif($D$60:$DS$60,J$41,$D$75:$DS$75),"") -> -46697.655 | K54: =iferror(sumif($D$60:$DS$60,K$41,$D$75:$DS$75),"") -> -48332.073 | ... M54: =iferror(sumif($D$60:$DS$60,M$41,$D$75:$DS$75),"") -> -51774.524
B55: Total Rental Income | C55: ='Historical Financials'!C15 -> 2827362.8 | D55: =iferror(sumif($D$60:$DS$60,D$41,$D$76:$DS$76),"") -> 2819967.9 | E55: =iferror(sumif($D$60:$DS$60,E$41,$D$76:$DS$76),"") -> 2987001.3 | F55: =iferror(sumif($D$60:$DS$60,F$41,$D$76:$DS$76),"") -> 3174156 | G55: =iferror(sumif($D$60:$DS$60,G$41,$D$76:$DS$76),"") -> 3285251.5 | H55: =iferror(sumif($D$60:$DS$60,H$41,$D$76:$DS$76),"") -> 3400235.3 | I55: =iferror(sumif($D$60:$DS$60,I$41,$D$76:$DS$76),"") -> 3519243.5 | J55: =iferror(sumif($D$60:$DS$60,J$41,$D$76:$DS$76),"") -> 3642417.1 | K55: =iferror(sumif($D$60:$DS$60,K$41,$D$76:$DS$76),"") -> 3769901.7 | ... M55: =iferror(sumif($D$60:$DS$60,M$41,$D$76:$DS$76),"") -> 4038412.9
B56: Total RUBS Income | C56: ='Historical Financials'!C16 -> 184233.56 | D56: =iferror(sumif($D$60:$DS$60,D$41,$D$77:$DS$77),"") -> 184401.12 | E56: =iferror(sumif($D$60:$DS$60,E$41,$D$77:$DS$77),"") -> 188558.34 | F56: =iferror(sumif($D$60:$DS$60,F$41,$D$77:$DS$77),"") -> 196548.71 | G56: =iferror(sumif($D$60:$DS$60,G$41,$D$77:$DS$77),"") -> 200479.68 | H56: =iferror(sumif($D$60:$DS$60,H$41,$D$77:$DS$77),"") -> 204489.27 | I56: =iferror(sumif($D$60:$DS$60,I$41,$D$77:$DS$77),"") -> 208579.06 | J56: =iferror(sumif($D$60:$DS$60,J$41,$D$77:$DS$77),"") -> 212750.64 | K56: =iferror(sumif($D$60:$DS$60,K$41,$D$77:$DS$77),"") -> 217005.65 | ... M56: =iferror(sumif($D$60:$DS$60,M$41,$D$77:$DS$77),"") -> 225772.68
B57: Total Other Income | C57: ='Historical Financials'!C17 -> 401184.55 | D57: =iferror(E14,"") -> 405000 | E57: =iferror(D57*(1+D29),"") -> 413100 | F57: =iferror(E57*(1+E29),"") -> 421362 | G57: =iferror(F57*(1+F29),"") -> 429789.24 | H57: =iferror(G57*(1+G29),"") -> 438385.02 | I57: =iferror(H57*(1+H29),"") -> 447152.73 | J57: =iferror(I57*(1+I29),"") -> 456095.78 | K57: =iferror(J57*(1+J29),"") -> 465217.7 | L57: =iferror(K57*(1+K29),"") -> 474522.05 | M57: =iferror(L57*(1+L29),"") -> 484012.49
B58: Total Revenue | C58: ='Historical Financials'!C18 -> 3412780.9 | D58: =iferror(sumif($D$60:$DS$60,D$41,$D$79:$DS$79),"") -> 3409369 | E58: =iferror(sumif($D$60:$DS$60,E$41,$D$79:$DS$79),"") -> 3588659.6 | F58: =iferror(sumif($D$60:$DS$60,F$41,$D$79:$DS$79),"") -> 3792066.7 | G58: =iferror(sumif($D$60:$DS$60,G$41,$D$79:$DS$79),"") -> 3915520.4 | H58: =iferror(sumif($D$60:$DS$60,H$41,$D$79:$DS$79),"") -> 4043109.6 | I58: =iferror(sumif($D$60:$DS$60,I$41,$D$79:$DS$79),"") -> 4174975.3 | J58: =iferror(sumif($D$60:$DS$60,J$41,$D$79:$DS$79),"") -> 4311263.5 | K58: =iferror(sumif($D$60:$DS$60,K$41,$D$79:$DS$79),"") -> 4452125 | ... M58: =iferror(sumif($D$60:$DS$60,M$41,$D$79:$DS$79),"") -> 4748198.1
B60: Analysis Year | D60: =ROUNDUP(D61/12,0) -> 1 | E60: =ROUNDUP(E61/12,0) -> 1 | F60: =ROUNDUP(F61/12,0) -> 1 | G60: =ROUNDUP(G61/12,0) -> 1 | H60: =ROUNDUP(H61/12,0) -> 1 | I60: =ROUNDUP(I61/12,0) -> 1 | J60: =ROUNDUP(J61/12,0) -> 1 | K60: =ROUNDUP(K61/12,0) -> 1 | ... DS60: =ROUNDUP(DS61/12,0) -> 10
B61: Date | D61: 1 | E61: =D61+1 -> 2 | F61: =E61+1 -> 3 | G61: =F61+1 -> 4 | H61: =G61+1 -> 5 | I61: =H61+1 -> 6 | J61: =I61+1 -> 7 | K61: =J61+1 -> 8 | L61: =K61+1 -> 9 | ... DS61: =DR61+1 -> 120
B62: Project Month | D62: ='Project Budget'!J7 -> 45869 | E62: =edate(D62,1) -> 45900 | F62: =edate(E62,1) -> 45930 | G62: =edate(F62,1) -> 45960 | H62: =edate(G62,1) -> 45991 | I62: =edate(H62,1) -> 46021 | J62: =edate(I62,1) -> 46052 | K62: =edate(J62,1) -> 46081 | L62: =edate(K62,1) -> 46109 | ... DS62: =edate(DR62,1) -> 49488
B63: Total Units | D63: ='Unit Mix & Comps'!$D$34 -> 184 | E63: ='Unit Mix & Comps'!$D$34 -> 184 | F63: ='Unit Mix & Comps'!$D$34 -> 184 | G63: ='Unit Mix & Comps'!$D$34 -> 184 | H63: ='Unit Mix & Comps'!$D$34 -> 184 | I63: ='Unit Mix & Comps'!$D$34 -> 184 | J63: ='Unit Mix & Comps'!$D$34 -> 184 | K63: ='Unit Mix & Comps'!$D$34 -> 184 | ... DS63: ='Unit Mix & Comps'!$D$34 -> 184
B64: Offline Units | D64: =iferror(ifs(D61<$I$6,0,and(D61=$I$6,$I$7<=$I$8),$I$7,and(D61=$I$6,$I$7>$I$8),$I$8,and(D61>$I$6,sum(D$64:$F64)+$I$7>$I$8),$I$8-sum(D$64:$F64),and(D61>$I$6,sum(D$64:$F64)+$I$7<=$I$8),$I$7),"") -> 0 | E64: =iferror(ifs(E61<$I$6,0,and(E61=$I$6,$I$7<=$I$8),$I$7,and(E61=$I$6,$I$7>$I$8),$I$8,and(E61>$I$6,sum($D$64:D64)+$I$7>$I$8),$I$8-sum($D$64:D64),and(E61>$I$6,sum($D$64:D64)+$I$7<=$I$8),$I$7),"") -> 0 | F64: =iferror(ifs(F61<$I$6,0,and(F61=$I$6,$I$7<=$I$8),$I$7,and(F61=$I$6,$I$7>$I$8),$I$8,and(F61>$I$6,sum($D$64:E64)+$I$7>$I$8),$I$8-sum($D$64:E64),and(F61>$I$6,sum($D$64:E64)+$I$7<=$I$8),$I$7),"") -> 0 | G64: =iferror(ifs(G61<$I$6,0,and(G61=$I$6,$I$7<=$I$8),$I$7,and(G61=$I$6,$I$7>$I$8),$I$8,and(G61>$I$6,sum($D$64:F64)+$I$7>$I$8),$I$8-sum($D$64:F64),and(G61>$I$6,sum($D$64:F64)+$I$7<=$I$8),$I$7),"") -> 3 | H64: =iferror(ifs(H61<$I$6,0,and(H61=$I$6,$I$7<=$I$8),$I$7,and(H61=$I$6,$I$7>$I$8),$I$8,and(H61>$I$6,sum($D$64:G64)+$I$7>$I$8),$I$8-sum($D$64:G64),and(H61>$I$6,sum($D$64:G64)+$I$7<=$I$8),$I$7),"") -> 3 | I64: =iferror(ifs(I61<$I$6,0,and(I61=$I$6,$I$7<=$I$8),$I$7,and(I61=$I$6,$I$7>$I$8),$I$8,and(I61>$I$6,sum($D$64:H64)+$I$7>$I$8),$I$8-sum($D$64:H64),and(I61>$I$6,sum($D$64:H64)+$I$7<=$I$8),$I$7),"") -> 3 | J64: =iferror(ifs(J61<$I$6,0,and(J61=$I$6,$I$7<=$I$8),$I$7,and(J61=$I$6,$I$7>$I$8),$I$8,and(J61>$I$6,sum($D$64:I64)+$I$7>$I$8),$I$8-sum($D$64:I64),and(J61>$I$6,sum($D$64:I64)+$I$7<=$I$8),$I$7),"") -> 3 | K64: =iferror(ifs(K61<$I$6,0,and(K61=$I$6,$I$7<=$I$8),$I$7,and(K61=$I$6,$I$7>$I$8),$I$8,and(K61>$I$6,sum($D$64:J64)+$I$7>$I$8),$I$8-sum($D$64:J64),and(K61>$I$6,sum($D$64:J64)+$I$7<=$I$8),$I$7),"") -> 3 | L64: =iferror(ifs(L61<$I$6,0,and(L61=$I$6,$I$7<=$I$8),$I$7,and(L61=$I$6,$I$7>$I$8),$I$8,and(L61>$I$6,sum($D$64:K64)+$I$7>$I$8),$I$8-sum($D$64:K64),and(L61>$I$6,sum($D$64:K64)+$I$7<=$I$8),$I$7),"") -> 3 | ... DS64: =iferror(ifs(DS61<$I$6,0,and(DS61=$I$6,$I$7<=$I$8),$I$7,and(DS61=$I$6,$I$7>$I$8),$I$8,and(DS61>$I$6,sum($D$64:DR64)+$I$7>$I$8),$I$8-sum($D$64:DR64),and(DS61>$I$6,sum($D$64:DR64)+$I$7<=$I$8),$I$7),"") -> 0
B65: Total Renovated Units | D65: =iferror(sum($D$64:E64),"") -> 0 | E65: =iferror(sum($D$64:F64),"") -> 0 | F65: =iferror(sum($D$64:F64),"") -> 0 | G65: =iferror(sum($D$64:F64),"") -> 0 | H65: =iferror(sum($D$64:G64),"") -> 3 | I65: =iferror(sum($D$64:H64),"") -> 6 | J65: =iferror(sum($D$64:I64),"") -> 9 | K65: =iferror(sum($D$64:J64),"") -> 12 | L65: =iferror(sum($D$64:K64),"") -> 15 | M65: =iferror(sum($D$64:L64),"") -> 18 | N65: =iferror(sum($D$64:M64),"") -> 21 | ... DS65: =iferror(sum($D$64:DR64),"") -> 49
B66: Occupancy % (Excluding Offline Units) | D66: =iferror(1-lookup(D$60,$C$26:$L$26,$C$34:$L$34),"") -> 0.92 | E66: =iferror(1-lookup(E$60,$C$26:$L$26,$C$34:$L$34),"") -> 0.92 | F66: =iferror(1-lookup(F$60,$C$26:$L$26,$C$34:$L$34),"") -> 0.92 | G66: =iferror(1-lookup(G$60,$C$26:$L$26,$C$34:$L$34),"") -> 0.92 | H66: =iferror(1-lookup(H$60,$C$26:$L$26,$C$34:$L$34),"") -> 0.92 | I66: =iferror(1-lookup(I$60,$C$26:$L$26,$C$34:$L$34),"") -> 0.92 | J66: =iferror(1-lookup(J$60,$C$26:$L$26,$C$34:$L$34),"") -> 0.92 | K66: =iferror(1-lookup(K$60,$C$26:$L$26,$C$34:$L$34),"") -> 0.92 | ... DS66: =iferror(1-lookup(DS$60,$C$26:$L$26,$C$34:$L$34),"") -> 0.93
B67: Loss to Lease % | D67: =iferror(-D71/D70,"") -> 0.066416429 | E67: =iferror(-E71/E70,"") -> 0.066416429 | F67: =iferror(-F71/F70,"") -> 0.066416429 | G67: =iferror(-G71/G70,"") -> 0.066416429 | H67: =iferror(-H71/H70,"") -> 0.064860693 | I67: =iferror(-I71/I70,"") -> 0.063304958 | J67: =iferror(-J71/J70,"") -> 0.061749222 | K67: =iferror(-K71/K70,"") -> 0.060193487 | ... DS67: =iferror(-DS71/DS70,"") -> 0.041006083
B69: Total Revenue
B70: Potential Rental Income | D70: =iferror(D63*lookup(D$60,$C$26:$L$26,$C$32:$L$32),"") -> 283963.75 | E70: =iferror(E63*lookup(E$60,$C$26:$L$26,$C$32:$L$32),"") -> 283963.75 | F70: =iferror(F63*lookup(F$60,$C$26:$L$26,$C$32:$L$32),"") -> 283963.75 | G70: =iferror(G63*lookup(G$60,$C$26:$L$26,$C$32:$L$32),"") -> 283963.75 | H70: =iferror(H63*lookup(H$60,$C$26:$L$26,$C$32:$L$32),"") -> 283963.75 | I70: =iferror(I63*lookup(I$60,$C$26:$L$26,$C$32:$L$32),"") -> 283963.75 | J70: =iferror(J63*lookup(J$60,$C$26:$L$26,$C$32:$L$32),"") -> 283963.75 | K70: =iferror(K63*lookup(K$60,$C$26:$L$26,$C$32:$L$32),"") -> 283963.75 | ... DS70: =iferror(DS63*lookup(DS$60,$C$26:$L$26,$C$32:$L$32),"") -> 387013.45
B71: Loss to Lease | D71: =iferror(-(D70-((D63-D65)*lookup(D$60,$C$26:$L$26,$C$31:$L$31))-(D65*lookup(D$60,$C$26:$L$26,$C$33:$L$33))),"") -> -18859.858 | E71: =iferror(-(E70-((E63-E65)*lookup(E$60,$C$26:$L$26,$C$31:$L$31))-(E65*lookup(E$60,$C$26:$L$26,$C$33:$L$33))),"") -> -18859.858 | F71: =iferror(-(F70-((F63-F65)*lookup(F$60,$C$26:$L$26,$C$31:$L$31))-(F65*lookup(F$60,$C$26:$L$26,$C$33:$L$33))),"") -> -18859.858 | G71: =iferror(-(G70-((G63-G65)*lookup(G$60,$C$26:$L$26,$C$31:$L$31))-(G65*lookup(G$60,$C$26:$L$26,$C$33:$L$33))),"") -> -18859.858 | H71: =iferror(-(H70-((H63-H65)*lookup(H$60,$C$26:$L$26,$C$31:$L$31))-(H65*lookup(H$60,$C$26:$L$26,$C$33:$L$33))),"") -> -18418.086 | I71: =iferror(-(I70-((I63-I65)*lookup(I$60,$C$26:$L$26,$C$31:$L$31))-(I65*lookup(I$60,$C$26:$L$26,$C$33:$L$33))),"") -> -17976.314 | J71: =iferror(-(J70-((J63-J65)*lookup(J$60,$C$26:$L$26,$C$31:$L$31))-(J65*lookup(J$60,$C$26:$L$26,$C$33:$L$33))),"") -> -17534.541 | K71: =iferror(-(K70-((K63-K65)*lookup(K$60,$C$26:$L$26,$C$31:$L$31))-(K65*lookup(K$60,$C$26:$L$26,$C$33:$L$33))),"") -> -17092.769 | ... DS71: =iferror(-(DS70-((DS63-DS65)*lookup(DS$60,$C$26:$L$26,$C$31:$L$31))-(DS65*lookup(DS$60,$C$26:$L$26,$C$33:$L$33))),"") -> -15869.906
B72: Vacancy Loss | D72: =iferror(-sum(D70:D71)*(1-D66),"") -> -21208.312 | E72: =iferror(-sum(E70:E71)*(1-E66),"") -> -21208.312 | F72: =iferror(-sum(F70:F71)*(1-F66),"") -> -21208.312 | G72: =iferror(-sum(G70:G71)*(1-G66),"") -> -21208.312 | H72: =iferror(-sum(H70:H71)*(1-H66),"") -> -21243.653 | I72: =iferror(-sum(I70:I71)*(1-I66),"") -> -21278.995 | J72: =iferror(-sum(J70:J71)*(1-J66),"") -> -21314.337 | K72: =iferror(-sum(K70:K71)*(1-K66),"") -> -21349.679 | ... DS72: =iferror(-sum(DS70:DS71)*(1-DS66),"") -> -25980.048
B73: Offline Renovation Loss | D73: =iferror(-D64*lookup(D$60,$C$26:$L$26,$C$32:$L$32),"") -> 0 | E73: =iferror(-E64*lookup(E$60,$C$26:$L$26,$C$32:$L$32),"") -> 0 | F73: =iferror(-F64*lookup(F$60,$C$26:$L$26,$C$32:$L$32),"") -> 0 | G73: =iferror(-G64*lookup(G$60,$C$26:$L$26,$C$32:$L$32),"") -> -4629.8438 | H73: =iferror(-H64*lookup(H$60,$C$26:$L$26,$C$32:$L$32),"") -> -4629.8438 | I73: =iferror(-I64*lookup(I$60,$C$26:$L$26,$C$32:$L$32),"") -> -4629.8438 | J73: =iferror(-J64*lookup(J$60,$C$26:$L$26,$C$32:$L$32),"") -> -4629.8438 | K73: =iferror(-K64*lookup(K$60,$C$26:$L$26,$C$32:$L$32),"") -> -4629.8438 | ... DS73: =iferror(-DS64*lookup(DS$60,$C$26:$L$26,$C$32:$L$32),"") -> 0
B74: Bad Debt Expense | D74: =iferror(-sum(D70:D73)*lookup(D$60,$C$26:$L$26,$C$35:$L$35),"") -> -3658.4338 | E74: =iferror(-sum(E70:E73)*lookup(E$60,$C$26:$L$26,$C$35:$L$35),"") -> -3658.4338 | F74: =iferror(-sum(F70:F73)*lookup(F$60,$C$26:$L$26,$C$35:$L$35),"") -> -3658.4338 | G74: =iferror(-sum(G70:G73)*lookup(G$60,$C$26:$L$26,$C$35:$L$35),"") -> -3588.9861 | H74: =iferror(-sum(H70:H73)*lookup(H$60,$C$26:$L$26,$C$35:$L$35),"") -> -3595.0826 | I74: =iferror(-sum(I70:I73)*lookup(I$60,$C$26:$L$26,$C$35:$L$35),"") -> -3601.179 | J74: =iferror(-sum(J70:J73)*lookup(J$60,$C$26:$L$26,$C$35:$L$35),"") -> -3607.2755 | K74: =iferror(-sum(K70:K73)*lookup(K$60,$C$26:$L$26,$C$35:$L$35),"") -> -3613.3719 | ... DS74: =iferror(-sum(DS70:DS73)*lookup(DS$60,$C$26:$L$26,$C$35:$L$35),"") -> -4314.5437
B75: Concessions | D75: =iferror(-sum(D70:D73)*lookup(D$60,$C$26:$L$26,$C$36:$L$36),"") -> -3048.6948 | E75: =iferror(-sum(E70:E73)*lookup(E$60,$C$26:$L$26,$C$36:$L$36),"") -> -3048.6948 | F75: =iferror(-sum(F70:F73)*lookup(F$60,$C$26:$L$26,$C$36:$L$36),"") -> -3048.6948 | G75: =iferror(-sum(G70:G73)*lookup(G$60,$C$26:$L$26,$C$36:$L$36),"") -> -2990.8218 | H75: =iferror(-sum(H70:H73)*lookup(H$60,$C$26:$L$26,$C$36:$L$36),"") -> -2995.9021 | I75: =iferror(-sum(I70:I73)*lookup(I$60,$C$26:$L$26,$C$36:$L$36),"") -> -3000.9825 | J75: =iferror(-sum(J70:J73)*lookup(J$60,$C$26:$L$26,$C$36:$L$36),"") -> -3006.0629 | K75: =iferror(-sum(K70:K73)*lookup(K$60,$C$26:$L$26,$C$36:$L$36),"") -> -3011.1433 | ... DS75: =iferror(-sum(DS70:DS73)*lookup(DS$60,$C$26:$L$26,$C$36:$L$36),"") -> -4314.5437
B76: Total Rental Income | D76: =iferror(sum(D70:D75),"") -> 237188.46 | E76: =iferror(sum(E70:E75),"") -> 237188.46 | F76: =iferror(sum(F70:F75),"") -> 237188.46 | G76: =iferror(sum(G70:G75),"") -> 232685.93 | H76: =iferror(sum(H70:H75),"") -> 233081.19 | I76: =iferror(sum(I70:I75),"") -> 233476.44 | J76: =iferror(sum(J70:J75),"") -> 233871.69 | K76: =iferror(sum(K70:K75),"") -> 234266.95 | ... DS76: =iferror(sum(DS70:DS75),"") -> 336534.41
B77: Total RUBS Income | D77: =iferror(((D63*D66)-D64)*lookup(D$60,$C$26:$L$26,$C$28:$L$28),"") -> 15573.76 | E77: =iferror(((E63*E66)-E64)*lookup(E$60,$C$26:$L$26,$C$28:$L$28),"") -> 15573.76 | F77: =iferror(((F63*F66)-F64)*lookup(F$60,$C$26:$L$26,$C$28:$L$28),"") -> 15573.76 | G77: =iferror(((G63*G66)-G64)*lookup(G$60,$C$26:$L$26,$C$28:$L$28),"") -> 15297.76 | H77: =iferror(((H63*H66)-H64)*lookup(H$60,$C$26:$L$26,$C$28:$L$28),"") -> 15297.76 | I77: =iferror(((I63*I66)-I64)*lookup(I$60,$C$26:$L$26,$C$28:$L$28),"") -> 15297.76 | J77: =iferror(((J63*J66)-J64)*lookup(J$60,$C$26:$L$26,$C$28:$L$28),"") -> 15297.76 | K77: =iferror(((K63*K66)-K64)*lookup(K$60,$C$26:$L$26,$C$28:$L$28),"") -> 15297.76 | ... DS77: =iferror(((DS63*DS66)-DS64)*lookup(DS$60,$C$26:$L$26,$C$28:$L$28),"") -> 18814.39
B78: Total Other Income | D78: =iferror(lookup(D$60,$D$41:$M$41,$D$57:$M$57)/12,"") -> 33750 | E78: =iferror(lookup(E$60,$D$41:$M$41,$D$57:$M$57)/12,"") -> 33750 | F78: =iferror(lookup(F$60,$D$41:$M$41,$D$57:$M$57)/12,"") -> 33750 | G78: =iferror(lookup(G$60,$D$41:$M$41,$D$57:$M$57)/12,"") -> 33750 | H78: =iferror(lookup(H$60,$D$41:$M$41,$D$57:$M$57)/12,"") -> 33750 | I78: =iferror(lookup(I$60,$D$41:$M$41,$D$57:$M$57)/12,"") -> 33750 | J78: =iferror(lookup(J$60,$D$41:$M$41,$D$57:$M$57)/12,"") -> 33750 | K78: =iferror(lookup(K$60,$D$41:$M$41,$D$57:$M$57)/12,"") -> 33750 | ... DS78: =iferror(lookup(DS$60,$D$41:$M$41,$D$57:$M$57)/12,"") -> 40334.374
B79: Total Revenue | D79: =iferror(sum(D76:D78),"") -> 286512.22 | E79: =iferror(sum(E76:E78),"") -> 286512.22 | F79: =iferror(sum(F76:F78),"") -> 286512.22 | G79: =iferror(sum(G76:G78),"") -> 281733.69 | H79: =iferror(sum(H76:H78),"") -> 282128.95 | I79: =iferror(sum(I76:I78),"") -> 282524.2 | J79: =iferror(sum(J76:J78),"") -> 282919.45 | K79: =iferror(sum(K76:K78),"") -> 283314.71 | ... DS79: =iferror(sum(DS76:DS78),"") -> 395683.17

Sheet Expenses
M2: Property Expenses
B3: ='Property Summary'!B3 -> Phoenix, AZ | M3: ='Property Summary'!I3 -> Wind River Group
B5: Per Unit Analysis | C5: T-12 | D5: T-12 Per Unit | E5: 1 | F5: 1 | H5: Payroll Assumptions | I5: Hourly | J5: Wage | K5: 0.3 | L5: Total
B6: Total General & Admin | C6: ='Historical Financials'!C21 -> 126768.37 | D6: =iferror(C6/'Unit Mix & Comps'!$D$34,"") -> 688.95853 | E6: 695 | F6: =iferror(E6*'Unit Mix & Comps'!$D$34,"") -> 127880 | H6: Manager | I6: 35 | J6: =iferror(I6*52*40,"") -> 72800 | K6: =iferror(J6*$K$5,"") -> 21840 | L6: =iferror(sum(J6:K6),"") -> 94640
B7: Total Payroll | C7: ='Historical Financials'!C22 -> 324615.54 | D7: =iferror(C7/'Unit Mix & Comps'!$D$34,"") -> 1764.2149 | E7: =L12 -> 1763.4783 | F7: =iferror(E7*'Unit Mix & Comps'!$D$34,"") -> 324480 | H7: Asst Manager | I7: 30 | J7: =iferror(I7*52*40,"") -> 62400 | K7: =iferror(J7*$K$5,"") -> 18720 | L7: =iferror(sum(J7:K7),"") -> 81120
B8: Total Leasing & Marketing | C8: ='Historical Financials'!C23 -> 86807.36 | D8: =iferror(C8/'Unit Mix & Comps'!$D$34,"") -> 471.77913 | E8: 475 | F8: =iferror(E8*'Unit Mix & Comps'!$D$34,"") -> 87400 | H8: Maintenance | I8: 32.5 | J8: =iferror(I8*52*40,"") -> 67600 | K8: =iferror(J8*$K$5,"") -> 20280 | L8: =iferror(sum(J8:K8),"") -> 87880
B9: Total Utilities | C9: ='Historical Financials'!C24 -> 262578.11 | D9: =iferror(C9/'Unit Mix & Comps'!$D$34,"") -> 1427.0549 | E9: 1440 | F9: =iferror(E9*'Unit Mix & Comps'!$D$34,"") -> 264960 | H9: Tech | I9: 22.5 | J9: =iferror(I9*52*40,"") -> 46800 | K9: =iferror(J9*$K$5,"") -> 14040 | L9: =iferror(sum(J9:K9),"") -> 60840
B10: Total Repairs & Maintenance | C10: ='Historical Financials'!C25 -> 55342.64 | D10: =iferror(C10/'Unit Mix & Comps'!$D$34,"") -> 300.77522 | E10: 305 | F10: =iferror(E10*'Unit Mix & Comps'!$D$34,"") -> 56120 | H10: Asst Tech | I10: 0 | J10: =iferror(I10*52*20,"") -> 0 | K10: =iferror(J10*$K$5,"") -> 0 | L10: =iferror(sum(J10:K10),"") -> 0
B11: Total HOA Assessments | C11: ='Historical Financials'!C26 -> 20329.82 | D11: =iferror(C11/'Unit Mix & Comps'!$D$34,"") -> 110.48815 | E11: 115 | F11: =iferror(E11*'Unit Mix & Comps'!$D$34,"") -> 21160 | H11: Total | J11: =iferror(sum(J6:J10),"") -> 249600 | K11: =iferror(sum(K6:K10),"") -> 74880 | L11: =iferror(sum(L6:L10),"") -> 324480
B12: Total Turnover Expense | C12: ='Historical Financials'!C27 -> 22404.11 | D12: =iferror(C12/'Unit Mix & Comps'!$D$34,"") -> 121.76147 | E12: 125 | F12: =iferror(E12*'Unit Mix & Comps'!$D$34,"") -> 23000 | H12: Per unit | L12: =iferror(L11/'Unit Mix & Comps'!D34,"") -> 1763.4783
B13: Total Contract Services | C13: ='Historical Financials'!C28 -> 46032.26 | D13: =iferror(C13/'Unit Mix & Comps'!$D$34,"") -> 250.17533 | E13: 255 | F13: =iferror(E13*'Unit Mix & Comps'!$D$34,"") -> 46920
B14: Total Insurance Expense | C14: ='Historical Financials'!C29 -> 53468.94 | D14: =iferror(C14/'Unit Mix & Comps'!$D$34,"") -> 290.59207 | E14: 295 | F14: =iferror(E14*'Unit Mix & Comps'!$D$34,"") -> 54280
B15: Total Property Taxes | C15: ='Historical Financials'!C30 -> 142164.14 | D15: =iferror(C15/'Unit Mix & Comps'!$D$34,"") -> 772.6312 | E15: =iferror(F15/'Unit Mix & Comps'!$D$34,"") -> 811.26196 | F15: =iferror(if(I26="Manual Override",I24,I23),"") -> 149272.2
B16: Total Management Fees | C16: ='Historical Financials'!C31 -> 104943.81 | D16: =iferror(C16/'Unit Mix & Comps'!$D$34,"") -> 570.34679 | E16: =iferror(F16/'Unit Mix & Comps'!$D$34,"") -> 555.87538 | F16: =D42 -> 102281.07
B17: Total Operating Expenses | C17: ='Historical Financials'!C32 -> 1245455.1 | D17: =iferror(C17/'Unit Mix & Comps'!$D$34,"") -> 6768.7777 | E17: =iferror(sum(E6:E16),"") -> 6835.6156 | F17: =iferror(E17*'Unit Mix & Comps'!$D$34,"") -> 1257753.3
B19: Expense Growth Assumptions | H19: Property Taxes Assessment
B20: Annual Insurance Expense Growth | C20: 0.01 | H20: Purchase Price | I20: ='Project Budget'!G8 -> 36500000
B21: Annual Payroll Expense Growth | C21: 0.025 | H21: Assessed Value (% of Purchase Price) | I21: 0.4
B22: Annual Repairs and Maintenance Expense Growth | C22: 0.025 | H22: Tax Rate (% of Assessed Value) | I22: 0.0317
B23: Tax Reassessment Growth | C23: 0.05 | H23: Assessed Year 1 Property Tax | I23: =iferror(I20*I21*I22,"") -> 462820
B24: Annual Tax Expense Growth | C24: 0.01 | H24: Manual Override | I24: =142164*1.05 -> 149272.2
B25: All Other Expense Growth | C25: 0.025 | H25: Years Between Reassessment | I25: 1 | J25: First Reassessment Year | K25: 2
B26: Property Management Fee (% of Total Revenue) | C26: 0.03 | H26: Method Used | I26: Manual Override | J26: Must be greater than 1
B28: Projected Annual Expenses
C31: T-12 | D31: 1 | E31: 2 | F31: 3 | G31: 4 | H31: 5 | I31: 6 | J31: 7 | K31: 8 | L31: 9 | M31: 10
B32: Total General & Admin | C32: ='Historical Financials'!C21 -> 126768.37 | D32: =iferror(F6,"") -> 127880 | E32: =iferror(D32*(1+$C$25),"") -> 131077 | F32: =iferror(E32*(1+$C$25),"") -> 134353.92 | G32: =iferror(F32*(1+$C$25),"") -> 137712.77 | H32: =iferror(G32*(1+$C$25),"") -> 141155.59 | I32: =iferror(H32*(1+$C$25),"") -> 144684.48 | J32: =iferror(I32*(1+$C$25),"") -> 148301.59 | K32: =iferror(J32*(1+$C$25),"") -> 152009.13 | L32: =iferror(K32*(1+$C$25),"") -> 155809.36 | M32: =iferror(L32*(1+$C$25),"") -> 159704.6
B33: Total Payroll | C33: ='Historical Financials'!C22 -> 324615.54 | D33: =iferror(F7,"") -> 324480 | E33: =iferror(D33*(1+$C$21),"") -> 332592 | F33: =iferror(E33*(1+$C$21),"") -> 340906.8 | G33: =iferror(F33*(1+$C$21),"") -> 349429.47 | H33: =iferror(G33*(1+$C$21),"") -> 358165.21 | I33: =iferror(H33*(1+$C$21),"") -> 367119.34 | J33: =iferror(I33*(1+$C$21),"") -> 376297.32 | K33: =iferror(J33*(1+$C$21),"") -> 385704.75 | L33: =iferror(K33*(1+$C$21),"") -> 395347.37 | M33: =iferror(L33*(1+$C$21),"") -> 405231.06
B34: Total Leasing & Marketing | C34: ='Historical Financials'!C23 -> 86807.36 | D34: =iferror(F8,"") -> 87400 | E34: =iferror(D34*(1+$C$25),"") -> 89585 | F34: =iferror(E34*(1+$C$25),"") -> 91824.625 | G34: =iferror(F34*(1+$C$25),"") -> 94120.241 | H34: =iferror(G34*(1+$C$25),"") -> 96473.247 | I34: =iferror(H34*(1+$C$25),"") -> 98885.078 | J34: =iferror(I34*(1+$C$25),"") -> 101357.2 | K34: =iferror(J34*(1+$C$25),"") -> 103891.13 | L34: =iferror(K34*(1+$C$25),"") -> 106488.41 | M34: =iferror(L34*(1+$C$25),"") -> 109150.62
B35: Total Utilities | C35: ='Historical Financials'!C24 -> 262578.11 | D35: =iferror(F9,"") -> 264960 | E35: =iferror(D35*(1+$C$25),"") -> 271584 | F35: =iferror(E35*(1+$C$25),"") -> 278373.6 | G35: =iferror(F35*(1+$C$25),"") -> 285332.94 | H35: =iferror(G35*(1+$C$25),"") -> 292466.26 | I35: =iferror(H35*(1+$C$25),"") -> 299777.92 | J35: =iferror(I35*(1+$C$25),"") -> 307272.37 | K35: =iferror(J35*(1+$C$25),"") -> 314954.18 | L35: =iferror(K35*(1+$C$25),"") -> 322828.03 | M35: =iferror(L35*(1+$C$25),"") -> 330898.73
B36: Total Repairs & Maintenance | C36: ='Historical Financials'!C25 -> 55342.64 | D36: =iferror(F10,"") -> 56120 | E36: =iferror(D36*(1+$C$22),"") -> 57523 | F36: =iferror(E36*(1+$C$22),"") -> 58961.075 | G36: =iferror(F36*(1+$C$22),"") -> 60435.102 | H36: =iferror(G36*(1+$C$22),"") -> 61945.979 | I36: =iferror(H36*(1+$C$22),"") -> 63494.629 | J36: =iferror(I36*(1+$C$22),"") -> 65081.995 | K36: =iferror(J36*(1+$C$22),"") -> 66709.045 | L36: =iferror(K36*(1+$C$22),"") -> 68376.771 | M36: =iferror(L36*(1+$C$22),"") -> 70086.19
B37: Total Supply Expense | C37: ='Historical Financials'!C26 -> 20329.82 | D37: =iferror(F11,"") -> 21160 | E37: =iferror(D37*(1+$C$25),"") -> 21689 | F37: =iferror(E37*(1+$C$25),"") -> 22231.225 | G37: =iferror(F37*(1+$C$25),"") -> 22787.006 | H37: =iferror(G37*(1+$C$25),"") -> 23356.681 | I37: =iferror(H37*(1+$C$25),"") -> 23940.598 | J37: =iferror(I37*(1+$C$25),"") -> 24539.113 | K37: =iferror(J37*(1+$C$25),"") -> 25152.591 | L37: =iferror(K37*(1+$C$25),"") -> 25781.405 | M37: =iferror(L37*(1+$C$25),"") -> 26425.94
B38: Total Turnover Expense | C38: ='Historical Financials'!C27 -> 22404.11 | D38: =iferror(F12,"") -> 23000 | E38: =iferror(D38*(1+$C$25),"") -> 23575 | F38: =iferror(E38*(1+$C$25),"") -> 24164.375 | G38: =iferror(F38*(1+$C$25),"") -> 24768.484 | H38: =iferror(G38*(1+$C$25),"") -> 25387.696 | I38: =iferror(H38*(1+$C$25),"") -> 26022.389 | J38: =iferror(I38*(1+$C$25),"") -> 26672.949 | K38: =iferror(J38*(1+$C$25),"") -> 27339.772 | L38: =iferror(K38*(1+$C$25),"") -> 28023.267 | M38: =iferror(L38*(1+$C$25),"") -> 28723.848
B39: Total Contract Services | C39: ='Historical Financials'!C28 -> 46032.26 | D39: =iferror(F13,"") -> 46920 | E39: =iferror(D39*(1+$C$25),"") -> 48093 | F39: =iferror(E39*(1+$C$25),"") -> 49295.325 | G39: =iferror(F39*(1+$C$25),"") -> 50527.708 | H39: =iferror(G39*(1+$C$25),"") -> 51790.901 | I39: =iferror(H39*(1+$C$25),"") -> 53085.673 | J39: =iferror(I39*(1+$C$25),"") -> 54412.815 | K39: =iferror(J39*(1+$C$25),"") -> 55773.136 | L39: =iferror(K39*(1+$C$25),"") -> 57167.464 | M39: =iferror(L39*(1+$C$25),"") -> 58596.651
B40: Total Insurance Expense | C40: ='Historical Financials'!C29 -> 53468.94 | D40: =iferror(F14,"") -> 54280 | E40: =iferror(D40*(1+$C$20),"") -> 54822.8 | F40: =iferror(E40*(1+$C$20),"") -> 55371.028 | G40: =iferror(F40*(1+$C$20),"") -> 55924.738 | H40: =iferror(G40*(1+$C$20),"") -> 56483.986 | I40: =iferror(H40*(1+$C$20),"") -> 57048.826 | J40: =iferror(I40*(1+$C$20),"") -> 57619.314 | K40: =iferror(J40*(1+$C$20),"") -> 58195.507 | L40: =iferror(K40*(1+$C$20),"") -> 58777.462 | M40: =iferror(L40*(1+$C$20),"") -> 59365.237
B41: Total Property Taxes | C41: ='Historical Financials'!C30 -> 142164.14 | D41: =iferror(F15,"") -> 149272.2 | E41: =iferror(if(E45="Yes",D41*(1+$C$23),D41*(1+$C$24)),"") -> 156735.81 | F41: =iferror(if(F45="Yes",E41*(1+$C$23),E41*(1+$C$24)),"") -> 164572.6 | G41: =iferror(if(G45="Yes",F41*(1+$C$23),F41*(1+$C$24)),"") -> 172801.23 | H41: =iferror(if(H45="Yes",G41*(1+$C$23),G41*(1+$C$24)),"") -> 181441.29 | I41: =iferror(if(I45="Yes",H41*(1+$C$23),H41*(1+$C$24)),"") -> 190513.36 | J41: =iferror(if(J45="Yes",I41*(1+$C$23),I41*(1+$C$24)),"") -> 200039.02 | K41: =iferror(if(K45="Yes",J41*(1+$C$23),J41*(1+$C$24)),"") -> 202039.41 | L41: =iferror(if(L45="Yes",K41*(1+$C$23),K41*(1+$C$24)),"") -> 204059.81 | M41: =iferror(if(M45="Yes",L41*(1+$C$23),L41*(1+$C$24)),"") -> 206100.41
B42: Total Management Fees | C42: ='Historical Financials'!C31 -> 104943.81 | D42: =iferror(lookup(D$31,Revenue!$D$41:$M$41,Revenue!$D$58:$M$58)*$C$26,"") -> 102281.07 | E42: =iferror(lookup(E$31,Revenue!$D$41:$M$41,Revenue!$D$58:$M$58)*$C$26,"") -> 107659.79 | F42: =iferror(lookup(F$31,Revenue!$D$41:$M$41,Revenue!$D$58:$M$58)*$C$26,"") -> 113762 | G42: =iferror(lookup(G$31,Revenue!$D$41:$M$41,Revenue!$D$58:$M$58)*$C$26,"") -> 117465.61 | H42: =iferror(lookup(H$31,Revenue!$D$41:$M$41,Revenue!$D$58:$M$58)*$C$26,"") -> 121293.29 | I42: =iferror(lookup(I$31,Revenue!$D$41:$M$41,Revenue!$D$58:$M$58)*$C$26,"") -> 125249.26 | J42: =iferror(lookup(J$31,Revenue!$D$41:$M$41,Revenue!$D$58:$M$58)*$C$26,"") -> 129337.9 | K42: =iferror(lookup(K$31,Revenue!$D$41:$M$41,Revenue!$D$58:$M$58)*$C$26,"") -> 133563.75 | ... M42: =iferror(lookup(M$31,Revenue!$D$41:$M$41,Revenue!$D$58:$M$58)*$C$26,"") -> 142445.94
B43: Total Operating Expenses | C43: ='Historical Financials'!C32 -> 1245455.1 | D43: =iferror(sum(D32:D42),"") -> 1257753.3 | E43: =iferror(sum(E32:E42),"") -> 1294936.4 | F43: =iferror(sum(F32:F42),"") -> 1333816.6 | G43: =iferror(sum(G32:G42),"") -> 1371305.3 | H43: =iferror(sum(H32:H42),"") -> 1409960.1 | I43: =iferror(sum(I32:I42),"") -> 1449821.5 | J43: =iferror(sum(J32:J42),"") -> 1490931.6 | K43: =iferror(sum(K32:K42),"") -> 1525332.4 | ... M43: =iferror(sum(M32:M42),"") -> 1596729.2
B44: Expense Ratio | C44: ='Historical Financials'!C33 -> 0.36493849 | D44: =iferror(D43/lookup(D$31,Revenue!$D$41:$M$41,Revenue!$D$58:$M$58),"") -> 0.36891086 | E44: =iferror(E43/lookup(E$31,Revenue!$D$41:$M$41,Revenue!$D$58:$M$58),"") -> 0.36084124 | F44: =iferror(F43/lookup(F$31,Revenue!$D$41:$M$41,Revenue!$D$58:$M$58),"") -> 0.35173869 | G44: =iferror(G43/lookup(G$31,Revenue!$D$41:$M$41,Revenue!$D$58:$M$58),"") -> 0.350223 | H44: =iferror(H43/lookup(H$31,Revenue!$D$41:$M$41,Revenue!$D$58:$M$58),"") -> 0.34873161 | I44: =iferror(I43/lookup(I$31,Revenue!$D$41:$M$41,Revenue!$D$58:$M$58),"") -> 0.3472647 | J44: =iferror(J43/lookup(J$31,Revenue!$D$41:$M$41,Revenue!$D$58:$M$58),"") -> 0.34582243 | K44: =iferror(K43/lookup(K$31,Revenue!$D$41:$M$41,Revenue!$D$58:$M$58),"") -> 0.34260772 | ... M44: =iferror(M43/lookup(M$31,Revenue!$D$41:$M$41,Revenue!$D$58:$M$58),"") -> 0.33628109
B45: Reassessment Year | D45: =iferror(ifs(D$31=$K$25,"Yes",$K$25+($I$25*1)=D$31,"Yes",$K$25+($I$25*2)=D$31,"Yes",$K$25+($I$25*3)=D$31,"Yes",$K$25+($I$25*4)=D$31,"Yes",$K$25+($I$25*5)=D$31,"Yes"),"No") -> No | E45: =iferror(ifs(E$31=$K$25,"Yes",$K$25+($I$25*1)=E$31,"Yes",$K$25+($I$25*2)=E$31,"Yes",$K$25+($I$25*3)=E$31,"Yes",$K$25+($I$25*4)=E$31,"Yes",$K$25+($I$25*5)=E$31,"Yes"),"No") -> Yes | F45: =iferror(ifs(F$31=$K$25,"Yes",$K$25+($I$25*1)=F$31,"Yes",$K$25+($I$25*2)=F$31,"Yes",$K$25+($I$25*3)=F$31,"Yes",$K$25+($I$25*4)=F$31,"Yes",$K$25+($I$25*5)=F$31,"Yes"),"No") -> Yes | G45: =iferror(ifs(G$31=$K$25,"Yes",$K$25+($I$25*1)=G$31,"Yes",$K$25+($I$25*2)=G$31,"Yes",$K$25+($I$25*3)=G$31,"Yes",$K$25+($I$25*4)=G$31,"Yes",$K$25+($I$25*5)=G$31,"Yes"),"No") -> Yes | H45: =iferror(ifs(H$31=$K$25,"Yes",$K$25+($I$25*1)=H$31,"Yes",$K$25+($I$25*2)=H$31,"Yes",$K$25+($I$25*3)=H$31,"Yes",$K$25+($I$25*4)=H$31,"Yes",$K$25+($I$25*5)=H$31,"Yes"),"No") -> Yes | I45: =iferror(ifs(I$31=$K$25,"Yes",$K$25+($I$25*1)=I$31,"Yes",$K$25+($I$25*2)=I$31,"Yes",$K$25+($I$25*3)=I$31,"Yes",$K$25+($I$25*4)=I$31,"Yes",$K$25+($I$25*5)=I$31,"Yes"),"No") -> Yes | J45: =iferror(ifs(J$31=$K$25,"Yes",$K$25+($I$25*1)=J$31,"Yes",$K$25+($I$25*2)=J$31,"Yes",$K$25+($I$25*3)=J$31,"Yes",$K$25+($I$25*4)=J$31,"Yes",$K$25+($I$25*5)=J$31,"Yes"),"No") -> Yes | K45: =iferror(ifs(K$31=$K$25,"Yes",$K$25+($I$25*1)=K$31,"Yes",$K$25+($I$25*2)=K$31,"Yes",$K$25+($I$25*3)=K$31,"Yes",$K$25+($I$25*4)=K$31,"Yes",$K$25+($I$25*5)=K$31,"Yes"),"No") -> No | ... M45: =iferror(ifs(M$31=$K$25,"Yes",$K$25+($I$25*1)=M$31,"Yes",$K$25+($I$25*2)=M$31,"Yes",$K$25+($I$25*3)=M$31,"Yes",$K$25+($I$25*4)=M$31,"Yes",$K$25+($I$25*5)=M$31,"Yes"),"No") -> No

Sheet CapEx
K2: CapEx Budget
B3: ='Property Summary'!B3 -> Phoenix, AZ | K3: ='Property Summary'!I3 -> Wind River Group
B5: Unit Renovations | J5: Item | K5: Cost
B6: Unit Type / SF | C6: Available Units | D6: Renovation Units | E6: Cost Per Unit | F6: Total Cost | G6: Rent Premium after Renovation | H6: Renovation ROI (Increase over Current) | J6: Black Appliances | K6: 1800
B7: ='Unit Mix & Comps'!B7&", "&'Unit Mix & Comps'!C7&" SF" -> 1 Bed- Classic, 678 SF | C7: ='Unit Mix & Comps'!D7 -> 16 | D7: ='Unit Mix & Comps'!F7 -> 10 | E7: 11000 | F7: =iferror(E7*D7,"") -> 110000 | G7: ='Unit Mix & Comps'!Q7 -> 224 | H7: =iferror((G7*12)/E7,"") -> 0.24436364 | J7: Vinyl Flooring | K7: 2000
B8: ='Unit Mix & Comps'!B8&", "&'Unit Mix & Comps'!C8&" SF" -> 1 Bed PU, 678 SF | C8: ='Unit Mix & Comps'!D8 -> 2 | D8: ='Unit Mix & Comps'!F8 | F8: =iferror(E8*D8,"") -> 0 | G8: ='Unit Mix & Comps'!Q8 | H8: =iferror((G8*12)/E8,"") | J8: Hardware/Fixtures | K8: 1000
B9: ='Unit Mix & Comps'!B9&", "&'Unit Mix & Comps'!C9&" SF" -> 1 Bed U, 678 SF | C9: ='Unit Mix & Comps'!D9 -> 30 | D9: ='Unit Mix & Comps'!F9 | F9: =iferror(E9*D9,"") -> 0 | G9: ='Unit Mix & Comps'!Q9 | H9: =iferror((G9*12)/E9,"") | J9: Cabinet Fronts | K9: 1100
B10: ='Unit Mix & Comps'!B10&", "&'Unit Mix & Comps'!C10&" SF" -> 1 Bed Classic, 734 SF | C10: ='Unit Mix & Comps'!D10 -> 9 | D10: ='Unit Mix & Comps'!F10 -> 9 | E10: 11000 | F10: =iferror(E10*D10,"") -> 99000 | G10: ='Unit Mix & Comps'!Q10 -> 151 | H10: =iferror((G10*12)/E10,"") -> 0.16472727 | J10: Backsplash | K10: 0
B11: ='Unit Mix & Comps'!B11&", "&'Unit Mix & Comps'!C11&" SF" -> 1 Bed PU, 734 SF | C11: ='Unit Mix & Comps'!D11 -> 1 | D11: ='Unit Mix & Comps'!F11 | F11: =iferror(E11*D11,"") -> 0 | G11: ='Unit Mix & Comps'!Q11 | H11: =iferror((G11*12)/E11,"") | J11: Granite Style Counters | K11: 1100
B12: ='Unit Mix & Comps'!B12&", "&'Unit Mix & Comps'!C12&" SF" -> 1 Bed U, 734 SF | C12: ='Unit Mix & Comps'!D12 -> 14 | D12: ='Unit Mix & Comps'!F12 | F12: =iferror(E12*D12,"") -> 0 | G12: ='Unit Mix & Comps'!Q12 | H12: =iferror((G12*12)/E12,"") | J12: Paint | K12: 700
B13: ='Unit Mix & Comps'!B13&", "&'Unit Mix & Comps'!C13&" SF" -> 1 Bed C, 771 SF | C13: ='Unit Mix & Comps'!D13 -> 13 | D13: ='Unit Mix & Comps'!F13 -> 10 | E13: 12500 | F13: =iferror(E13*D13,"") -> 125000 | G13: ='Unit Mix & Comps'!Q13 -> 132 | H13: =iferror((G13*12)/E13,"") -> 0.12672 | J13: Lighting | K13: 500
B14: ='Unit Mix & Comps'!B14&", "&'Unit Mix & Comps'!C14&" SF" -> 1 Bed PU, 771 SF | C14: ='Unit Mix & Comps'!D14 -> 1 | D14: ='Unit Mix & Comps'!F14 | F14: =iferror(E14*D14,"") -> 0 | G14: ='Unit Mix & Comps'!Q14 | H14: =iferror((G14*12)/E14,"") | J14: WD Connections | K14: 0
B15: ='Unit Mix & Comps'!B15&", "&'Unit Mix & Comps'!C15&" SF" -> 1 Bed U, 771 SF | C15: ='Unit Mix & Comps'!D15 -> 9 | D15: ='Unit Mix & Comps'!F15 | F15: =iferror(E15*D15,"") -> 0 | G15: ='Unit Mix & Comps'!Q15 | H15: =iferror((G15*12)/E15,"") | J15: WD Units | K15: 0
B16: ='Unit Mix & Comps'!B16&", "&'Unit Mix & Comps'!C16&" SF" -> 2B / 1B -C, 863 SF | C16: ='Unit Mix & Comps'!D16 -> 9 | D16: ='Unit Mix & Comps'!F16 -> 10 | E16: 13000 | F16: =iferror(E16*D16,"") -> 130000 | G16: ='Unit Mix & Comps'!Q16 -> 248 | H16: =iferror((G16*12)/E16,"") -> 0.22892308 | J16: Bathroom | K16: 600
B17: ='Unit Mix & Comps'!B17&", "&'Unit Mix & Comps'!C17&" SF" -> 2B / 1B -E, 863 SF | C17: ='Unit Mix & Comps'!D17 -> 1 | D17: ='Unit Mix & Comps'!F17 | F17: =iferror(E17*D17,"") -> 0 | G17: ='Unit Mix & Comps'!Q17 | H17: =iferror((G17*12)/E17,"") | J17: Smart Home | K17: 200
B18: ='Unit Mix & Comps'!B18&", "&'Unit Mix & Comps'!C18&" SF" -> 2B / 1B -U, 863 SF | C18: ='Unit Mix & Comps'!D18 -> 14 | D18: ='Unit Mix & Comps'!F18 | F18: =iferror(E18*D18,"") -> 0 | G18: ='Unit Mix & Comps'!Q18 | H18: =iferror((G18*12)/E18,"") | J18: Labor | K18: 2000
B19: ='Unit Mix & Comps'!B19&", "&'Unit Mix & Comps'!C19&" SF" -> 2B/ 2B- C, 958 SF | C19: ='Unit Mix & Comps'!D19 -> 4 | D19: ='Unit Mix & Comps'!F19 | F19: =iferror(E19*D19,"") -> 0 | G19: ='Unit Mix & Comps'!Q19 | H19: =iferror((G19*12)/E19,"") | J19: Other | K19: 0
B20: ='Unit Mix & Comps'!B20&", "&'Unit Mix & Comps'!C20&" SF" -> 2B/ 2B- PU, 958 SF | C20: ='Unit Mix & Comps'!D20 -> 3 | D20: ='Unit Mix & Comps'!F20 | F20: =iferror(E20*D20,"") -> 0 | G20: ='Unit Mix & Comps'!Q20 | H20: =iferror((G20*12)/E20,"") | J20: Total | K20: =SUM(K6:K19) -> 11000
B21: ='Unit Mix & Comps'!B21&", "&'Unit Mix & Comps'!C21&" SF" -> 2B/ 2B- U, 958 SF | C21: ='Unit Mix & Comps'!D21 -> 9 | D21: ='Unit Mix & Comps'!F21 | F21: =iferror(E21*D21,"") -> 0 | G21: ='Unit Mix & Comps'!Q21 | H21: =iferror((G21*12)/E21,"")
B22: ='Unit Mix & Comps'!B22&", "&'Unit Mix & Comps'!C22&" SF" -> 2B/2B C, 1000 SF | C22: ='Unit Mix & Comps'!D22 -> 7 | D22: ='Unit Mix & Comps'!F22 -> 7 | E22: 14000 | F22: =iferror(E22*D22,"") -> 98000 | G22: ='Unit Mix & Comps'!Q22 -> 230 | H22: =iferror((G22*12)/E22,"") -> 0.19714286
B23: ='Unit Mix & Comps'!B23&", "&'Unit Mix & Comps'!C23&" SF" -> 2B/ 2B- PU, 1000 SF | C23: ='Unit Mix & Comps'!D23 -> 3 | D23: ='Unit Mix & Comps'!F23 | F23: =iferror(E23*D23,"") -> 0 | G23: ='Unit Mix & Comps'!Q23 | H23: =iferror((G23*12)/E23,"")
B24: ='Unit Mix & Comps'!B24&", "&'Unit Mix & Comps'!C24&" SF" -> 2B/ 2B- U, 1000 SF | C24: ='Unit Mix & Comps'!D24 -> 22 | D24: ='Unit Mix & Comps'!F24 | F24: =iferror(E24*D24,"") -> 0 | G24: ='Unit Mix & Comps'!Q24 | H24: =iferror((G24*12)/E24,"")
B25: ='Unit Mix & Comps'!B25&", "&'Unit Mix & Comps'!C25&" SF" -> 2B/2B C, 1040 SF | C25: ='Unit Mix & Comps'!D25 -> 3 | D25: ='Unit Mix & Comps'!F25 -> 3 | E25: 14500 | F25: =iferror(E25*D25,"") -> 43500 | G25: ='Unit Mix & Comps'!Q25 -> 198 | H25: =iferror((G25*12)/E25,"") -> 0.16386207
B26: ='Unit Mix & Comps'!B26&", "&'Unit Mix & Comps'!C26&" SF" -> 2B/ 2B- PU, 1040 SF | C26: ='Unit Mix & Comps'!D26 -> 1 | D26: ='Unit Mix & Comps'!F26 | F26: =iferror(E26*D26,"") -> 0 | G26: ='Unit Mix & Comps'!Q26 | H26: =iferror((G26*12)/E26,"")
B27: ='Unit Mix & Comps'!B27&", "&'Unit Mix & Comps'!C27&" SF" -> 2B/ 2B- U, 1040 SF | C27: ='Unit Mix & Comps'!D27 -> 13 | D27: ='Unit Mix & Comps'!F27 | F27: =iferror(E27*D27,"") -> 0 | G27: ='Unit Mix & Comps'!Q27 | H27: =iferror((G27*12)/E27,"")
B28: Total / Average | C28: =iferror(sum(C7:C27),"") -> 184 | D28: =iferror(sum(D7:D27),"") -> 49 | E28: =iferror(F28/D28,"") -> 12357.143 | F28: =iferror(sum(F7:F27),"") -> 605500 | H28: =iferror((sumproduct(G7:G27,D7:D27)*12)/F28,"") -> 0.19031544 | J28: Sourcing From China | K28: Cost
J29: Stainless Steel | K29: 1000
B30: General Improvements | J30: Vinyl Flooring | K30: 350
B31: Item | C31: Quantity | D31: Cost Per Item | E31: Total Cost | F31: Details | J31: Hardware/Fixtures | K31: 300
B32: Exterior Wood Repairs | C32: 0 | D32: 83600 | E32: =iferror(C32*D32,"") -> 0 | J32: Cabinet Fronts | K32: 400
B33: Package hub | C33: 0 | D33: 15000 | E33: =iferror(C33*D33,"") -> 0 | J33: Backsplash | K33: 100
B34: Asphalt | C34: 0 | D34: 70000 | E34: =iferror(C34*D34,"") -> 0 | J34: Granite Counters | K34: 500
B35: Dog Park Improvements | C35: 0 | D35: 0 | E35: =iferror(C35*D35,"") -> 0 | J35: Paint | K35: 700
B36: Exterior lighting & Breezeway Lighting | C36: 0 | D36: 4570 | E36: =iferror(C36*D36,"") -> 0 | J36: Lighting | K36: 150
B37: Security Cameras in Common Areas | C37: 0 | D37: 13407 | E37: =iferror(C37*D37,"") -> 0 | J37: WD Connections | K37: 0
B38: Paint exterior | C38: 0 | D38: 174500 | E38: =iferror(C38*D38,"") -> 0 | J38: WD Units | K38: 500
B39: Property signage | C39: 0 | D39: 2981 | E39: =iferror(C39*D39,"") -> 0 | J39: Bathroom | K39: 200
B40: Landscaping | C40: 0 | D40: 24555 | E40: =iferror(C40*D40,"") -> 0 | J40: Smart Home | K40: 100
B41: Concrete Repairs (including steps) | C41: 0 | D41: 20625 | E41: =iferror(C41*D41,"") -> 0 | J41: Labor | K41: 2500
B42: Leasing office Exterior | C42: 0 | D42: 25000 | E42: =iferror(C42*D42,"") -> 0 | J42: Other | K42: 0
B43: Mailboxes | C43: 0 | D43: 28000 | E43: =iferror(C43*D43,"") -> 0 | J43: Total | K43: =SUM(K29:K42) -> 6800
B44: Fitness Center Equipment Upgrade | C44: 0 | D44: 28000 | E44: =iferror(C44*D44,"") -> 0
B45: Gym Flooring & Gym Refresh | C45: 0 | D45: 6800 | E45: =iferror(C45*D45,"") -> 0
B46: Laundry Room Refresh | C46: 0 | D46: 800 | E46: =iferror(C46*D46,"") -> 0
B47: Key Fob System | C47: 0 | D47: 28042 | E47: =iferror(C47*D47,"") -> 0
B48: Leasing Office Interior Updates | C48: 0 | D48: 10000 | E48: =iferror(C48*D48,"") -> 0
B49: Shed for Cart | C49: 0 | D49: 0 | E49: =iferror(C49*D49,"") -> 0
B50: Metal Railing | C50: 0 | D50: 10000 | E50: =iferror(C50*D50,"") -> 0
B51: MISC | C51: 1 | D51: 500000 | E51: =iferror(C51*D51,"") -> 500000
B52: Total | E52: =sum(E32:E51) -> 500000

Sheet Project Budget
G2: Project Budget
B3: ='Property Summary'!B3 -> Phoenix, AZ | G3: ='Property Summary'!I3 -> Wind River Group
I5: =ROUNDUP(I6/12,0) -> 0 | J5: =ROUNDUP(J6/12,0) -> 1 | K5: =ROUNDUP(K6/12,0) -> 1 | L5: =ROUNDUP(L6/12,0) -> 1 | M5: =ROUNDUP(M6/12,0) -> 1 | N5: =ROUNDUP(N6/12,0) -> 1 | O5: =ROUNDUP(O6/12,0) -> 1 | P5: =ROUNDUP(P6/12,0) -> 1 | ... DY5: =ROUNDUP(DY6/12,0) -> 10
E6: =iferror('Unit Mix & Comps'!C34,"") -> 153613 | F6: =iferror('Unit Mix & Comps'!D34,"") -> 184 | I6: 0 | J6: =I6+1 -> 1 | K6: =J6+1 -> 2 | L6: =K6+1 -> 3 | M6: =L6+1 -> 4 | N6: =M6+1 -> 5 | O6: =N6+1 -> 6 | P6: =O6+1 -> 7 | Q6: =P6+1 -> 8 | ... DY6: =DX6+1 -> 120
B7: Acquisition Cost | C7: Start | D7: Duration | E7: /SF | F7: /Unit | G7: Amount | H7: Error Check | I7: ='Investment Summary'!G7 -> 45838 | J7: =EOMONTH(I7,1) -> 45869 | K7: =EOMONTH(J7,1) -> 45900 | L7: =EOMONTH(K7,1) -> 45930 | M7: =EOMONTH(L7,1) -> 45961 | N7: =EOMONTH(M7,1) -> 45991 | O7: =EOMONTH(N7,1) -> 46022 | P7: =EOMONTH(O7,1) -> 46053 | Q7: =EOMONTH(P7,1) -> 46081 | ... DY7: =EOMONTH(DX7,1) -> 49490
B8: Purchase Price | C8: 0 | D8: 1 | E8: =iferror(G8/$E$6,"") -> 237.6101 | F8: =iferror(G8/$F$6,"") -> 198369.57 | G8: 36500000 | H8: =IF(SUM(I8:DY8)=G8,"OK","FALSE") -> OK | I8: =IF(AND($C8=0,$D8=0,I$6=0),$G8,IF(AND(I$6>=$C8,I$6<($C8+$D8)),$G8/$D8,0)) -> 36500000 | J8: =IF(AND($C8=0,$D8=0,J$6=0),$G8,IF(AND(J$6>=$C8,J$6<($C8+$D8)),$G8/$D8,0)) -> 0 | K8: =IF(AND($C8=0,$D8=0,K$6=0),$G8,IF(AND(K$6>=$C8,K$6<($C8+$D8)),$G8/$D8,0)) -> 0 | L8: =IF(AND($C8=0,$D8=0,L$6=0),$G8,IF(AND(L$6>=$C8,L$6<($C8+$D8)),$G8/$D8,0)) -> 0 | M8: =IF(AND($C8=0,$D8=0,M$6=0),$G8,IF(AND(M$6>=$C8,M$6<($C8+$D8)),$G8/$D8,0)) -> 0 | N8: =IF(AND($C8=0,$D8=0,N$6=0),$G8,IF(AND(N$6>=$C8,N$6<($C8+$D8)),$G8/$D8,0)) -> 0 | O8: =IF(AND($C8=0,$D8=0,O$6=0),$G8,IF(AND(O$6>=$C8,O$6<($C8+$D8)),$G8/$D8,0)) -> 0 | P8: =IF(AND($C8=0,$D8=0,P$6=0),$G8,IF(AND(P$6>=$C8,P$6<($C8+$D8)),$G8/$D8,0)) -> 0 | ... DY8: =IF(AND($C8=0,$D8=0,DY$6=0),$G8,IF(AND(DY$6>=$C8,DY$6<($C8+$D8)),$G8/$D8,0)) -> 0
B9: Seller Credit | C9: 0 | D9: 1 | E9: =iferror(G9/$E$6,"") -> -0.32549329 | F9: =iferror(G9/$F$6,"") -> -271.73913 | G9: -50000 | H9: =IF(SUM(I9:DY9)=G9,"OK","FALSE") -> OK | I9: =IF(AND($C9=0,$D9=0,I$6=0),$G9,IF(AND(I$6>=$C9,I$6<($C9+$D9)),$G9/$D9,0)) -> -50000 | J9: =IF(AND($C9=0,$D9=0,J$6=0),$G9,IF(AND(J$6>=$C9,J$6<($C9+$D9)),$G9/$D9,0)) -> 0 | K9: =IF(AND($C9=0,$D9=0,K$6=0),$G9,IF(AND(K$6>=$C9,K$6<($C9+$D9)),$G9/$D9,0)) -> 0 | L9: =IF(AND($C9=0,$D9=0,L$6=0),$G9,IF(AND(L$6>=$C9,L$6<($C9+$D9)),$G9/$D9,0)) -> 0 | M9: =IF(AND($C9=0,$D9=0,M$6=0),$G9,IF(AND(M$6>=$C9,M$6<($C9+$D9)),$G9/$D9,0)) -> 0 | N9: =IF(AND($C9=0,$D9=0,N$6=0),$G9,IF(AND(N$6>=$C9,N$6<($C9+$D9)),$G9/$D9,0)) -> 0 | O9: =IF(AND($C9=0,$D9=0,O$6=0),$G9,IF(AND(O$6>=$C9,O$6<($C9+$D9)),$G9/$D9,0)) -> 0 | P9: =IF(AND($C9=0,$D9=0,P$6=0),$G9,IF(AND(P$6>=$C9,P$6<($C9+$D9)),$G9/$D9,0)) -> 0 | ... DY9: =IF(AND($C9=0,$D9=0,DY$6=0),$G9,IF(AND(DY$6>=$C9,DY$6<($C9+$D9)),$G9/$D9,0)) -> 0
B10: Buyer Legal | C10: 0 | D10: 1 | E10: =iferror(G10/$E$6,"") -> 0.65098657 | F10: =iferror(G10/$F$6,"") -> 543.47826 | G10: 100000 | H10: =IF(SUM(I10:DY10)=G10,"OK","FALSE") -> OK | I10: =IF(AND($C10=0,$D10=0,I$6=0),$G10,IF(AND(I$6>=$C10,I$6<($C10+$D10)),$G10/$D10,0)) -> 100000 | J10: =IF(AND($C10=0,$D10=0,J$6=0),$G10,IF(AND(J$6>=$C10,J$6<($C10+$D10)),$G10/$D10,0)) -> 0 | K10: =IF(AND($C10=0,$D10=0,K$6=0),$G10,IF(AND(K$6>=$C10,K$6<($C10+$D10)),$G10/$D10,0)) -> 0 | L10: =IF(AND($C10=0,$D10=0,L$6=0),$G10,IF(AND(L$6>=$C10,L$6<($C10+$D10)),$G10/$D10,0)) -> 0 | M10: =IF(AND($C10=0,$D10=0,M$6=0),$G10,IF(AND(M$6>=$C10,M$6<($C10+$D10)),$G10/$D10,0)) -> 0 | N10: =IF(AND($C10=0,$D10=0,N$6=0),$G10,IF(AND(N$6>=$C10,N$6<($C10+$D10)),$G10/$D10,0)) -> 0 | O10: =IF(AND($C10=0,$D10=0,O$6=0),$G10,IF(AND(O$6>=$C10,O$6<($C10+$D10)),$G10/$D10,0)) -> 0 | P10: =IF(AND($C10=0,$D10=0,P$6=0),$G10,IF(AND(P$6>=$C10,P$6<($C10+$D10)),$G10/$D10,0)) -> 0 | ... DY10: =IF(AND($C10=0,$D10=0,DY$6=0),$G10,IF(AND(DY$6>=$C10,DY$6<($C10+$D10)),$G10/$D10,0)) -> 0
B11: Prepaid Taxes | C11: 0 | D11: 1 | E11: =iferror(G11/$E$6,"") -> 0.48823993 | F11: =iferror(G11/$F$6,"") -> 407.6087 | G11: 75000 | H11: =IF(SUM(I11:DY11)=G11,"OK","FALSE") -> OK | I11: =IF(AND($C11=0,$D11=0,I$6=0),$G11,IF(AND(I$6>=$C11,I$6<($C11+$D11)),$G11/$D11,0)) -> 75000 | J11: =IF(AND($C11=0,$D11=0,J$6=0),$G11,IF(AND(J$6>=$C11,J$6<($C11+$D11)),$G11/$D11,0)) -> 0 | K11: =IF(AND($C11=0,$D11=0,K$6=0),$G11,IF(AND(K$6>=$C11,K$6<($C11+$D11)),$G11/$D11,0)) -> 0 | L11: =IF(AND($C11=0,$D11=0,L$6=0),$G11,IF(AND(L$6>=$C11,L$6<($C11+$D11)),$G11/$D11,0)) -> 0 | M11: =IF(AND($C11=0,$D11=0,M$6=0),$G11,IF(AND(M$6>=$C11,M$6<($C11+$D11)),$G11/$D11,0)) -> 0 | N11: =IF(AND($C11=0,$D11=0,N$6=0),$G11,IF(AND(N$6>=$C11,N$6<($C11+$D11)),$G11/$D11,0)) -> 0 | O11: =IF(AND($C11=0,$D11=0,O$6=0),$G11,IF(AND(O$6>=$C11,O$6<($C11+$D11)),$G11/$D11,0)) -> 0 | P11: =IF(AND($C11=0,$D11=0,P$6=0),$G11,IF(AND(P$6>=$C11,P$6<($C11+$D11)),$G11/$D11,0)) -> 0 | ... DY11: =IF(AND($C11=0,$D11=0,DY$6=0),$G11,IF(AND(DY$6>=$C11,DY$6<($C11+$D11)),$G11/$D11,0)) -> 0
B12: Prepaid Insurance | C12: 0 | D12: 1 | E12: =iferror(G12/$E$6,"") -> 0.35804261 | F12: =iferror(G12/$F$6,"") -> 298.91304 | G12: 55000 | H12: =IF(SUM(I12:DY12)=G12,"OK","FALSE") -> OK | I12: =IF(AND($C12=0,$D12=0,I$6=0),$G12,IF(AND(I$6>=$C12,I$6<($C12+$D12)),$G12/$D12,0)) -> 55000 | J12: =IF(AND($C12=0,$D12=0,J$6=0),$G12,IF(AND(J$6>=$C12,J$6<($C12+$D12)),$G12/$D12,0)) -> 0 | K12: =IF(AND($C12=0,$D12=0,K$6=0),$G12,IF(AND(K$6>=$C12,K$6<($C12+$D12)),$G12/$D12,0)) -> 0 | L12: =IF(AND($C12=0,$D12=0,L$6=0),$G12,IF(AND(L$6>=$C12,L$6<($C12+$D12)),$G12/$D12,0)) -> 0 | M12: =IF(AND($C12=0,$D12=0,M$6=0),$G12,IF(AND(M$6>=$C12,M$6<($C12+$D12)),$G12/$D12,0)) -> 0 | N12: =IF(AND($C12=0,$D12=0,N$6=0),$G12,IF(AND(N$6>=$C12,N$6<($C12+$D12)),$G12/$D12,0)) -> 0 | O12: =IF(AND($C12=0,$D12=0,O$6=0),$G12,IF(AND(O$6>=$C12,O$6<($C12+$D12)),$G12/$D12,0)) -> 0 | P12: =IF(AND($C12=0,$D12=0,P$6=0),$G12,IF(AND(P$6>=$C12,P$6<($C12+$D12)),$G12/$D12,0)) -> 0 | ... DY12: =IF(AND($C12=0,$D12=0,DY$6=0),$G12,IF(AND(DY$6>=$C12,DY$6<($C12+$D12)),$G12/$D12,0)) -> 0
B13: Prepaid Interest | C13: 0 | D13: 1 | E13: =iferror(G13/$E$6,"") -> 0 | F13: =iferror(G13/$F$6,"") -> 0 | G13: 0 | H13: =IF(SUM(I13:DY13)=G13,"OK","FALSE") -> OK | I13: =IF(AND($C13=0,$D13=0,I$6=0),$G13,IF(AND(I$6>=$C13,I$6<($C13+$D13)),$G13/$D13,0)) -> 0 | J13: =IF(AND($C13=0,$D13=0,J$6=0),$G13,IF(AND(J$6>=$C13,J$6<($C13+$D13)),$G13/$D13,0)) -> 0 | K13: =IF(AND($C13=0,$D13=0,K$6=0),$G13,IF(AND(K$6>=$C13,K$6<($C13+$D13)),$G13/$D13,0)) -> 0 | L13: =IF(AND($C13=0,$D13=0,L$6=0),$G13,IF(AND(L$6>=$C13,L$6<($C13+$D13)),$G13/$D13,0)) -> 0 | M13: =IF(AND($C13=0,$D13=0,M$6=0),$G13,IF(AND(M$6>=$C13,M$6<($C13+$D13)),$G13/$D13,0)) -> 0 | N13: =IF(AND($C13=0,$D13=0,N$6=0),$G13,IF(AND(N$6>=$C13,N$6<($C13+$D13)),$G13/$D13,0)) -> 0 | O13: =IF(AND($C13=0,$D13=0,O$6=0),$G13,IF(AND(O$6>=$C13,O$6<($C13+$D13)),$G13/$D13,0)) -> 0 | P13: =IF(AND($C13=0,$D13=0,P$6=0),$G13,IF(AND(P$6>=$C13,P$6<($C13+$D13)),$G13/$D13,0)) -> 0 | ... DY13: =IF(AND($C13=0,$D13=0,DY$6=0),$G13,IF(AND(DY$6>=$C13,DY$6<($C13+$D13)),$G13/$D13,0)) -> 0
B14: Owner's Title Policy | C14: 0 | D14: 1 | E14: =iferror(G14/$E$6,"") -> 0.48823993 | F14: =iferror(G14/$F$6,"") -> 407.6087 | G14: 75000 | H14: =IF(SUM(I14:DY14)=G14,"OK","FALSE") -> OK | I14: =IF(AND($C14=0,$D14=0,I$6=0),$G14,IF(AND(I$6>=$C14,I$6<($C14+$D14)),$G14/$D14,0)) -> 75000 | J14: =IF(AND($C14=0,$D14=0,J$6=0),$G14,IF(AND(J$6>=$C14,J$6<($C14+$D14)),$G14/$D14,0)) -> 0 | K14: =IF(AND($C14=0,$D14=0,K$6=0),$G14,IF(AND(K$6>=$C14,K$6<($C14+$D14)),$G14/$D14,0)) -> 0 | L14: =IF(AND($C14=0,$D14=0,L$6=0),$G14,IF(AND(L$6>=$C14,L$6<($C14+$D14)),$G14/$D14,0)) -> 0 | M14: =IF(AND($C14=0,$D14=0,M$6=0),$G14,IF(AND(M$6>=$C14,M$6<($C14+$D14)),$G14/$D14,0)) -> 0 | N14: =IF(AND($C14=0,$D14=0,N$6=0),$G14,IF(AND(N$6>=$C14,N$6<($C14+$D14)),$G14/$D14,0)) -> 0 | O14: =IF(AND($C14=0,$D14=0,O$6=0),$G14,IF(AND(O$6>=$C14,O$6<($C14+$D14)),$G14/$D14,0)) -> 0 | P14: =IF(AND($C14=0,$D14=0,P$6=0),$G14,IF(AND(P$6>=$C14,P$6<($C14+$D14)),$G14/$D14,0)) -> 0 | ... DY14: =IF(AND($C14=0,$D14=0,DY$6=0),$G14,IF(AND(DY$6>=$C14,DY$6<($C14+$D14)),$G14/$D14,0)) -> 0
B15: Endorsements | C15: 0 | D15: 1 | E15: =iferror(G15/$E$6,"") -> 0 | F15: =iferror(G15/$F$6,"") -> 0 | G15: 0 | H15: =IF(SUM(I15:DY15)=G15,"OK","FALSE") -> OK | I15: =IF(AND($C15=0,$D15=0,I$6=0),$G15,IF(AND(I$6>=$C15,I$6<($C15+$D15)),$G15/$D15,0)) -> 0 | J15: =IF(AND($C15=0,$D15=0,J$6=0),$G15,IF(AND(J$6>=$C15,J$6<($C15+$D15)),$G15/$D15,0)) -> 0 | K15: =IF(AND($C15=0,$D15=0,K$6=0),$G15,IF(AND(K$6>=$C15,K$6<($C15+$D15)),$G15/$D15,0)) -> 0 | L15: =IF(AND($C15=0,$D15=0,L$6=0),$G15,IF(AND(L$6>=$C15,L$6<($C15+$D15)),$G15/$D15,0)) -> 0 | M15: =IF(AND($C15=0,$D15=0,M$6=0),$G15,IF(AND(M$6>=$C15,M$6<($C15+$D15)),$G15/$D15,0)) -> 0 | N15: =IF(AND($C15=0,$D15=0,N$6=0),$G15,IF(AND(N$6>=$C15,N$6<($C15+$D15)),$G15/$D15,0)) -> 0 | O15: =IF(AND($C15=0,$D15=0,O$6=0),$G15,IF(AND(O$6>=$C15,O$6<($C15+$D15)),$G15/$D15,0)) -> 0 | P15: =IF(AND($C15=0,$D15=0,P$6=0),$G15,IF(AND(P$6>=$C15,P$6<($C15+$D15)),$G15/$D15,0)) -> 0 | ... DY15: =IF(AND($C15=0,$D15=0,DY$6=0),$G15,IF(AND(DY$6>=$C15,DY$6<($C15+$D15)),$G15/$D15,0)) -> 0
B16: Closing & Recording | C16: 0 | D16: 1 | E16: =iferror(G16/$E$6,"") -> 0.016274664 | F16: =iferror(G16/$F$6,"") -> 13.586957 | G16: 2500 | H16: =IF(SUM(I16:DY16)=G16,"OK","FALSE") -> OK | I16: =IF(AND($C16=0,$D16=0,I$6=0),$G16,IF(AND(I$6>=$C16,I$6<($C16+$D16)),$G16/$D16,0)) -> 2500 | J16: =IF(AND($C16=0,$D16=0,J$6=0),$G16,IF(AND(J$6>=$C16,J$6<($C16+$D16)),$G16/$D16,0)) -> 0 | K16: =IF(AND($C16=0,$D16=0,K$6=0),$G16,IF(AND(K$6>=$C16,K$6<($C16+$D16)),$G16/$D16,0)) -> 0 | L16: =IF(AND($C16=0,$D16=0,L$6=0),$G16,IF(AND(L$6>=$C16,L$6<($C16+$D16)),$G16/$D16,0)) -> 0 | M16: =IF(AND($C16=0,$D16=0,M$6=0),$G16,IF(AND(M$6>=$C16,M$6<($C16+$D16)),$G16/$D16,0)) -> 0 | N16: =IF(AND($C16=0,$D16=0,N$6=0),$G16,IF(AND(N$6>=$C16,N$6<($C16+$D16)),$G16/$D16,0)) -> 0 | O16: =IF(AND($C16=0,$D16=0,O$6=0),$G16,IF(AND(O$6>=$C16,O$6<($C16+$D16)),$G16/$D16,0)) -> 0 | P16: =IF(AND($C16=0,$D16=0,P$6=0),$G16,IF(AND(P$6>=$C16,P$6<($C16+$D16)),$G16/$D16,0)) -> 0 | ... DY16: =IF(AND($C16=0,$D16=0,DY$6=0),$G16,IF(AND(DY$6>=$C16,DY$6<($C16+$D16)),$G16/$D16,0)) -> 0
B17: Cost Segregation Study | C17: 0 | D17: 1 | E17: =iferror(G17/$E$6,"") -> 0.065098657 | F17: =iferror(G17/$F$6,"") -> 54.347826 | G17: 10000 | H17: =IF(SUM(I17:DY17)=G17,"OK","FALSE") -> OK | I17: =IF(AND($C17=0,$D17=0,I$6=0),$G17,IF(AND(I$6>=$C17,I$6<($C17+$D17)),$G17/$D17,0)) -> 10000 | J17: =IF(AND($C17=0,$D17=0,J$6=0),$G17,IF(AND(J$6>=$C17,J$6<($C17+$D17)),$G17/$D17,0)) -> 0 | K17: =IF(AND($C17=0,$D17=0,K$6=0),$G17,IF(AND(K$6>=$C17,K$6<($C17+$D17)),$G17/$D17,0)) -> 0 | L17: =IF(AND($C17=0,$D17=0,L$6=0),$G17,IF(AND(L$6>=$C17,L$6<($C17+$D17)),$G17/$D17,0)) -> 0 | M17: =IF(AND($C17=0,$D17=0,M$6=0),$G17,IF(AND(M$6>=$C17,M$6<($C17+$D17)),$G17/$D17,0)) -> 0 | N17: =IF(AND($C17=0,$D17=0,N$6=0),$G17,IF(AND(N$6>=$C17,N$6<($C17+$D17)),$G17/$D17,0)) -> 0 | O17: =IF(AND($C17=0,$D17=0,O$6=0),$G17,IF(AND(O$6>=$C17,O$6<($C17+$D17)),$G17/$D17,0)) -> 0 | P17: =IF(AND($C17=0,$D17=0,P$6=0),$G17,IF(AND(P$6>=$C17,P$6<($C17+$D17)),$G17/$D17,0)) -> 0 | ... DY17: =IF(AND($C17=0,$D17=0,DY$6=0),$G17,IF(AND(DY$6>=$C17,DY$6<($C17+$D17)),$G17/$D17,0)) -> 0
B18: Buyer Travel | C18: 0 | D18: 1 | E18: =iferror(G18/$E$6,"") -> 0.032549329 | F18: =iferror(G18/$F$6,"") -> 27.173913 | G18: 5000 | H18: =IF(SUM(I18:DY18)=G18,"OK","FALSE") -> OK | I18: =IF(AND($C18=0,$D18=0,I$6=0),$G18,IF(AND(I$6>=$C18,I$6<($C18+$D18)),$G18/$D18,0)) -> 5000 | J18: =IF(AND($C18=0,$D18=0,J$6=0),$G18,IF(AND(J$6>=$C18,J$6<($C18+$D18)),$G18/$D18,0)) -> 0 | K18: =IF(AND($C18=0,$D18=0,K$6=0),$G18,IF(AND(K$6>=$C18,K$6<($C18+$D18)),$G18/$D18,0)) -> 0 | L18: =IF(AND($C18=0,$D18=0,L$6=0),$G18,IF(AND(L$6>=$C18,L$6<($C18+$D18)),$G18/$D18,0)) -> 0 | M18: =IF(AND($C18=0,$D18=0,M$6=0),$G18,IF(AND(M$6>=$C18,M$6<($C18+$D18)),$G18/$D18,0)) -> 0 | N18: =IF(AND($C18=0,$D18=0,N$6=0),$G18,IF(AND(N$6>=$C18,N$6<($C18+$D18)),$G18/$D18,0)) -> 0 | O18: =IF(AND($C18=0,$D18=0,O$6=0),$G18,IF(AND(O$6>=$C18,O$6<($C18+$D18)),$G18/$D18,0)) -> 0 | P18: =IF(AND($C18=0,$D18=0,P$6=0),$G18,IF(AND(P$6>=$C18,P$6<($C18+$D18)),$G18/$D18,0)) -> 0 | ... DY18: =IF(AND($C18=0,$D18=0,DY$6=0),$G18,IF(AND(DY$6>=$C18,DY$6<($C18+$D18)),$G18/$D18,0)) -> 0
B19: Technology Due Diligence | C19: 0 | D19: 1 | E19: =iferror(G19/$E$6,"") -> 0.065098657 | F19: =iferror(G19/$F$6,"") -> 54.347826 | G19: 10000 | H19: =IF(SUM(I19:DY19)=G19,"OK","FALSE") -> OK | I19: =IF(AND($C19=0,$D19=0,I$6=0),$G19,IF(AND(I$6>=$C19,I$6<($C19+$D19)),$G19/$D19,0)) -> 10000 | J19: =IF(AND($C19=0,$D19=0,J$6=0),$G19,IF(AND(J$6>=$C19,J$6<($C19+$D19)),$G19/$D19,0)) -> 0 | K19: =IF(AND($C19=0,$D19=0,K$6=0),$G19,IF(AND(K$6>=$C19,K$6<($C19+$D19)),$G19/$D19,0)) -> 0 | L19: =IF(AND($C19=0,$D19=0,L$6=0),$G19,IF(AND(L$6>=$C19,L$6<($C19+$D19)),$G19/$D19,0)) -> 0 | M19: =IF(AND($C19=0,$D19=0,M$6=0),$G19,IF(AND(M$6>=$C19,M$6<($C19+$D19)),$G19/$D19,0)) -> 0 | N19: =IF(AND($C19=0,$D19=0,N$6=0),$G19,IF(AND(N$6>=$C19,N$6<($C19+$D19)),$G19/$D19,0)) -> 0 | O19: =IF(AND($C19=0,$D19=0,O$6=0),$G19,IF(AND(O$6>=$C19,O$6<($C19+$D19)),$G19/$D19,0)) -> 0 | P19: =IF(AND($C19=0,$D19=0,P$6=0),$G19,IF(AND(P$6>=$C19,P$6<($C19+$D19)),$G19/$D19,0)) -> 0 | ... DY19: =IF(AND($C19=0,$D19=0,DY$6=0),$G19,IF(AND(DY$6>=$C19,DY$6<($C19+$D19)),$G19/$D19,0)) -> 0
B20: Total Acquisition Costs | E20: =iferror(G20/$E$6,"") -> 239.44914 | F20: =iferror(G20/$F$6,"") -> 199904.89 | G20: =sum(G8:G19) -> 36782500 | I20: =sum(I8:I19) -> 36782500 | J20: =sum(J8:J19) -> 0 | K20: =sum(K8:K19) -> 0 | L20: =sum(L8:L19) -> 0 | M20: =sum(M8:M19) -> 0 | N20: =sum(N8:N19) -> 0 | O20: =sum(O8:O19) -> 0 | P20: =sum(P8:P19) -> 0 | ... DY20: =sum(DY8:DY19) -> 0
B22: CapEx Budget
B23: Immediate Repairs | C23: 0 | D23: 1 | E23: =iferror(G23/$E$6,"") -> 0 | F23: =iferror(G23/$F$6,"") -> 0 | G23: 0 | H23: =IF(SUM(I23:DY23)=G23,"OK","FALSE") -> OK | I23: =IF(AND($C23=0,$D23=0,I$6=0),$G23,IF(AND(I$6>=$C23,I$6<($C23+$D23)),$G23/$D23,0)) -> 0 | J23: =IF(AND($C23=0,$D23=0,J$6=0),$G23,IF(AND(J$6>=$C23,J$6<($C23+$D23)),$G23/$D23,0)) -> 0 | K23: =IF(AND($C23=0,$D23=0,K$6=0),$G23,IF(AND(K$6>=$C23,K$6<($C23+$D23)),$G23/$D23,0)) -> 0 | L23: =IF(AND($C23=0,$D23=0,L$6=0),$G23,IF(AND(L$6>=$C23,L$6<($C23+$D23)),$G23/$D23,0)) -> 0 | M23: =IF(AND($C23=0,$D23=0,M$6=0),$G23,IF(AND(M$6>=$C23,M$6<($C23+$D23)),$G23/$D23,0)) -> 0 | N23: =IF(AND($C23=0,$D23=0,N$6=0),$G23,IF(AND(N$6>=$C23,N$6<($C23+$D23)),$G23/$D23,0)) -> 0 | O23: =IF(AND($C23=0,$D23=0,O$6=0),$G23,IF(AND(O$6>=$C23,O$6<($C23+$D23)),$G23/$D23,0)) -> 0 | P23: =IF(AND($C23=0,$D23=0,P$6=0),$G23,IF(AND(P$6>=$C23,P$6<($C23+$D23)),$G23/$D23,0)) -> 0 | ... DY23: =IF(AND($C23=0,$D23=0,DY$6=0),$G23,IF(AND(DY$6>=$C23,DY$6<($C23+$D23)),$G23/$D23,0)) -> 0
B24: 0.1 | C24: 0 | D24: 1 | E24: =iferror(G24/$E$6,"") -> 0 | F24: =iferror(G24/$F$6,"") -> 0 | G24: =G23*B24 -> 0 | H24: =IF(SUM(I24:DY24)=G24,"OK","FALSE") -> OK | I24: =IF(AND($C24=0,$D24=0,I$6=0),$G24,IF(AND(I$6>=$C24,I$6<($C24+$D24)),$G24/$D24,0)) -> 0 | J24: =IF(AND($C24=0,$D24=0,J$6=0),$G24,IF(AND(J$6>=$C24,J$6<($C24+$D24)),$G24/$D24,0)) -> 0 | K24: =IF(AND($C24=0,$D24=0,K$6=0),$G24,IF(AND(K$6>=$C24,K$6<($C24+$D24)),$G24/$D24,0)) -> 0 | L24: =IF(AND($C24=0,$D24=0,L$6=0),$G24,IF(AND(L$6>=$C24,L$6<($C24+$D24)),$G24/$D24,0)) -> 0 | M24: =IF(AND($C24=0,$D24=0,M$6=0),$G24,IF(AND(M$6>=$C24,M$6<($C24+$D24)),$G24/$D24,0)) -> 0 | N24: =IF(AND($C24=0,$D24=0,N$6=0),$G24,IF(AND(N$6>=$C24,N$6<($C24+$D24)),$G24/$D24,0)) -> 0 | O24: =IF(AND($C24=0,$D24=0,O$6=0),$G24,IF(AND(O$6>=$C24,O$6<($C24+$D24)),$G24/$D24,0)) -> 0 | P24: =IF(AND($C24=0,$D24=0,P$6=0),$G24,IF(AND(P$6>=$C24,P$6<($C24+$D24)),$G24/$D24,0)) -> 0 | ... DY24: =IF(AND($C24=0,$D24=0,DY$6=0),$G24,IF(AND(DY$6>=$C24,DY$6<($C24+$D24)),$G24/$D24,0)) -> 0
B25: Unit Renovations | C25: 0 | D25: 1 | E25: =iferror(G25/$E$6,"") -> 3.9417237 | F25: =iferror(G25/$F$6,"") -> 3290.7609 | G25: =CapEx!F28 -> 605500 | H25: =IF(SUM(I25:DY25)=G25,"OK","FALSE") -> OK | I25: =IF(AND($C25=0,$D25=0,I$6=0),$G25,IF(AND(I$6>=$C25,I$6<($C25+$D25)),$G25/$D25,0)) -> 605500 | J25: =IF(AND($C25=0,$D25=0,J$6=0),$G25,IF(AND(J$6>=$C25,J$6<($C25+$D25)),$G25/$D25,0)) -> 0 | K25: =IF(AND($C25=0,$D25=0,K$6=0),$G25,IF(AND(K$6>=$C25,K$6<($C25+$D25)),$G25/$D25,0)) -> 0 | L25: =IF(AND($C25=0,$D25=0,L$6=0),$G25,IF(AND(L$6>=$C25,L$6<($C25+$D25)),$G25/$D25,0)) -> 0 | M25: =IF(AND($C25=0,$D25=0,M$6=0),$G25,IF(AND(M$6>=$C25,M$6<($C25+$D25)),$G25/$D25,0)) -> 0 | N25: =IF(AND($C25=0,$D25=0,N$6=0),$G25,IF(AND(N$6>=$C25,N$6<($C25+$D25)),$G25/$D25,0)) -> 0 | O25: =IF(AND($C25=0,$D25=0,O$6=0),$G25,IF(AND(O$6>=$C25,O$6<($C25+$D25)),$G25/$D25,0)) -> 0 | P25: =IF(AND($C25=0,$D25=0,P$6=0),$G25,IF(AND(P$6>=$C25,P$6<($C25+$D25)),$G25/$D25,0)) -> 0 | ... DY25: =IF(AND($C25=0,$D25=0,DY$6=0),$G25,IF(AND(DY$6>=$C25,DY$6<($C25+$D25)),$G25/$D25,0)) -> 0
B26: General Improvements | C26: 0 | D26: 1 | E26: =iferror(G26/$E$6,"") -> 0 | F26: =iferror(G26/$F$6,"") -> 0 | G26: 0 | H26: =IF(SUM(I26:DY26)=G26,"OK","FALSE") -> OK | I26: =IF(AND($C26=0,$D26=0,I$6=0),$G26,IF(AND(I$6>=$C26,I$6<($C26+$D26)),$G26/$D26,0)) -> 0 | J26: =IF(AND($C26=0,$D26=0,J$6=0),$G26,IF(AND(J$6>=$C26,J$6<($C26+$D26)),$G26/$D26,0)) -> 0 | K26: =IF(AND($C26=0,$D26=0,K$6=0),$G26,IF(AND(K$6>=$C26,K$6<($C26+$D26)),$G26/$D26,0)) -> 0 | L26: =IF(AND($C26=0,$D26=0,L$6=0),$G26,IF(AND(L$6>=$C26,L$6<($C26+$D26)),$G26/$D26,0)) -> 0 | M26: =IF(AND($C26=0,$D26=0,M$6=0),$G26,IF(AND(M$6>=$C26,M$6<($C26+$D26)),$G26/$D26,0)) -> 0 | N26: =IF(AND($C26=0,$D26=0,N$6=0),$G26,IF(AND(N$6>=$C26,N$6<($C26+$D26)),$G26/$D26,0)) -> 0 | O26: =IF(AND($C26=0,$D26=0,O$6=0),$G26,IF(AND(O$6>=$C26,O$6<($C26+$D26)),$G26/$D26,0)) -> 0 | P26: =IF(AND($C26=0,$D26=0,P$6=0),$G26,IF(AND(P$6>=$C26,P$6<($C26+$D26)),$G26/$D26,0)) -> 0 | ... DY26: =IF(AND($C26=0,$D26=0,DY$6=0),$G26,IF(AND(DY$6>=$C26,DY$6<($C26+$D26)),$G26/$D26,0)) -> 0
B27: 0.1 | C27: 0 | D27: 1 | E27: =iferror(G27/$E$6,"") -> 0.39417237 | F27: =iferror(G27/$F$6,"") -> 329.07609 | G27: =sum(G25:G26)*B27 -> 60550 | H27: =IF(SUM(I27:DY27)=G27,"OK","FALSE") -> OK | I27: =IF(AND($C27=0,$D27=0,I$6=0),$G27,IF(AND(I$6>=$C27,I$6<($C27+$D27)),$G27/$D27,0)) -> 60550 | J27: =IF(AND($C27=0,$D27=0,J$6=0),$G27,IF(AND(J$6>=$C27,J$6<($C27+$D27)),$G27/$D27,0)) -> 0 | K27: =IF(AND($C27=0,$D27=0,K$6=0),$G27,IF(AND(K$6>=$C27,K$6<($C27+$D27)),$G27/$D27,0)) -> 0 | L27: =IF(AND($C27=0,$D27=0,L$6=0),$G27,IF(AND(L$6>=$C27,L$6<($C27+$D27)),$G27/$D27,0)) -> 0 | M27: =IF(AND($C27=0,$D27=0,M$6=0),$G27,IF(AND(M$6>=$C27,M$6<($C27+$D27)),$G27/$D27,0)) -> 0 | N27: =IF(AND($C27=0,$D27=0,N$6=0),$G27,IF(AND(N$6>=$C27,N$6<($C27+$D27)),$G27/$D27,0)) -> 0 | O27: =IF(AND($C27=0,$D27=0,O$6=0),$G27,IF(AND(O$6>=$C27,O$6<($C27+$D27)),$G27/$D27,0)) -> 0 | P27: =IF(AND($C27=0,$D27=0,P$6=0),$G27,IF(AND(P$6>=$C27,P$6<($C27+$D27)),$G27/$D27,0)) -> 0 | ... DY27: =IF(AND($C27=0,$D27=0,DY$6=0),$G27,IF(AND(DY$6>=$C27,DY$6<($C27+$D27)),$G27/$D27,0)) -> 0
B28: 2
B29: 3000 | C29: 0 | D29: 1 | E29: =iferror(G29/$E$6,"") -> 7.1868917 | F29: =iferror(G29/$F$6,"") -> 6000 | G29: =iferror(F6*B29*B28,"") -> 1104000 | H29: =IF(SUM(I29:DY29)=G29,"OK","FALSE") -> OK | I29: =IF(AND($C29=0,$D29=0,I$6=0),$G29,IF(AND(I$6>=$C29,I$6<($C29+$D29)),$G29/$D29,0)) -> 1104000 | J29: =IF(AND($C29=0,$D29=0,J$6=0),$G29,IF(AND(J$6>=$C29,J$6<($C29+$D29)),$G29/$D29,0)) -> 0 | K29: =IF(AND($C29=0,$D29=0,K$6=0),$G29,IF(AND(K$6>=$C29,K$6<($C29+$D29)),$G29/$D29,0)) -> 0 | L29: =IF(AND($C29=0,$D29=0,L$6=0),$G29,IF(AND(L$6>=$C29,L$6<($C29+$D29)),$G29/$D29,0)) -> 0 | M29: =IF(AND($C29=0,$D29=0,M$6=0),$G29,IF(AND(M$6>=$C29,M$6<($C29+$D29)),$G29/$D29,0)) -> 0 | N29: =IF(AND($C29=0,$D29=0,N$6=0),$G29,IF(AND(N$6>=$C29,N$6<($C29+$D29)),$G29/$D29,0)) -> 0 | O29: =IF(AND($C29=0,$D29=0,O$6=0),$G29,IF(AND(O$6>=$C29,O$6<($C29+$D29)),$G29/$D29,0)) -> 0 | P29: =IF(AND($C29=0,$D29=0,P$6=0),$G29,IF(AND(P$6>=$C29,P$6<($C29+$D29)),$G29/$D29,0)) -> 0 | ... DY29: =IF(AND($C29=0,$D29=0,DY$6=0),$G29,IF(AND(DY$6>=$C29,DY$6<($C29+$D29)),$G29/$D29,0)) -> 0
B30: Working Capital Reserve | C30: 0 | D30: 1 | E30: =iferror(G30/$E$6,"") -> 1.9529597 | F30: =iferror(G30/$F$6,"") -> 1630.4348 | G30: 300000 | H30: =IF(SUM(I30:DY30)=G30,"OK","FALSE") -> OK | I30: =IF(AND($C30=0,$D30=0,I$6=0),$G30,IF(AND(I$6>=$C30,I$6<($C30+$D30)),$G30/$D30,0)) -> 300000 | J30: =IF(AND($C30=0,$D30=0,J$6=0),$G30,IF(AND(J$6>=$C30,J$6<($C30+$D30)),$G30/$D30,0)) -> 0 | K30: =IF(AND($C30=0,$D30=0,K$6=0),$G30,IF(AND(K$6>=$C30,K$6<($C30+$D30)),$G30/$D30,0)) -> 0 | L30: =IF(AND($C30=0,$D30=0,L$6=0),$G30,IF(AND(L$6>=$C30,L$6<($C30+$D30)),$G30/$D30,0)) -> 0 | M30: =IF(AND($C30=0,$D30=0,M$6=0),$G30,IF(AND(M$6>=$C30,M$6<($C30+$D30)),$G30/$D30,0)) -> 0 | N30: =IF(AND($C30=0,$D30=0,N$6=0),$G30,IF(AND(N$6>=$C30,N$6<($C30+$D30)),$G30/$D30,0)) -> 0 | O30: =IF(AND($C30=0,$D30=0,O$6=0),$G30,IF(AND(O$6>=$C30,O$6<($C30+$D30)),$G30/$D30,0)) -> 0 | P30: =IF(AND($C30=0,$D30=0,P$6=0),$G30,IF(AND(P$6>=$C30,P$6<($C30+$D30)),$G30/$D30,0)) -> 0 | ... DY30: =IF(AND($C30=0,$D30=0,DY$6=0),$G30,IF(AND(DY$6>=$C30,DY$6<($C30+$D30)),$G30/$D30,0)) -> 0
B31: Total CapEx Budget | E31: =iferror(G31/$E$6,"") -> 13.475748 | F31: =iferror(G31/$F$6,"") -> 11250.272 | G31: =sum(G23:G30) -> 2070050 | I31: =sum(I23:I30) -> 2070050 | J31: =sum(J23:J30) -> 0 | K31: =sum(K23:K30) -> 0 | L31: =sum(L23:L30) -> 0 | M31: =sum(M23:M30) -> 0 | N31: =sum(N23:N30) -> 0 | O31: =sum(O23:O30) -> 0 | P31: =sum(P23:P30) -> 0 | ... DY31: =sum(DY23:DY30) -> 0
B33: Financing Costs
B34: Loan Amount | G34: ='Capital Stack'!C17 -> 21900000
B35: 0.001 | C35: 0 | D35: 1 | E35: =iferror(G35/$E$6,"") -> 0.14256606 | F35: =iferror(G35/$F$6,"") -> 119.02174 | G35: =G34*B35 -> 21900 | H35: =IF(SUM(I35:DY35)=G35,"OK","FALSE") -> OK | I35: =IF(AND($C35=0,$D35=0,I$6=0),$G35,IF(AND(I$6>=$C35,I$6<($C35+$D35)),$G35/$D35,0)) -> 21900 | J35: =IF(AND($C35=0,$D35=0,J$6=0),$G35,IF(AND(J$6>=$C35,J$6<($C35+$D35)),$G35/$D35,0)) -> 0 | K35: =IF(AND($C35=0,$D35=0,K$6=0),$G35,IF(AND(K$6>=$C35,K$6<($C35+$D35)),$G35/$D35,0)) -> 0 | L35: =IF(AND($C35=0,$D35=0,L$6=0),$G35,IF(AND(L$6>=$C35,L$6<($C35+$D35)),$G35/$D35,0)) -> 0 | M35: =IF(AND($C35=0,$D35=0,M$6=0),$G35,IF(AND(M$6>=$C35,M$6<($C35+$D35)),$G35/$D35,0)) -> 0 | N35: =IF(AND($C35=0,$D35=0,N$6=0),$G35,IF(AND(N$6>=$C35,N$6<($C35+$D35)),$G35/$D35,0)) -> 0 | O35: =IF(AND($C35=0,$D35=0,O$6=0),$G35,IF(AND(O$6>=$C35,O$6<($C35+$D35)),$G35/$D35,0)) -> 0 | P35: =IF(AND($C35=0,$D35=0,P$6=0),$G35,IF(AND(P$6>=$C35,P$6<($C35+$D35)),$G35/$D35,0)) -> 0 | ... DY35: =IF(AND($C35=0,$D35=0,DY$6=0),$G35,IF(AND(DY$6>=$C35,DY$6<($C35+$D35)),$G35/$D35,0)) -> 0
B36: Lender Legal | C36: 0 | D36: 1 | E36: =iferror(G36/$E$6,"") -> 0.16274664 | F36: =iferror(G36/$F$6,"") -> 135.86957 | G36: 25000 | H36: =IF(SUM(I36:DY36)=G36,"OK","FALSE") -> OK | I36: =IF(AND($C36=0,$D36=0,I$6=0),$G36,IF(AND(I$6>=$C36,I$6<($C36+$D36)),$G36/$D36,0)) -> 25000 | J36: =IF(AND($C36=0,$D36=0,J$6=0),$G36,IF(AND(J$6>=$C36,J$6<($C36+$D36)),$G36/$D36,0)) -> 0 | K36: =IF(AND($C36=0,$D36=0,K$6=0),$G36,IF(AND(K$6>=$C36,K$6<($C36+$D36)),$G36/$D36,0)) -> 0 | L36: =IF(AND($C36=0,$D36=0,L$6=0),$G36,IF(AND(L$6>=$C36,L$6<($C36+$D36)),$G36/$D36,0)) -> 0 | M36: =IF(AND($C36=0,$D36=0,M$6=0),$G36,IF(AND(M$6>=$C36,M$6<($C36+$D36)),$G36/$D36,0)) -> 0 | N36: =IF(AND($C36=0,$D36=0,N$6=0),$G36,IF(AND(N$6>=$C36,N$6<($C36+$D36)),$G36/$D36,0)) -> 0 | O36: =IF(AND($C36=0,$D36=0,O$6=0),$G36,IF(AND(O$6>=$C36,O$6<($C36+$D36)),$G36/$D36,0)) -> 0 | P36: =IF(AND($C36=0,$D36=0,P$6=0),$G36,IF(AND(P$6>=$C36,P$6<($C36+$D36)),$G36/$D36,0)) -> 0 | ... DY36: =IF(AND($C36=0,$D36=0,DY$6=0),$G36,IF(AND(DY$6>=$C36,DY$6<($C36+$D36)),$G36/$D36,0)) -> 0
B37: Phase I, Appraisal & Property Condition Assessment | C37: 0 | D37: 1 | E37: =iferror(G37/$E$6,"") -> 0.097647986 | F37: =iferror(G37/$F$6,"") -> 81.521739 | G37: 15000 | H37: =IF(SUM(I37:DY37)=G37,"OK","FALSE") -> OK | I37: =IF(AND($C37=0,$D37=0,I$6=0),$G37,IF(AND(I$6>=$C37,I$6<($C37+$D37)),$G37/$D37,0)) -> 15000 | J37: =IF(AND($C37=0,$D37=0,J$6=0),$G37,IF(AND(J$6>=$C37,J$6<($C37+$D37)),$G37/$D37,0)) -> 0 | K37: =IF(AND($C37=0,$D37=0,K$6=0),$G37,IF(AND(K$6>=$C37,K$6<($C37+$D37)),$G37/$D37,0)) -> 0 | L37: =IF(AND($C37=0,$D37=0,L$6=0),$G37,IF(AND(L$6>=$C37,L$6<($C37+$D37)),$G37/$D37,0)) -> 0 | M37: =IF(AND($C37=0,$D37=0,M$6=0),$G37,IF(AND(M$6>=$C37,M$6<($C37+$D37)),$G37/$D37,0)) -> 0 | N37: =IF(AND($C37=0,$D37=0,N$6=0),$G37,IF(AND(N$6>=$C37,N$6<($C37+$D37)),$G37/$D37,0)) -> 0 | O37: =IF(AND($C37=0,$D37=0,O$6=0),$G37,IF(AND(O$6>=$C37,O$6<($C37+$D37)),$G37/$D37,0)) -> 0 | P37: =IF(AND($C37=0,$D37=0,P$6=0),$G37,IF(AND(P$6>=$C37,P$6<($C37+$D37)),$G37/$D37,0)) -> 0 | ... DY37: =IF(AND($C37=0,$D37=0,DY$6=0),$G37,IF(AND(DY$6>=$C37,DY$6<($C37+$D37)),$G37/$D37,0)) -> 0
B38: Mortgage Tax | C38: 0 | D38: 1 | E38: =iferror(G38/$E$6,"") -> 0 | F38: =iferror(G38/$F$6,"") -> 0 | G38: 0 | H38: =IF(SUM(I38:DY38)=G38,"OK","FALSE") -> OK | I38: =IF(AND($C38=0,$D38=0,I$6=0),$G38,IF(AND(I$6>=$C38,I$6<($C38+$D38)),$G38/$D38,0)) -> 0 | J38: =IF(AND($C38=0,$D38=0,J$6=0),$G38,IF(AND(J$6>=$C38,J$6<($C38+$D38)),$G38/$D38,0)) -> 0 | K38: =IF(AND($C38=0,$D38=0,K$6=0),$G38,IF(AND(K$6>=$C38,K$6<($C38+$D38)),$G38/$D38,0)) -> 0 | L38: =IF(AND($C38=0,$D38=0,L$6=0),$G38,IF(AND(L$6>=$C38,L$6<($C38+$D38)),$G38/$D38,0)) -> 0 | M38: =IF(AND($C38=0,$D38=0,M$6=0),$G38,IF(AND(M$6>=$C38,M$6<($C38+$D38)),$G38/$D38,0)) -> 0 | N38: =IF(AND($C38=0,$D38=0,N$6=0),$G38,IF(AND(N$6>=$C38,N$6<($C38+$D38)),$G38/$D38,0)) -> 0 | O38: =IF(AND($C38=0,$D38=0,O$6=0),$G38,IF(AND(O$6>=$C38,O$6<($C38+$D38)),$G38/$D38,0)) -> 0 | P38: =IF(AND($C38=0,$D38=0,P$6=0),$G38,IF(AND(P$6>=$C38,P$6<($C38+$D38)),$G38/$D38,0)) -> 0 | ... DY38: =IF(AND($C38=0,$D38=0,DY$6=0),$G38,IF(AND(DY$6>=$C38,DY$6<($C38+$D38)),$G38/$D38,0)) -> 0
B39: 0.0175 | C39: 0 | D39: 1 | E39: =iferror(G39/$E$6,"") -> 2.494906 | F39: =iferror(G39/$F$6,"") -> 2082.8804 | G39: =G34*B39 -> 383250 | H39: =IF(SUM(I39:DY39)=G39,"OK","FALSE") -> OK | I39: =IF(AND($C39=0,$D39=0,I$6=0),$G39,IF(AND(I$6>=$C39,I$6<($C39+$D39)),$G39/$D39,0)) -> 383250 | J39: =IF(AND($C39=0,$D39=0,J$6=0),$G39,IF(AND(J$6>=$C39,J$6<($C39+$D39)),$G39/$D39,0)) -> 0 | K39: =IF(AND($C39=0,$D39=0,K$6=0),$G39,IF(AND(K$6>=$C39,K$6<($C39+$D39)),$G39/$D39,0)) -> 0 | L39: =IF(AND($C39=0,$D39=0,L$6=0),$G39,IF(AND(L$6>=$C39,L$6<($C39+$D39)),$G39/$D39,0)) -> 0 | M39: =IF(AND($C39=0,$D39=0,M$6=0),$G39,IF(AND(M$6>=$C39,M$6<($C39+$D39)),$G39/$D39,0)) -> 0 | N39: =IF(AND($C39=0,$D39=0,N$6=0),$G39,IF(AND(N$6>=$C39,N$6<($C39+$D39)),$G39/$D39,0)) -> 0 | O39: =IF(AND($C39=0,$D39=0,O$6=0),$G39,IF(AND(O$6>=$C39,O$6<($C39+$D39)),$G39/$D39,0)) -> 0 | P39: =IF(AND($C39=0,$D39=0,P$6=0),$G39,IF(AND(P$6>=$C39,P$6<($C39+$D39)),$G39/$D39,0)) -> 0 | ... DY39: =IF(AND($C39=0,$D39=0,DY$6=0),$G39,IF(AND(DY$6>=$C39,DY$6<($C39+$D39)),$G39/$D39,0)) -> 0
B40: 0.01 | C40: 0 | D40: 1 | E40: =iferror(G40/$E$6,"") -> 1.4256606 | F40: =iferror(G40/$F$6,"") -> 1190.2174 | G40: =G34*B40 -> 219000 | H40: =IF(SUM(I40:DY40)=G40,"OK","FALSE") -> OK | I40: =IF(AND($C40=0,$D40=0,I$6=0),$G40,IF(AND(I$6>=$C40,I$6<($C40+$D40)),$G40/$D40,0)) -> 219000 | J40: =IF(AND($C40=0,$D40=0,J$6=0),$G40,IF(AND(J$6>=$C40,J$6<($C40+$D40)),$G40/$D40,0)) -> 0 | K40: =IF(AND($C40=0,$D40=0,K$6=0),$G40,IF(AND(K$6>=$C40,K$6<($C40+$D40)),$G40/$D40,0)) -> 0 | L40: =IF(AND($C40=0,$D40=0,L$6=0),$G40,IF(AND(L$6>=$C40,L$6<($C40+$D40)),$G40/$D40,0)) -> 0 | M40: =IF(AND($C40=0,$D40=0,M$6=0),$G40,IF(AND(M$6>=$C40,M$6<($C40+$D40)),$G40/$D40,0)) -> 0 | N40: =IF(AND($C40=0,$D40=0,N$6=0),$G40,IF(AND(N$6>=$C40,N$6<($C40+$D40)),$G40/$D40,0)) -> 0 | O40: =IF(AND($C40=0,$D40=0,O$6=0),$G40,IF(AND(O$6>=$C40,O$6<($C40+$D40)),$G40/$D40,0)) -> 0 | P40: =IF(AND($C40=0,$D40=0,P$6=0),$G40,IF(AND(P$6>=$C40,P$6<($C40+$D40)),$G40/$D40,0)) -> 0 | ... DY40: =IF(AND($C40=0,$D40=0,DY$6=0),$G40,IF(AND(DY$6>=$C40,DY$6<($C40+$D40)),$G40/$D40,0)) -> 0
B41: Total Financing Costs | E41: =iferror(G41/$E$6,"") -> 4.3235273 | F41: =iferror(G41/$F$6,"") -> 3609.5109 | G41: =sum(G35:G40) -> 664150 | I41: =sum(I35:I40) -> 664150 | J41: =sum(J35:J40) -> 0 | K41: =sum(K35:K40) -> 0 | L41: =sum(L35:L40) -> 0 | M41: =sum(M35:M40) -> 0 | N41: =sum(N35:N40) -> 0 | O41: =sum(O35:O40) -> 0 | P41: =sum(P35:P40) -> 0 | ... DY41: =sum(DY35:DY40) -> 0
B43: Wind River Group Fees
B44: ='Investment Summary'!F16 -> 0.025 | C44: 0 | D44: 1 | E44: =iferror(G44/$E$6,"") -> 5.9402525 | F44: =iferror(G44/$F$6,"") -> 4959.2391 | G44: =G8*B44 -> 912500 | H44: =IF(SUM(I44:DY44)=G44,"OK","FALSE") -> OK | I44: =IF(AND($C44=0,$D44=0,I$6=0),$G44,IF(AND(I$6>=$C44,I$6<($C44+$D44)),$G44/$D44,0)) -> 912500 | J44: =IF(AND($C44=0,$D44=0,J$6=0),$G44,IF(AND(J$6>=$C44,J$6<($C44+$D44)),$G44/$D44,0)) -> 0 | K44: =IF(AND($C44=0,$D44=0,K$6=0),$G44,IF(AND(K$6>=$C44,K$6<($C44+$D44)),$G44/$D44,0)) -> 0 | L44: =IF(AND($C44=0,$D44=0,L$6=0),$G44,IF(AND(L$6>=$C44,L$6<($C44+$D44)),$G44/$D44,0)) -> 0 | M44: =IF(AND($C44=0,$D44=0,M$6=0),$G44,IF(AND(M$6>=$C44,M$6<($C44+$D44)),$G44/$D44,0)) -> 0 | N44: =IF(AND($C44=0,$D44=0,N$6=0),$G44,IF(AND(N$6>=$C44,N$6<($C44+$D44)),$G44/$D44,0)) -> 0 | O44: =IF(AND($C44=0,$D44=0,O$6=0),$G44,IF(AND(O$6>=$C44,O$6<($C44+$D44)),$G44/$D44,0)) -> 0 | P44: =IF(AND($C44=0,$D44=0,P$6=0),$G44,IF(AND(P$6>=$C44,P$6<($C44+$D44)),$G44/$D44,0)) -> 0 | ... DY44: =IF(AND($C44=0,$D44=0,DY$6=0),$G44,IF(AND(DY$6>=$C44,DY$6<($C44+$D44)),$G44/$D44,0)) -> 0
B45: ='Investment Summary'!F15 -> 0.05 | C45: 0 | D45: 1 | E45: =iferror(G45/$E$6,"") -> 0.57613939 | F45: =iferror(G45/$F$6,"") -> 480.99185 | G45: =(G31-G30)*B45 -> 88502.5 | H45: =IF(SUM(I45:DY45)=G45,"OK","FALSE") -> OK | I45: =IF(AND($C45=0,$D45=0,I$6=0),$G45,IF(AND(I$6>=$C45,I$6<($C45+$D45)),$G45/$D45,0)) -> 88502.5 | J45: =IF(AND($C45=0,$D45=0,J$6=0),$G45,IF(AND(J$6>=$C45,J$6<($C45+$D45)),$G45/$D45,0)) -> 0 | K45: =IF(AND($C45=0,$D45=0,K$6=0),$G45,IF(AND(K$6>=$C45,K$6<($C45+$D45)),$G45/$D45,0)) -> 0 | L45: =IF(AND($C45=0,$D45=0,L$6=0),$G45,IF(AND(L$6>=$C45,L$6<($C45+$D45)),$G45/$D45,0)) -> 0 | M45: =IF(AND($C45=0,$D45=0,M$6=0),$G45,IF(AND(M$6>=$C45,M$6<($C45+$D45)),$G45/$D45,0)) -> 0 | N45: =IF(AND($C45=0,$D45=0,N$6=0),$G45,IF(AND(N$6>=$C45,N$6<($C45+$D45)),$G45/$D45,0)) -> 0 | O45: =IF(AND($C45=0,$D45=0,O$6=0),$G45,IF(AND(O$6>=$C45,O$6<($C45+$D45)),$G45/$D45,0)) -> 0 | P45: =IF(AND($C45=0,$D45=0,P$6=0),$G45,IF(AND(P$6>=$C45,P$6<($C45+$D45)),$G45/$D45,0)) -> 0 | ... DY45: =IF(AND($C45=0,$D45=0,DY$6=0),$G45,IF(AND(DY$6>=$C45,DY$6<($C45+$D45)),$G45/$D45,0)) -> 0
B46: Total Wind River Group Fees | E46: =iferror(G46/$E$6,"") -> 6.5163918 | F46: =iferror(G46/$F$6,"") -> 5440.231 | G46: =sum(G44:G45) -> 1001002.5 | I46: =sum(I44:I45) -> 1001002.5 | J46: =sum(J44:J45) -> 0 | K46: =sum(K44:K45) -> 0 | L46: =sum(L44:L45) -> 0 | M46: =sum(M44:M45) -> 0 | N46: =sum(N44:N45) -> 0 | O46: =sum(O44:O45) -> 0 | P46: =sum(P44:P45) -> 0 | ... DY46: =sum(DY44:DY45) -> 0
B48: Total Project Cost (Pre Lender Reserves) | E48: =iferror(G48/$E$6,"") -> 263.7648 | F48: =iferror(G48/$F$6,"") -> 220204.9 | G48: =sum(G20,G31,G41,G46) -> 40517702 | I48: =sum(I20,I31,I41,I46) -> 40517702 | J48: =sum(J20,J31,J41,J46) -> 0 | K48: =sum(K20,K31,K41,K46) -> 0 | L48: =sum(L20,L31,L41,L46) -> 0 | M48: =sum(M20,M31,M41,M46) -> 0 | N48: =sum(N20,N31,N41,N46) -> 0 | O48: =sum(O20,O31,O41,O46) -> 0 | P48: =sum(P20,P31,P41,P46) -> 0 | ... DY48: =sum(DY20,DY31,DY41,DY46) -> 0

Sheet Capital Stack
G2: Loan Information | K2: Sources & Uses
B3: ='Property Summary'!B3 -> Phoenix, AZ | G3: ='Property Summary'!I3 -> Wind River Group | I3: ='Property Summary'!B3 -> Phoenix, AZ | K3: ='Property Summary'!I3 -> Wind River Group
B5: Loan Information | C5: Acquisition Loan | D5: Refinance Loan | F5: Current Treasuries | G5: Rate | I5: Sources | J5: Amount | K5: % of Sources
B6: Term | C6: 7 | D6: 7 | F6: 3 | G6: 0.0434 | I6: Senior Loan | J6: =C17 -> 21900000 | K6: =iferror(J6/$J$10,"") -> 0.54050449
B7: Rate Index | C7: =C6 -> 7 | D7: =D6 -> 7 | F7: 5 | G7: 0.04428 | I7: Mezzanine Loan | J7: 0 | K7: =iferror(J7/$J$10,"") -> 0
B8: Current Rate | C8: =lookup(C7,$F$6:$F$9,$G$6:$G$9) -> 0.04377 | D8: =lookup(D7,$F$6:$F$9,$G$6:$G$9) -> 0.04377 | F8: 7 | G8: 0.04377 | I8: Limited Partner(s) Equity | J8: =($J$20-sum($J$6:$J$7))*'Investment Summary'!F19 -> 18617702 | K8: =iferror(J8/$J$10,"") -> 0.45949551
B9: Rate Type | C9: Fixed | D9: Fixed | F9: 10 | G9: 0.04623 | I9: General Partner Equity | J9: =($J$20-sum($J$6:$J$7))*(1-'Investment Summary'!F19) -> 0 | K9: =iferror(J9/$J$10,"") -> 0
B10: Spread | C10: 99 | D10: 120 | I10: Total Sources | J10: =sum(J6:J9) -> 40517702 | K10: =iferror(J10/$J$10,"") -> 1
B11: Interest Rate | C11: =sum(C8,C10/10000) -> 0.05367 | D11: =sum(D8,D10/10000) -> 0.05577
B12: Interest Only Period | C12: 84 | D12: 84 | I12: Uses | J12: Amount | K12: % of Uses
B13: Amortization | C13: 30 | D13: 30 | I13: Purchase Price | J13: ='Project Budget'!G8 -> 36500000 | K13: =iferror(J13/$J$20,"") -> 0.90084081
B14: Loan to Purchase Price | C14: 0.6 | I14: Acquisition Costs | J14: ='Project Budget'!G20-'Project Budget'!G8 -> 282500 | K14: =iferror(J14/$J$20,"") -> 0.0069722611
B15: Loan to Value (LTV) | D15: 0.65 | I15: CapEx Budget | J15: ='Project Budget'!G31 -> 2070050 | K15: =iferror(J15/$J$20,"") -> 0.051090014
B16: Minimum DSCR | C16: 1.35 | D16: 1.35 | I16: Financing Costs | J16: ='Project Budget'!G41 -> 664150 | K16: =iferror(J16/$J$20,"") -> 0.016391601
B17: Loan Amount | C17: =iferror(C14*'Project Budget'!G8,"") -> 21900000 | D17: =iferror(((lookup('Investment Summary'!F8,'Cash Flows'!$E$57:$DT$57,'Cash Flows'!$E$92:$DT$92)*12)/'Investment Summary'!F11)*D15,0) -> 0 | I17: Acquisition Fee | J17: ='Project Budget'!G44 -> 912500 | K17: =iferror(J17/$J$20,"") -> 0.02252102
C18: ='Cash Flows'!C40 -> 1.8439472 | D18: ='Cash Flows'!C124 -> 0 | I18: CapEx Management Fee | J18: ='Project Budget'!G45 -> 88502.5 | K18: =iferror(J18/$J$20,"") -> 0.0021842922
I19: Lender Operating Reserves | J19: =sum('Cash Flows'!$D$47:$M$47) -> 0 | K19: =iferror(J19/$J$20,"") -> 0
I20: Total Uses | J20: =sum(J13:J19) -> 40517702 | K20: =iferror(J20/$J$20,"") -> 1

Sheet Cash Flows
M2: Cash Flows
B3: ='Property Summary'!B3 -> Phoenix, AZ | M3: ='Property Summary'!I3 -> Wind River Group
C5: T-12 | D5: 1 | E5: 2 | F5: 3 | G5: 4 | H5: 5 | I5: 6 | J5: 7 | K5: 8 | L5: 9 | M5: 10
B6: Year End Total Units | C6: =Revenue!C42 -> 184 | D6: =lookup(D$5*12,$E$57:$DT$57,$E59:$DT59) -> 184 | E6: =lookup(E$5*12,$E$57:$DT$57,$E59:$DT59) -> 184 | F6: =lookup(F$5*12,$E$57:$DT$57,$E59:$DT59) -> 184 | G6: =lookup(G$5*12,$E$57:$DT$57,$E59:$DT59) -> 184 | H6: =lookup(H$5*12,$E$57:$DT$57,$E59:$DT59) -> 184 | I6: =lookup(I$5*12,$E$57:$DT$57,$E59:$DT59) -> 184 | J6: =lookup(J$5*12,$E$57:$DT$57,$E59:$DT59) -> 184 | K6: =lookup(K$5*12,$E$57:$DT$57,$E59:$DT59) -> 184 | ... M6: =lookup(M$5*12,$E$57:$DT$57,$E59:$DT59) -> 184
B7: Year End Offline Units | C7: =Revenue!C43 -> 0 | D7: =lookup(D$5*12,$E$57:$DT$57,$E60:$DT60) -> 3 | E7: =lookup(E$5*12,$E$57:$DT$57,$E60:$DT60) -> 0 | F7: =lookup(F$5*12,$E$57:$DT$57,$E60:$DT60) -> 0 | G7: =lookup(G$5*12,$E$57:$DT$57,$E60:$DT60) -> 0 | H7: =lookup(H$5*12,$E$57:$DT$57,$E60:$DT60) -> 0 | I7: =lookup(I$5*12,$E$57:$DT$57,$E60:$DT60) -> 0 | J7: =lookup(J$5*12,$E$57:$DT$57,$E60:$DT60) -> 0 | K7: =lookup(K$5*12,$E$57:$DT$57,$E60:$DT60) -> 0 | ... M7: =lookup(M$5*12,$E$57:$DT$57,$E60:$DT60) -> 0
B8: Total Renovated Units | C8: =Revenue!C44 -> 0 | D8: =lookup(D$5*12,$E$57:$DT$57,$E61:$DT61) -> 24 | E8: =lookup(E$5*12,$E$57:$DT$57,$E61:$DT61) -> 49 | F8: =lookup(F$5*12,$E$57:$DT$57,$E61:$DT61) -> 49 | G8: =lookup(G$5*12,$E$57:$DT$57,$E61:$DT61) -> 49 | H8: =lookup(H$5*12,$E$57:$DT$57,$E61:$DT61) -> 49 | I8: =lookup(I$5*12,$E$57:$DT$57,$E61:$DT61) -> 49 | J8: =lookup(J$5*12,$E$57:$DT$57,$E61:$DT61) -> 49 | K8: =lookup(K$5*12,$E$57:$DT$57,$E61:$DT61) -> 49 | ... M8: =lookup(M$5*12,$E$57:$DT$57,$E61:$DT61) -> 49
B9: Year End Occupancy % (Excl Offline Units) | C9: =Revenue!C45 -> 0.91847826 | D9: =lookup(D$5*12,$E$57:$DT$57,$E62:$DT62) -> 0.92 | E9: =lookup(E$5*12,$E$57:$DT$57,$E62:$DT62) -> 0.92 | F9: =lookup(F$5*12,$E$57:$DT$57,$E62:$DT62) -> 0.93 | G9: =lookup(G$5*12,$E$57:$DT$57,$E62:$DT62) -> 0.93 | H9: =lookup(H$5*12,$E$57:$DT$57,$E62:$DT62) -> 0.93 | I9: =lookup(I$5*12,$E$57:$DT$57,$E62:$DT62) -> 0.93 | J9: =lookup(J$5*12,$E$57:$DT$57,$E62:$DT62) -> 0.93 | K9: =lookup(K$5*12,$E$57:$DT$57,$E62:$DT62) -> 0.93 | ... M9: =lookup(M$5*12,$E$57:$DT$57,$E62:$DT62) -> 0.93
B10: Loss to Lease % | C10: =Revenue!C46 -> 0.071881657 | D10: =iferror(-D14/D13,"") -> 0.061749222 | E10: =iferror(-E14/E13,"") -> 0.044981851 | F10: =iferror(-F14/F13,"") -> 0.041006083 | G10: =iferror(-G14/G13,"") -> 0.041006083 | H10: =iferror(-H14/H13,"") -> 0.041006083 | I10: =iferror(-I14/I13,"") -> 0.041006083 | J10: =iferror(-J14/J13,"") -> 0.041006083 | K10: =iferror(-K14/K13,"") -> 0.041006083 | ... M10: =iferror(-M14/M13,"") -> 0.041006083
B12: Total Revenue
B13: Potential Rental Income | C13: =Revenue!C49 -> 3425241 | D13: =iferror(sumif($E$56:$DT$56,D$5,$E66:$DT66),"") -> 3407565.1 | E13: =iferror(sumif($E$56:$DT$56,E$5,$E66:$DT66),"") -> 3526829.8 | F13: =iferror(sumif($E$56:$DT$56,F$5,$E66:$DT66),"") -> 3650268.9 | G13: =iferror(sumif($E$56:$DT$56,G$5,$E66:$DT66),"") -> 3778028.3 | H13: =iferror(sumif($E$56:$DT$56,H$5,$E66:$DT66),"") -> 3910259.3 | I13: =iferror(sumif($E$56:$DT$56,I$5,$E66:$DT66),"") -> 4047118.4 | J13: =iferror(sumif($E$56:$DT$56,J$5,$E66:$DT66),"") -> 4188767.5 | K13: =iferror(sumif($E$56:$DT$56,K$5,$E66:$DT66),"") -> 4335374.4 | ... M13: =iferror(sumif($E$56:$DT$56,M$5,$E66:$DT66),"") -> 4644161.4
B14: Loss to Lease | C14: =Revenue!C50 -> -246212 | D14: =iferror(sumif($E$56:$DT$56,D$5,$E67:$DT67),"") -> -210414.49 | E14: =iferror(sumif($E$56:$DT$56,E$5,$E67:$DT67),"") -> -158643.34 | F14: =iferror(sumif($E$56:$DT$56,F$5,$E67:$DT67),"") -> -149683.23 | G14: =iferror(sumif($E$56:$DT$56,G$5,$E67:$DT67),"") -> -154922.14 | H14: =iferror(sumif($E$56:$DT$56,H$5,$E67:$DT67),"") -> -160344.42 | I14: =iferror(sumif($E$56:$DT$56,I$5,$E67:$DT67),"") -> -165956.47 | J14: =iferror(sumif($E$56:$DT$56,J$5,$E67:$DT67),"") -> -171764.95 | K14: =iferror(sumif($E$56:$DT$56,K$5,$E67:$DT67),"") -> -177776.72 | ... M14: =iferror(sumif($E$56:$DT$56,M$5,$E67:$DT67),"") -> -190438.87
B15: Vacancy Loss | C15: =Revenue!C51 -> -255589.29 | D15: =iferror(sumif($E$56:$DT$56,D$5,$E68:$DT68),"") -> -255772.05 | E15: =iferror(sumif($E$56:$DT$56,E$5,$E68:$DT68),"") -> -269454.92 | F15: =iferror(sumif($E$56:$DT$56,F$5,$E68:$DT68),"") -> -245041 | G15: =iferror(sumif($E$56:$DT$56,G$5,$E68:$DT68),"") -> -253617.43 | H15: =iferror(sumif($E$56:$DT$56,H$5,$E68:$DT68),"") -> -262494.04 | I15: =iferror(sumif($E$56:$DT$56,I$5,$E68:$DT68),"") -> -271681.33 | J15: =iferror(sumif($E$56:$DT$56,J$5,$E68:$DT68),"") -> -281190.18 | K15: =iferror(sumif($E$56:$DT$56,K$5,$E68:$DT68),"") -> -291031.83 | ... M15: =iferror(sumif($E$56:$DT$56,M$5,$E68:$DT68),"") -> -311760.58
B16: Offline Renovation Loss | C16: =Revenue!C52 -> 0 | D16: =iferror(sumif($E$56:$DT$56,D$5,$E69:$DT69),"") -> -41668.594 | E16: =iferror(sumif($E$56:$DT$56,E$5,$E69:$DT69),"") -> -35140.515 | F16: =iferror(sumif($E$56:$DT$56,F$5,$E69:$DT69),"") -> 0 | G16: =iferror(sumif($E$56:$DT$56,G$5,$E69:$DT69),"") -> 0 | H16: =iferror(sumif($E$56:$DT$56,H$5,$E69:$DT69),"") -> 0 | I16: =iferror(sumif($E$56:$DT$56,I$5,$E69:$DT69),"") -> 0 | J16: =iferror(sumif($E$56:$DT$56,J$5,$E69:$DT69),"") -> 0 | K16: =iferror(sumif($E$56:$DT$56,K$5,$E69:$DT69),"") -> 0 | ... M16: =iferror(sumif($E$56:$DT$56,M$5,$E69:$DT69),"") -> 0
B17: Bad Debt Expense | C17: =Revenue!C53 -> -42218.63 | D17: =iferror(sumif($E$56:$DT$56,D$5,$E70:$DT70),"") -> -43495.649 | E17: =iferror(sumif($E$56:$DT$56,E$5,$E70:$DT70),"") -> -38294.888 | F17: =iferror(sumif($E$56:$DT$56,F$5,$E70:$DT70),"") -> -40694.308 | G17: =iferror(sumif($E$56:$DT$56,G$5,$E70:$DT70),"") -> -42118.609 | H17: =iferror(sumif($E$56:$DT$56,H$5,$E70:$DT70),"") -> -43592.76 | I17: =iferror(sumif($E$56:$DT$56,I$5,$E70:$DT70),"") -> -45118.507 | J17: =iferror(sumif($E$56:$DT$56,J$5,$E70:$DT70),"") -> -46697.655 | K17: =iferror(sumif($E$56:$DT$56,K$5,$E70:$DT70),"") -> -48332.073 | ... M17: =iferror(sumif($E$56:$DT$56,M$5,$E70:$DT70),"") -> -51774.524
B18: Concessions | C18: =Revenue!C54 -> -53858.32 | D18: =iferror(sumif($E$56:$DT$56,D$5,$E71:$DT71),"") -> -36246.374 | E18: =iferror(sumif($E$56:$DT$56,E$5,$E71:$DT71),"") -> -38294.888 | F18: =iferror(sumif($E$56:$DT$56,F$5,$E71:$DT71),"") -> -40694.308 | G18: =iferror(sumif($E$56:$DT$56,G$5,$E71:$DT71),"") -> -42118.609 | H18: =iferror(sumif($E$56:$DT$56,H$5,$E71:$DT71),"") -> -43592.76 | I18: =iferror(sumif($E$56:$DT$56,I$5,$E71:$DT71),"") -> -45118.507 | J18: =iferror(sumif($E$56:$DT$56,J$5,$E71:$DT71),"") -> -46697.655 | K18: =iferror(sumif($E$56:$DT$56,K$5,$E71:$DT71),"") -> -48332.073 | ... M18: =iferror(sumif($E$56:$DT$56,M$5,$E71:$DT71),"") -> -51774.524
B19: Total Rental Income | C19: =Revenue!C55 -> 2827362.8 | D19: =iferror(sumif($E$56:$DT$56,D$5,$E72:$DT72),"") -> 2819967.9 | E19: =iferror(sumif($E$56:$DT$56,E$5,$E72:$DT72),"") -> 2987001.3 | F19: =iferror(sumif($E$56:$DT$56,F$5,$E72:$DT72),"") -> 3174156 | G19: =iferror(sumif($E$56:$DT$56,G$5,$E72:$DT72),"") -> 3285251.5 | H19: =iferror(sumif($E$56:$DT$56,H$5,$E72:$DT72),"") -> 3400235.3 | I19: =iferror(sumif($E$56:$DT$56,I$5,$E72:$DT72),"") -> 3519243.5 | J19: =iferror(sumif($E$56:$DT$56,J$5,$E72:$DT72),"") -> 3642417.1 | K19: =iferror(sumif($E$56:$DT$56,K$5,$E72:$DT72),"") -> 3769901.7 | ... M19: =iferror(sumif($E$56:$DT$56,M$5,$E72:$DT72),"") -> 4038412.9
B20: Total RUBS Income | C20: =Revenue!C56 -> 184233.56 | D20: =iferror(sumif($E$56:$DT$56,D$5,$E73:$DT73),"") -> 184401.12 | E20: =iferror(sumif($E$56:$DT$56,E$5,$E73:$DT73),"") -> 188558.34 | F20: =iferror(sumif($E$56:$DT$56,F$5,$E73:$DT73),"") -> 196548.71 | G20: =iferror(sumif($E$56:$DT$56,G$5,$E73:$DT73),"") -> 200479.68 | H20: =iferror(sumif($E$56:$DT$56,H$5,$E73:$DT73),"") -> 204489.27 | I20: =iferror(sumif($E$56:$DT$56,I$5,$E73:$DT73),"") -> 208579.06 | J20: =iferror(sumif($E$56:$DT$56,J$5,$E73:$DT73),"") -> 212750.64 | K20: =iferror(sumif($E$56:$DT$56,K$5,$E73:$DT73),"") -> 217005.65 | ... M20: =iferror(sumif($E$56:$DT$56,M$5,$E73:$DT73),"") -> 225772.68
B21: Total Other Income | C21: =Revenue!C57 -> 401184.55 | D21: =iferror(sumif($E$56:$DT$56,D$5,$E74:$DT74),"") -> 405000 | E21: =iferror(sumif($E$56:$DT$56,E$5,$E74:$DT74),"") -> 413100 | F21: =iferror(sumif($E$56:$DT$56,F$5,$E74:$DT74),"") -> 421362 | G21: =iferror(sumif($E$56:$DT$56,G$5,$E74:$DT74),"") -> 429789.24 | H21: =iferror(sumif($E$56:$DT$56,H$5,$E74:$DT74),"") -> 438385.02 | I21: =iferror(sumif($E$56:$DT$56,I$5,$E74:$DT74),"") -> 447152.73 | J21: =iferror(sumif($E$56:$DT$56,J$5,$E74:$DT74),"") -> 456095.78 | K21: =iferror(sumif($E$56:$DT$56,K$5,$E74:$DT74),"") -> 465217.7 | ... M21: =iferror(sumif($E$56:$DT$56,M$5,$E74:$DT74),"") -> 484012.49
B22: Total Revenue | C22: =Revenue!C58 -> 3412780.9 | D22: =iferror(sumif($E$56:$DT$56,D$5,$E75:$DT75),"") -> 3409369 | E22: =iferror(sumif($E$56:$DT$56,E$5,$E75:$DT75),"") -> 3588659.6 | F22: =iferror(sumif($E$56:$DT$56,F$5,$E75:$DT75),"") -> 3792066.7 | G22: =iferror(sumif($E$56:$DT$56,G$5,$E75:$DT75),"") -> 3915520.4 | H22: =iferror(sumif($E$56:$DT$56,H$5,$E75:$DT75),"") -> 4043109.6 | I22: =iferror(sumif($E$56:$DT$56,I$5,$E75:$DT75),"") -> 4174975.3 | J22: =iferror(sumif($E$56:$DT$56,J$5,$E75:$DT75),"") -> 4311263.5 | K22: =iferror(sumif($E$56:$DT$56,K$5,$E75:$DT75),"") -> 4452125 | ... M22: =iferror(sumif($E$56:$DT$56,M$5,$E75:$DT75),"") -> 4748198.1
B24: Operating Expenses
B25: Total General & Admin | C25: =Expenses!C32 -> 126768.37 | D25: =iferror(sumif($E$56:$DT$56,D$5,$E78:$DT78),"") -> 127880 | E25: =iferror(sumif($E$56:$DT$56,E$5,$E78:$DT78),"") -> 131077 | F25: =iferror(sumif($E$56:$DT$56,F$5,$E78:$DT78),"") -> 134353.92 | G25: =iferror(sumif($E$56:$DT$56,G$5,$E78:$DT78),"") -> 137712.77 | H25: =iferror(sumif($E$56:$DT$56,H$5,$E78:$DT78),"") -> 141155.59 | I25: =iferror(sumif($E$56:$DT$56,I$5,$E78:$DT78),"") -> 144684.48 | J25: =iferror(sumif($E$56:$DT$56,J$5,$E78:$DT78),"") -> 148301.59 | K25: =iferror(sumif($E$56:$DT$56,K$5,$E78:$DT78),"") -> 152009.13 | ... M25: =iferror(sumif($E$56:$DT$56,M$5,$E78:$DT78),"") -> 159704.6
B26: Total Payroll | C26: =Expenses!C33 -> 324615.54 | D26: =iferror(sumif($E$56:$DT$56,D$5,$E79:$DT79),"") -> 324480 | E26: =iferror(sumif($E$56:$DT$56,E$5,$E79:$DT79),"") -> 332592 | F26: =iferror(sumif($E$56:$DT$56,F$5,$E79:$DT79),"") -> 340906.8 | G26: =iferror(sumif($E$56:$DT$56,G$5,$E79:$DT79),"") -> 349429.47 | H26: =iferror(sumif($E$56:$DT$56,H$5,$E79:$DT79),"") -> 358165.21 | I26: =iferror(sumif($E$56:$DT$56,I$5,$E79:$DT79),"") -> 367119.34 | J26: =iferror(sumif($E$56:$DT$56,J$5,$E79:$DT79),"") -> 376297.32 | K26: =iferror(sumif($E$56:$DT$56,K$5,$E79:$DT79),"") -> 385704.75 | ... M26: =iferror(sumif($E$56:$DT$56,M$5,$E79:$DT79),"") -> 405231.06
B27: Total Leasing & Marketing | C27: =Expenses!C34 -> 86807.36 | D27: =iferror(sumif($E$56:$DT$56,D$5,$E80:$DT80),"") -> 87400 | E27: =iferror(sumif($E$56:$DT$56,E$5,$E80:$DT80),"") -> 89585 | F27: =iferror(sumif($E$56:$DT$56,F$5,$E80:$DT80),"") -> 91824.625 | G27: =iferror(sumif($E$56:$DT$56,G$5,$E80:$DT80),"") -> 94120.241 | H27: =iferror(sumif($E$56:$DT$56,H$5,$E80:$DT80),"") -> 96473.247 | I27: =iferror(sumif($E$56:$DT$56,I$5,$E80:$DT80),"") -> 98885.078 | J27: =iferror(sumif($E$56:$DT$56,J$5,$E80:$DT80),"") -> 101357.2 | K27: =iferror(sumif($E$56:$DT$56,K$5,$E80:$DT80),"") -> 103891.13 | ... M27: =iferror(sumif($E$56:$DT$56,M$5,$E80:$DT80),"") -> 109150.62
B28: Total Utilities | C28: =Expenses!C35 -> 262578.11 | D28: =iferror(sumif($E$56:$DT$56,D$5,$E81:$DT81),"") -> 264960 | E28: =iferror(sumif($E$56:$DT$56,E$5,$E81:$DT81),"") -> 271584 | F28: =iferror(sumif($E$56:$DT$56,F$5,$E81:$DT81),"") -> 278373.6 | G28: =iferror(sumif($E$56:$DT$56,G$5,$E81:$DT81),"") -> 285332.94 | H28: =iferror(sumif($E$56:$DT$56,H$5,$E81:$DT81),"") -> 292466.26 | I28: =iferror(sumif($E$56:$DT$56,I$5,$E81:$DT81),"") -> 299777.92 | J28: =iferror(sumif($E$56:$DT$56,J$5,$E81:$DT81),"") -> 307272.37 | K28: =iferror(sumif($E$56:$DT$56,K$5,$E81:$DT81),"") -> 314954.18 | ... M28: =iferror(sumif($E$56:$DT$56,M$5,$E81:$DT81),"") -> 330898.73
B29: Total Repairs & Maintenance | C29: =Expenses!C36 -> 55342.64 | D29: =iferror(sumif($E$56:$DT$56,D$5,$E82:$DT82),"") -> 56120 | E29: =iferror(sumif($E$56:$DT$56,E$5,$E82:$DT82),"") -> 57523 | F29: =iferror(sumif($E$56:$DT$56,F$5,$E82:$DT82),"") -> 58961.075 | G29: =iferror(sumif($E$56:$DT$56,G$5,$E82:$DT82),"") -> 60435.102 | H29: =iferror(sumif($E$56:$DT$56,H$5,$E82:$DT82),"") -> 61945.979 | I29: =iferror(sumif($E$56:$DT$56,I$5,$E82:$DT82),"") -> 63494.629 | J29: =iferror(sumif($E$56:$DT$56,J$5,$E82:$DT82),"") -> 65081.995 | K29: =iferror(sumif($E$56:$DT$56,K$5,$E82:$DT82),"") -> 66709.045 | ... M29: =iferror(sumif($E$56:$DT$56,M$5,$E82:$DT82),"") -> 70086.19
B30: Total HOA Assessments | C30: =Expenses!C37 -> 20329.82 | D30: =iferror(sumif($E$56:$DT$56,D$5,$E83:$DT83),"") -> 21160 | E30: =iferror(sumif($E$56:$DT$56,E$5,$E83:$DT83),"") -> 21689 | F30: =iferror(sumif($E$56:$DT$56,F$5,$E83:$DT83),"") -> 22231.225 | G30: =iferror(sumif($E$56:$DT$56,G$5,$E83:$DT83),"") -> 22787.006 | H30: =iferror(sumif($E$56:$DT$56,H$5,$E83:$DT83),"") -> 23356.681 | I30: =iferror(sumif($E$56:$DT$56,I$5,$E83:$DT83),"") -> 23940.598 | J30: =iferror(sumif($E$56:$DT$56,J$5,$E83:$DT83),"") -> 24539.113 | K30: =iferror(sumif($E$56:$DT$56,K$5,$E83:$DT83),"") -> 25152.591 | ... M30: =iferror(sumif($E$56:$DT$56,M$5,$E83:$DT83),"") -> 26425.94
B31: Total Turnover Expense | C31: =Expenses!C38 -> 22404.11 | D31: =iferror(sumif($E$56:$DT$56,D$5,$E84:$DT84),"") -> 23000 | E31: =iferror(sumif($E$56:$DT$56,E$5,$E84:$DT84),"") -> 23575 | F31: =iferror(sumif($E$56:$DT$56,F$5,$E84:$DT84),"") -> 24164.375 | G31: =iferror(sumif($E$56:$DT$56,G$5,$E84:$DT84),"") -> 24768.484 | H31: =iferror(sumif($E$56:$DT$56,H$5,$E84:$DT84),"") -> 25387.696 | I31: =iferror(sumif($E$56:$DT$56,I$5,$E84:$DT84),"") -> 26022.389 | J31: =iferror(sumif($E$56:$DT$56,J$5,$E84:$DT84),"") -> 26672.949 | K31: =iferror(sumif($E$56:$DT$56,K$5,$E84:$DT84),"") -> 27339.772 | ... M31: =iferror(sumif($E$56:$DT$56,M$5,$E84:$DT84),"") -> 28723.848
B32: Total Contract Services | C32: =Expenses!C39 -> 46032.26 | D32: =iferror(sumif($E$56:$DT$56,D$5,$E85:$DT85),"") -> 46920 | E32: =iferror(sumif($E$56:$DT$56,E$5,$E85:$DT85),"") -> 48093 | F32: =iferror(sumif($E$56:$DT$56,F$5,$E85:$DT85),"") -> 49295.325 | G32: =iferror(sumif($E$56:$DT$56,G$5,$E85:$DT85),"") -> 50527.708 | H32: =iferror(sumif($E$56:$DT$56,H$5,$E85:$DT85),"") -> 51790.901 | I32: =iferror(sumif($E$56:$DT$56,I$5,$E85:$DT85),"") -> 53085.673 | J32: =iferror(sumif($E$56:$DT$56,J$5,$E85:$DT85),"") -> 54412.815 | K32: =iferror(sumif($E$56:$DT$56,K$5,$E85:$DT85),"") -> 55773.136 | ... M32: =iferror(sumif($E$56:$DT$56,M$5,$E85:$DT85),"") -> 58596.651
B33: Total Insurance Expense | C33: =Expenses!C40 -> 53468.94 | D33: =iferror(sumif($E$56:$DT$56,D$5,$E86:$DT86),"") -> 54280 | E33: =iferror(sumif($E$56:$DT$56,E$5,$E86:$DT86),"") -> 54822.8 | F33: =iferror(sumif($E$56:$DT$56,F$5,$E86:$DT86),"") -> 55371.028 | G33: =iferror(sumif($E$56:$DT$56,G$5,$E86:$DT86),"") -> 55924.738 | H33: =iferror(sumif($E$56:$DT$56,H$5,$E86:$DT86),"") -> 56483.986 | I33: =iferror(sumif($E$56:$DT$56,I$5,$E86:$DT86),"") -> 57048.826 | J33: =iferror(sumif($E$56:$DT$56,J$5,$E86:$DT86),"") -> 57619.314 | K33: =iferror(sumif($E$56:$DT$56,K$5,$E86:$DT86),"") -> 58195.507 | ... M33: =iferror(sumif($E$56:$DT$56,M$5,$E86:$DT86),"") -> 59365.237
B34: Total Property Taxes | C34: =Expenses!C41 -> 142164.14 | D34: =iferror(sumif($E$56:$DT$56,D$5,$E87:$DT87),"") -> 149272.2 | E34: =iferror(sumif($E$56:$DT$56,E$5,$E87:$DT87),"") -> 156735.81 | F34: =iferror(sumif($E$56:$DT$56,F$5,$E87:$DT87),"") -> 164572.6 | G34: =iferror(sumif($E$56:$DT$56,G$5,$E87:$DT87),"") -> 172801.23 | H34: =iferror(sumif($E$56:$DT$56,H$5,$E87:$DT87),"") -> 181441.29 | I34: =iferror(sumif($E$56:$DT$56,I$5,$E87:$DT87),"") -> 190513.36 | J34: =iferror(sumif($E$56:$DT$56,J$5,$E87:$DT87),"") -> 200039.02 | K34: =iferror(sumif($E$56:$DT$56,K$5,$E87:$DT87),"") -> 202039.41 | ... M34: =iferror(sumif($E$56:$DT$56,M$5,$E87:$DT87),"") -> 206100.41
B35: Total Management Fees | C35: =Expenses!C42 -> 104943.81 | D35: =iferror(sumif($E$56:$DT$56,D$5,$E88:$DT88),"") -> 102281.07 | E35: =iferror(sumif($E$56:$DT$56,E$5,$E88:$DT88),"") -> 107659.79 | F35: =iferror(sumif($E$56:$DT$56,F$5,$E88:$DT88),"") -> 113762 | G35: =iferror(sumif($E$56:$DT$56,G$5,$E88:$DT88),"") -> 117465.61 | H35: =iferror(sumif($E$56:$DT$56,H$5,$E88:$DT88),"") -> 121293.29 | I35: =iferror(sumif($E$56:$DT$56,I$5,$E88:$DT88),"") -> 125249.26 | J35: =iferror(sumif($E$56:$DT$56,J$5,$E88:$DT88),"") -> 129337.9 | K35: =iferror(sumif($E$56:$DT$56,K$5,$E88:$DT88),"") -> 133563.75 | ... M35: =iferror(sumif($E$56:$DT$56,M$5,$E88:$DT88),"") -> 142445.94
B36: Total Operating Expenses | C36: =Expenses!C43 -> 1245455.1 | D36: =iferror(sumif($E$56:$DT$56,D$5,$E89:$DT89),"") -> 1257753.3 | E36: =iferror(sumif($E$56:$DT$56,E$5,$E89:$DT89),"") -> 1294936.4 | F36: =iferror(sumif($E$56:$DT$56,F$5,$E89:$DT89),"") -> 1333816.6 | G36: =iferror(sumif($E$56:$DT$56,G$5,$E89:$DT89),"") -> 1371305.3 | H36: =iferror(sumif($E$56:$DT$56,H$5,$E89:$DT89),"") -> 1409960.1 | I36: =iferror(sumif($E$56:$DT$56,I$5,$E89:$DT89),"") -> 1449821.5 | J36: =iferror(sumif($E$56:$DT$56,J$5,$E89:$DT89),"") -> 1490931.6 | K36: =iferror(sumif($E$56:$DT$56,K$5,$E89:$DT89),"") -> 1525332.4 | ... M36: =iferror(sumif($E$56:$DT$56,M$5,$E89:$DT89),"") -> 1596729.2
B37: Expense Ratio | C37: =Expenses!C44 -> 0.36493849 | D37: =iferror(D36/D22,"") -> 0.36891086 | E37: =iferror(E36/E22,"") -> 0.36084124 | F37: =iferror(F36/F22,"") -> 0.35173869 | G37: =iferror(G36/G22,"") -> 0.350223 | H37: =iferror(H36/H22,"") -> 0.34873161 | I37: =iferror(I36/I22,"") -> 0.3472647 | J37: =iferror(J36/J22,"") -> 0.34582243 | K37: =iferror(K36/K22,"") -> 0.34260772 | ... M37: =iferror(M36/M22,"") -> 0.33628109
B39: Net Operating Income | C39: =iferror(C22-C36,"") -> 2167325.8 | D39: =iferror(sumif($E$56:$DT$56,D$5,$E92:$DT92),"") -> 2151615.7 | E39: =iferror(sumif($E$56:$DT$56,E$5,$E92:$DT92),"") -> 2293723.2 | F39: =iferror(sumif($E$56:$DT$56,F$5,$E92:$DT92),"") -> 2458250.2 | G39: =iferror(sumif($E$56:$DT$56,G$5,$E92:$DT92),"") -> 2544215.1 | H39: =iferror(sumif($E$56:$DT$56,H$5,$E92:$DT92),"") -> 2633149.5 | I39: =iferror(sumif($E$56:$DT$56,I$5,$E92:$DT92),"") -> 2725153.8 | J39: =iferror(sumif($E$56:$DT$56,J$5,$E92:$DT92),"") -> 2820331.9 | K39: =iferror(sumif($E$56:$DT$56,K$5,$E92:$DT92),"") -> 2926792.6 | ... M39: =iferror(sumif($E$56:$DT$56,M$5,$E92:$DT92),"") -> 3151468.8
C40: =C39/-sum(D45:D46) -> 1.8439472
B41: Asset Management Fees | D41: =iferror(sumif($E$56:$DT$56,D$5,$E94:$DT94),"") -> -68187.38 | E41: =iferror(sumif($E$56:$DT$56,E$5,$E94:$DT94),"") -> -71773.193 | F41: =iferror(sumif($E$56:$DT$56,F$5,$E94:$DT94),"") -> -75841.335 | G41: =iferror(sumif($E$56:$DT$56,G$5,$E94:$DT94),"") -> -78310.408 | H41: =iferror(sumif($E$56:$DT$56,H$5,$E94:$DT94),"") -> -80862.192 | I41: =iferror(sumif($E$56:$DT$56,I$5,$E94:$DT94),"") -> -83499.506 | J41: =iferror(sumif($E$56:$DT$56,J$5,$E94:$DT94),"") -> -86225.27 | K41: =iferror(sumif($E$56:$DT$56,K$5,$E94:$DT94),"") -> -89042.5 | ... M41: =iferror(sumif($E$56:$DT$56,M$5,$E94:$DT94),"") -> -94963.961
B42: 1000 | D42: =iferror(sumif($E$56:$DT$56,D$5,$E95:$DT95),"") -> -184000 | E42: =iferror(sumif($E$56:$DT$56,E$5,$E95:$DT95),"") -> -184000 | F42: =iferror(sumif($E$56:$DT$56,F$5,$E95:$DT95),"") -> -184000 | G42: =iferror(sumif($E$56:$DT$56,G$5,$E95:$DT95),"") -> -184000 | H42: =iferror(sumif($E$56:$DT$56,H$5,$E95:$DT95),"") -> -184000 | I42: =iferror(sumif($E$56:$DT$56,I$5,$E95:$DT95),"") -> -184000 | J42: =iferror(sumif($E$56:$DT$56,J$5,$E95:$DT95),"") -> -184000 | K42: =iferror(sumif($E$56:$DT$56,K$5,$E95:$DT95),"") -> -184000 | ... M42: =iferror(sumif($E$56:$DT$56,M$5,$E95:$DT95),"") -> -184000
B43: Operating Cash Flow | D43: =iferror(sumif($E$56:$DT$56,D$5,$E96:$DT96),"") -> 1899428.4 | E43: =iferror(sumif($E$56:$DT$56,E$5,$E96:$DT96),"") -> 2037950 | F43: =iferror(sumif($E$56:$DT$56,F$5,$E96:$DT96),"") -> 2198408.8 | G43: =iferror(sumif($E$56:$DT$56,G$5,$E96:$DT96),"") -> 2281904.7 | H43: =iferror(sumif($E$56:$DT$56,H$5,$E96:$DT96),"") -> 2368287.3 | I43: =iferror(sumif($E$56:$DT$56,I$5,$E96:$DT96),"") -> 2457654.3 | J43: =iferror(sumif($E$56:$DT$56,J$5,$E96:$DT96),"") -> 2550106.6 | K43: =iferror(sumif($E$56:$DT$56,K$5,$E96:$DT96),"") -> 2653750.1 | ... M43: =iferror(sumif($E$56:$DT$56,M$5,$E96:$DT96),"") -> 2872504.9
B45: Debt Service - Interest | D45: =-sumif($E$56:$DT$56,D$5,$E103:$DT103)-sumif($E$56:$DT$56,D$5,$E118:$DT118) -> -1175373 | E45: =-sumif($E$56:$DT$56,E$5,$E103:$DT103)-sumif($E$56:$DT$56,E$5,$E118:$DT118) -> -1175373 | F45: =-sumif($E$56:$DT$56,F$5,$E103:$DT103)-sumif($E$56:$DT$56,F$5,$E118:$DT118) -> -1175373 | G45: =-sumif($E$56:$DT$56,G$5,$E103:$DT103)-sumif($E$56:$DT$56,G$5,$E118:$DT118) -> -1175373 | H45: =-sumif($E$56:$DT$56,H$5,$E103:$DT103)-sumif($E$56:$DT$56,H$5,$E118:$DT118) -> -1175373 | I45: =-sumif($E$56:$DT$56,I$5,$E103:$DT103)-sumif($E$56:$DT$56,I$5,$E118:$DT118) -> -1175373 | J45: =-sumif($E$56:$DT$56,J$5,$E103:$DT103)-sumif($E$56:$DT$56,J$5,$E118:$DT118) -> -1175373 | K45: =-sumif($E$56:$DT$56,K$5,$E103:$DT103)-sumif($E$56:$DT$56,K$5,$E118:$DT118) -> -1175373 | ... M45: =-sumif($E$56:$DT$56,M$5,$E103:$DT103)-sumif($E$56:$DT$56,M$5,$E118:$DT118) -> -1175373
B46: Debt Service - Principal | D46: =-sumif($E$56:$DT$56,D$5,$E104:$DT104)-sumif($E$56:$DT$56,D$5,$E119:$DT119) -> 0 | E46: =-sumif($E$56:$DT$56,E$5,$E104:$DT104)-sumif($E$56:$DT$56,E$5,$E119:$DT119) -> 0 | F46: =-sumif($E$56:$DT$56,F$5,$E104:$DT104)-sumif($E$56:$DT$56,F$5,$E119:$DT119) -> 0 | G46: =-sumif($E$56:$DT$56,G$5,$E104:$DT104)-sumif($E$56:$DT$56,G$5,$E119:$DT119) -> 0 | H46: =-sumif($E$56:$DT$56,H$5,$E104:$DT104)-sumif($E$56:$DT$56,H$5,$E119:$DT119) -> 0 | I46: =-sumif($E$56:$DT$56,I$5,$E104:$DT104)-sumif($E$56:$DT$56,I$5,$E119:$DT119) -> 0 | J46: =-sumif($E$56:$DT$56,J$5,$E104:$DT104)-sumif($E$56:$DT$56,J$5,$E119:$DT119) -> 0 | K46: =-sumif($E$56:$DT$56,K$5,$E104:$DT104)-sumif($E$56:$DT$56,K$5,$E119:$DT119) -> -294921.01 | ... M46: =-sumif($E$56:$DT$56,M$5,$E104:$DT104)-sumif($E$56:$DT$56,M$5,$E119:$DT119) -> -294921.01
B47: Lender Reserves | D47: =sumif($E$56:$DT$56,D$5,$E108:$DT108)+sumif($E$56:$DT$56,D$5,$E110:$DT110)+sumif($E$56:$DT$56,D$5,$E123:$DT123) -> 0 | E47: =sumif($E$56:$DT$56,E$5,$E108:$DT108)+sumif($E$56:$DT$56,E$5,$E110:$DT110)+sumif($E$56:$DT$56,E$5,$E123:$DT123) -> 0 | F47: =sumif($E$56:$DT$56,F$5,$E108:$DT108)+sumif($E$56:$DT$56,F$5,$E110:$DT110)+sumif($E$56:$DT$56,F$5,$E123:$DT123) -> 0 | G47: =sumif($E$56:$DT$56,G$5,$E108:$DT108)+sumif($E$56:$DT$56,G$5,$E110:$DT110)+sumif($E$56:$DT$56,G$5,$E123:$DT123) -> 0 | H47: =sumif($E$56:$DT$56,H$5,$E108:$DT108)+sumif($E$56:$DT$56,H$5,$E110:$DT110)+sumif($E$56:$DT$56,H$5,$E123:$DT123) -> 0 | I47: =sumif($E$56:$DT$56,I$5,$E108:$DT108)+sumif($E$56:$DT$56,I$5,$E110:$DT110)+sumif($E$56:$DT$56,I$5,$E123:$DT123) -> 0 | J47: =sumif($E$56:$DT$56,J$5,$E108:$DT108)+sumif($E$56:$DT$56,J$5,$E110:$DT110)+sumif($E$56:$DT$56,J$5,$E123:$DT123) -> 0 | K47: =sumif($E$56:$DT$56,K$5,$E108:$DT108)+sumif($E$56:$DT$56,K$5,$E110:$DT110)+sumif($E$56:$DT$56,K$5,$E123:$DT123) -> 0 | ... M47: =sumif($E$56:$DT$56,M$5,$E108:$DT108)+sumif($E$56:$DT$56,M$5,$E110:$DT110)+sumif($E$56:$DT$56,M$5,$E123:$DT123) -> 0
B48: Net Cash Flow | D48: =sum(D43,D45:D47) -> 724055.37 | E48: =sum(E43,E45:E47) -> 862577.04 | F48: =sum(F43,F45:F47) -> 1023035.8 | G48: =sum(G43,G45:G47) -> 1106531.7 | H48: =sum(H43,H45:H47) -> 1192914.3 | I48: =sum(I43,I45:I47) -> 1282281.3 | J48: =sum(J43,J45:J47) -> 1374733.6 | K48: =sum(K43,K45:K47) -> 1183456.1 | ... M48: =sum(M43,M45:M47) -> 1402210.9
B49: Annual Financial Metrics
B50: Cash on Cash | D50: =if(D$5>'Investment Summary'!$F$10,"",D$48/sum('Capital Stack'!$J$8:$J$9)) -> 0.038890694 | E50: =if(E$5>'Investment Summary'!$F$10,"",E$48/sum('Capital Stack'!$J$8:$J$9)) -> 0.046331014 | F50: =if(F$5>'Investment Summary'!$F$10,"",F$48/sum('Capital Stack'!$J$8:$J$9)) -> 0.054949628 | G50: =if(G$5>'Investment Summary'!$F$10,"",G$48/sum('Capital Stack'!$J$8:$J$9)) -> 0.059434385 | H50: =if(H$5>'Investment Summary'!$F$10,"",H$48/sum('Capital Stack'!$J$8:$J$9)) -> 0.064074194 | I50: =if(I$5>'Investment Summary'!$F$10,"",I$48/sum('Capital Stack'!$J$8:$J$9)) -> 0.068874302 | J50: =if(J$5>'Investment Summary'!$F$10,"",J$48/sum('Capital Stack'!$J$8:$J$9)) -> 0.073840132 | K50: =if(K$5>'Investment Summary'!$F$10,"",K$48/sum('Capital Stack'!$J$8:$J$9)) | ... M50: =if(M$5>'Investment Summary'!$F$10,"",M$48/sum('Capital Stack'!$J$8:$J$9))
B51: Yield on Cost | D51: =if(D$5>'Investment Summary'!$F$10,"",D39/'Capital Stack'!$J$20) -> 0.053103103 | E51: =if(E$5>'Investment Summary'!$F$10,"",E39/'Capital Stack'!$J$20) -> 0.056610397 | F51: =if(F$5>'Investment Summary'!$F$10,"",F39/'Capital Stack'!$J$20) -> 0.060671016 | G51: =if(G$5>'Investment Summary'!$F$10,"",G39/'Capital Stack'!$J$20) -> 0.06279268 | H51: =if(H$5>'Investment Summary'!$F$10,"",H39/'Capital Stack'!$J$20) -> 0.06498763 | I51: =if(I$5>'Investment Summary'!$F$10,"",I39/'Capital Stack'!$J$20) -> 0.067258349 | J51: =if(J$5>'Investment Summary'!$F$10,"",J39/'Capital Stack'!$J$20) -> 0.069607399 | K51: =if(K$5>'Investment Summary'!$F$10,"",K39/'Capital Stack'!$J$20) | ... M51: =if(M$5>'Investment Summary'!$F$10,"",M39/'Capital Stack'!$J$20)
B52: Debt Yield | D52: =iferror(if(D$5>'Investment Summary'!$F$10,"",if(or('Investment Summary'!$F$8=0,D$5<='Investment Summary'!$F$8/12),D39/'Capital Stack'!$C$17,D39/'Capital Stack'!$D$17)),"") -> 0.098247294 | E52: =iferror(if(E$5>'Investment Summary'!$F$10,"",if(or('Investment Summary'!$F$8=0,E$5<='Investment Summary'!$F$8/12),E39/'Capital Stack'!$C$17,E39/'Capital Stack'!$D$17)),"") -> 0.10473622 | F52: =iferror(if(F$5>'Investment Summary'!$F$10,"",if(or('Investment Summary'!$F$8=0,F$5<='Investment Summary'!$F$8/12),F39/'Capital Stack'!$C$17,F39/'Capital Stack'!$D$17)),"") -> 0.11224887 | G52: =iferror(if(G$5>'Investment Summary'!$F$10,"",if(or('Investment Summary'!$F$8=0,G$5<='Investment Summary'!$F$8/12),G39/'Capital Stack'!$C$17,G39/'Capital Stack'!$D$17)),"") -> 0.11617421 | H52: =iferror(if(H$5>'Investment Summary'!$F$10,"",if(or('Investment Summary'!$F$8=0,H$5<='Investment Summary'!$F$8/12),H39/'Capital Stack'!$C$17,H39/'Capital Stack'!$D$17)),"") -> 0.12023514 | I52: =iferror(if(I$5>'Investment Summary'!$F$10,"",if(or('Investment Summary'!$F$8=0,I$5<='Investment Summary'!$F$8/12),I39/'Capital Stack'!$C$17,I39/'Capital Stack'!$D$17)),"") -> 0.12443625 | J52: =iferror(if(J$5>'Investment Summary'!$F$10,"",if(or('Investment Summary'!$F$8=0,J$5<='Investment Summary'!$F$8/12),J39/'Capital Stack'!$C$17,J39/'Capital Stack'!$D$17)),"") -> 0.12878228 | K52: =iferror(if(K$5>'Investment Summary'!$F$10,"",if(or('Investment Summary'!$F$8=0,K$5<='Investment Summary'!$F$8/12),K39/'Capital Stack'!$C$17,K39/'Capital Stack'!$D$17)),"") | ... M52: =iferror(if(M$5>'Investment Summary'!$F$10,"",if(or('Investment Summary'!$F$8=0,M$5<='Investment Summary'!$F$8/12),M39/'Capital Stack'!$C$17,M39/'Capital Stack'!$D$17)),"")
B53: DSCR | D53: =iferror(if(D$5>'Investment Summary'!$F$10,"",sum(D43,D47)/-sum(D45:D46)),"") -> 1.6160218 | E53: =iferror(if(E$5>'Investment Summary'!$F$10,"",sum(E43,E47)/-sum(E45:E46)),"") -> 1.7338752 | F53: =iferror(if(F$5>'Investment Summary'!$F$10,"",sum(F43,F47)/-sum(F45:F46)),"") -> 1.8703925 | G53: =iferror(if(G$5>'Investment Summary'!$F$10,"",sum(G43,G47)/-sum(G45:G46)),"") -> 1.9414303 | H53: =iferror(if(H$5>'Investment Summary'!$F$10,"",sum(H43,H47)/-sum(H45:H46)),"") -> 2.014924 | I53: =iferror(if(I$5>'Investment Summary'!$F$10,"",sum(I43,I47)/-sum(I45:I46)),"") -> 2.0909569 | J53: =iferror(if(J$5>'Investment Summary'!$F$10,"",sum(J43,J47)/-sum(J45:J46)),"") -> 2.1696148 | K53: =iferror(if(K$5>'Investment Summary'!$F$10,"",sum(K43,K47)/-sum(K45:K46)),"") | ... M53: =iferror(if(M$5>'Investment Summary'!$F$10,"",sum(M43,M47)/-sum(M45:M46)),"")
B55: Monthly Cash Flows
B56: Analysis Year | D56: =ROUNDUP(D57/12,0) -> 0 | E56: =ROUNDUP(E57/12,0) -> 1 | F56: =ROUNDUP(F57/12,0) -> 1 | G56: =ROUNDUP(G57/12,0) -> 1 | H56: =ROUNDUP(H57/12,0) -> 1 | I56: =ROUNDUP(I57/12,0) -> 1 | J56: =ROUNDUP(J57/12,0) -> 1 | K56: =ROUNDUP(K57/12,0) -> 1 | ... DT56: =ROUNDUP(DT57/12,0) -> 10
B57: Project Month | D57: ='Project Budget'!$I$6 -> 0 | E57: =D57+1 -> 1 | F57: =E57+1 -> 2 | G57: =F57+1 -> 3 | H57: =G57+1 -> 4 | I57: =H57+1 -> 5 | J57: =I57+1 -> 6 | K57: =J57+1 -> 7 | L57: =K57+1 -> 8 | ... DT57: =DS57+1 -> 120
B58: Date | D58: ='Project Budget'!I$7 -> 45838 | E58: ='Project Budget'!J$7 -> 45869 | F58: ='Project Budget'!K$7 -> 45900 | G58: ='Project Budget'!L$7 -> 45930 | H58: ='Project Budget'!M$7 -> 45961 | I58: ='Project Budget'!N$7 -> 45991 | J58: ='Project Budget'!O$7 -> 46022 | K58: ='Project Budget'!P$7 -> 46053 | ... DT58: ='Project Budget'!DY$7 -> 49490
B59: Total Units | E59: =lookup(E$57,Revenue!$D$61:$DS$61,Revenue!$D63:$DS63) -> 184 | F59: =lookup(F$57,Revenue!$D$61:$DS$61,Revenue!$D63:$DS63) -> 184 | G59: =lookup(G$57,Revenue!$D$61:$DS$61,Revenue!$D63:$DS63) -> 184 | H59: =lookup(H$57,Revenue!$D$61:$DS$61,Revenue!$D63:$DS63) -> 184 | I59: =lookup(I$57,Revenue!$D$61:$DS$61,Revenue!$D63:$DS63) -> 184 | J59: =lookup(J$57,Revenue!$D$61:$DS$61,Revenue!$D63:$DS63) -> 184 | K59: =lookup(K$57,Revenue!$D$61:$DS$61,Revenue!$D63:$DS63) -> 184 | L59: =lookup(L$57,Revenue!$D$61:$DS$61,Revenue!$D63:$DS63) -> 184 | ... DT59: =lookup(DT$57,Revenue!$D$61:$DS$61,Revenue!$D63:$DS63) -> 184
B60: Offline Units | E60: =lookup(E$57,Revenue!$D$61:$DS$61,Revenue!$D64:$DS64) -> 0 | F60: =lookup(F$57,Revenue!$D$61:$DS$61,Revenue!$D64:$DS64) -> 0 | G60: =lookup(G$57,Revenue!$D$61:$DS$61,Revenue!$D64:$DS64) -> 0 | H60: =lookup(H$57,Revenue!$D$61:$DS$61,Revenue!$D64:$DS64) -> 3 | I60: =lookup(I$57,Revenue!$D$61:$DS$61,Revenue!$D64:$DS64) -> 3 | J60: =lookup(J$57,Revenue!$D$61:$DS$61,Revenue!$D64:$DS64) -> 3 | K60: =lookup(K$57,Revenue!$D$61:$DS$61,Revenue!$D64:$DS64) -> 3 | L60: =lookup(L$57,Revenue!$D$61:$DS$61,Revenue!$D64:$DS64) -> 3 | ... DT60: =lookup(DT$57,Revenue!$D$61:$DS$61,Revenue!$D64:$DS64) -> 0
B61: Total Renovated Units | E61: =lookup(E$57,Revenue!$D$61:$DS$61,Revenue!$D65:$DS65) -> 0 | F61: =lookup(F$57,Revenue!$D$61:$DS$61,Revenue!$D65:$DS65) -> 0 | G61: =lookup(G$57,Revenue!$D$61:$DS$61,Revenue!$D65:$DS65) -> 0 | H61: =lookup(H$57,Revenue!$D$61:$DS$61,Revenue!$D65:$DS65) -> 0 | I61: =lookup(I$57,Revenue!$D$61:$DS$61,Revenue!$D65:$DS65) -> 3 | J61: =lookup(J$57,Revenue!$D$61:$DS$61,Revenue!$D65:$DS65) -> 6 | K61: =lookup(K$57,Revenue!$D$61:$DS$61,Revenue!$D65:$DS65) -> 9 | L61: =lookup(L$57,Revenue!$D$61:$DS$61,Revenue!$D65:$DS65) -> 12 | ... DT61: =lookup(DT$57,Revenue!$D$61:$DS$61,Revenue!$D65:$DS65) -> 49
B62: Occupancy % (Excluding Offline Units) | E62: =lookup(E$57,Revenue!$D$61:$DS$61,Revenue!$D66:$DS66) -> 0.92 | F62: =lookup(F$57,Revenue!$D$61:$DS$61,Revenue!$D66:$DS66) -> 0.92 | G62: =lookup(G$57,Revenue!$D$61:$DS$61,Revenue!$D66:$DS66) -> 0.92 | H62: =lookup(H$57,Revenue!$D$61:$DS$61,Revenue!$D66:$DS66) -> 0.92 | I62: =lookup(I$57,Revenue!$D$61:$DS$61,Revenue!$D66:$DS66) -> 0.92 | J62: =lookup(J$57,Revenue!$D$61:$DS$61,Revenue!$D66:$DS66) -> 0.92 | K62: =lookup(K$57,Revenue!$D$61:$DS$61,Revenue!$D66:$DS66) -> 0.92 | L62: =lookup(L$57,Revenue!$D$61:$DS$61,Revenue!$D66:$DS66) -> 0.92 | ... DT62: =lookup(DT$57,Revenue!$D$61:$DS$61,Revenue!$D66:$DS66) -> 0.93
B63: Loss to Lease % | E63: =lookup(E$57,Revenue!$D$61:$DS$61,Revenue!$D67:$DS67) -> 0.066416429 | F63: =lookup(F$57,Revenue!$D$61:$DS$61,Revenue!$D67:$DS67) -> 0.066416429 | G63: =lookup(G$57,Revenue!$D$61:$DS$61,Revenue!$D67:$DS67) -> 0.066416429 | H63: =lookup(H$57,Revenue!$D$61:$DS$61,Revenue!$D67:$DS67) -> 0.066416429 | I63: =lookup(I$57,Revenue!$D$61:$DS$61,Revenue!$D67:$DS67) -> 0.064860693 | J63: =lookup(J$57,Revenue!$D$61:$DS$61,Revenue!$D67:$DS67) -> 0.063304958 | K63: =lookup(K$57,Revenue!$D$61:$DS$61,Revenue!$D67:$DS67) -> 0.061749222 | L63: =lookup(L$57,Revenue!$D$61:$DS$61,Revenue!$D67:$DS67) -> 0.060193487 | ... DT63: =lookup(DT$57,Revenue!$D$61:$DS$61,Revenue!$D67:$DS67) -> 0.041006083
E64: =lookup(E$57,Revenue!$D$61:$DS$61,Revenue!$D68:$DS68) | F64: =lookup(F$57,Revenue!$D$61:$DS$61,Revenue!$D68:$DS68) | G64: =lookup(G$57,Revenue!$D$61:$DS$61,Revenue!$D68:$DS68) | H64: =lookup(H$57,Revenue!$D$61:$DS$61,Revenue!$D68:$DS68) | I64: =lookup(I$57,Revenue!$D$61:$DS$61,Revenue!$D68:$DS68) | J64: =lookup(J$57,Revenue!$D$61:$DS$61,Revenue!$D68:$DS68) | K64: =lookup(K$57,Revenue!$D$61:$DS$61,Revenue!$D68:$DS68) | L64: =lookup(L$57,Revenue!$D$61:$DS$61,Revenue!$D68:$DS68) | ... DT64: =lookup(DT$57,Revenue!$D$61:$DS$61,Revenue!$D68:$DS68)
B65: Rental Income | E65: =lookup(E$57,Revenue!$D$61:$DS$61,Revenue!$D69:$DS69) | F65: =lookup(F$57,Revenue!$D$61:$DS$61,Revenue!$D69:$DS69) | G65: =lookup(G$57,Revenue!$D$61:$DS$61,Revenue!$D69:$DS69) | H65: =lookup(H$57,Revenue!$D$61:$DS$61,Revenue!$D69:$DS69) | I65: =lookup(I$57,Revenue!$D$61:$DS$61,Revenue!$D69:$DS69) | J65: =lookup(J$57,Revenue!$D$61:$DS$61,Revenue!$D69:$DS69) | K65: =lookup(K$57,Revenue!$D$61:$DS$61,Revenue!$D69:$DS69) | L65: =lookup(L$57,Revenue!$D$61:$DS$61,Revenue!$D69:$DS69) | ... DT65: =lookup(DT$57,Revenue!$D$61:$DS$61,Revenue!$D69:$DS69)
B66: Potential Rental Income | E66: =lookup(E$57,Revenue!$D$61:$DS$61,Revenue!$D70:$DS70) -> 283963.75 | F66: =lookup(F$57,Revenue!$D$61:$DS$61,Revenue!$D70:$DS70) -> 283963.75 | G66: =lookup(G$57,Revenue!$D$61:$DS$61,Revenue!$D70:$DS70) -> 283963.75 | H66: =lookup(H$57,Revenue!$D$61:$DS$61,Revenue!$D70:$DS70) -> 283963.75 | I66: =lookup(I$57,Revenue!$D$61:$DS$61,Revenue!$D70:$DS70) -> 283963.75 | J66: =lookup(J$57,Revenue!$D$61:$DS$61,Revenue!$D70:$DS70) -> 283963.75 | K66: =lookup(K$57,Revenue!$D$61:$DS$61,Revenue!$D70:$DS70) -> 283963.75 | L66: =lookup(L$57,Revenue!$D$61:$DS$61,Revenue!$D70:$DS70) -> 283963.75 | ... DT66: =lookup(DT$57,Revenue!$D$61:$DS$61,Revenue!$D70:$DS70) -> 387013.45
B67: Loss to Lease | E67: =lookup(E$57,Revenue!$D$61:$DS$61,Revenue!$D71:$DS71) -> -18859.858 | F67: =lookup(F$57,Revenue!$D$61:$DS$61,Revenue!$D71:$DS71) -> -18859.858 | G67: =lookup(G$57,Revenue!$D$61:$DS$61,Revenue!$D71:$DS71) -> -18859.858 | H67: =lookup(H$57,Revenue!$D$61:$DS$61,Revenue!$D71:$DS71) -> -18859.858 | I67: =lookup(I$57,Revenue!$D$61:$DS$61,Revenue!$D71:$DS71) -> -18418.086 | J67: =lookup(J$57,Revenue!$D$61:$DS$61,Revenue!$D71:$DS71) -> -17976.314 | K67: =lookup(K$57,Revenue!$D$61:$DS$61,Revenue!$D71:$DS71) -> -17534.541 | L67: =lookup(L$57,Revenue!$D$61:$DS$61,Revenue!$D71:$DS71) -> -17092.769 | ... DT67: =lookup(DT$57,Revenue!$D$61:$DS$61,Revenue!$D71:$DS71) -> -15869.906
B68: Vacancy Loss | E68: =lookup(E$57,Revenue!$D$61:$DS$61,Revenue!$D72:$DS72) -> -21208.312 | F68: =lookup(F$57,Revenue!$D$61:$DS$61,Revenue!$D72:$DS72) -> -21208.312 | G68: =lookup(G$57,Revenue!$D$61:$DS$61,Revenue!$D72:$DS72) -> -21208.312 | H68: =lookup(H$57,Revenue!$D$61:$DS$61,Revenue!$D72:$DS72) -> -21208.312 | I68: =lookup(I$57,Revenue!$D$61:$DS$61,Revenue!$D72:$DS72) -> -21243.653 | J68: =lookup(J$57,Revenue!$D$61:$DS$61,Revenue!$D72:$DS72) -> -21278.995 | K68: =lookup(K$57,Revenue!$D$61:$DS$61,Revenue!$D72:$DS72) -> -21314.337 | L68: =lookup(L$57,Revenue!$D$61:$DS$61,Revenue!$D72:$DS72) -> -21349.679 | ... DT68: =lookup(DT$57,Revenue!$D$61:$DS$61,Revenue!$D72:$DS72) -> -25980.048
B69: Offline Renovation Loss | E69: =lookup(E$57,Revenue!$D$61:$DS$61,Revenue!$D73:$DS73) -> 0 | F69: =lookup(F$57,Revenue!$D$61:$DS$61,Revenue!$D73:$DS73) -> 0 | G69: =lookup(G$57,Revenue!$D$61:$DS$61,Revenue!$D73:$DS73) -> 0 | H69: =lookup(H$57,Revenue!$D$61:$DS$61,Revenue!$D73:$DS73) -> -4629.8438 | I69: =lookup(I$57,Revenue!$D$61:$DS$61,Revenue!$D73:$DS73) -> -4629.8438 | J69: =lookup(J$57,Revenue!$D$61:$DS$61,Revenue!$D73:$DS73) -> -4629.8438 | K69: =lookup(K$57,Revenue!$D$61:$DS$61,Revenue!$D73:$DS73) -> -4629.8438 | L69: =lookup(L$57,Revenue!$D$61:$DS$61,Revenue!$D73:$DS73) -> -4629.8438 | ... DT69: =lookup(DT$57,Revenue!$D$61:$DS$61,Revenue!$D73:$DS73) -> 0
B70: Bad Debt Expense | E70: =lookup(E$57,Revenue!$D$61:$DS$61,Revenue!$D74:$DS74) -> -3658.4338 | F70: =lookup(F$57,Revenue!$D$61:$DS$61,Revenue!$D74:$DS74) -> -3658.4338 | G70: =lookup(G$57,Revenue!$D$61:$DS$61,Revenue!$D74:$DS74) -> -3658.4338 | H70: =lookup(H$57,Revenue!$D$61:$DS$61,Revenue!$D74:$DS74) -> -3588.9861 | I70: =lookup(I$57,Revenue!$D$61:$DS$61,Revenue!$D74:$DS74) -> -3595.0826 | J70: =lookup(J$57,Revenue!$D$61:$DS$61,Revenue!$D74:$DS74) -> -3601.179 | K70: =lookup(K$57,Revenue!$D$61:$DS$61,Revenue!$D74:$DS74) -> -3607.2755 | L70: =lookup(L$57,Revenue!$D$61:$DS$61,Revenue!$D74:$DS74) -> -3613.3719 | ... DT70: =lookup(DT$57,Revenue!$D$61:$DS$61,Revenue!$D74:$DS74) -> -4314.5437
B71: Concessions | E71: =lookup(E$57,Revenue!$D$61:$DS$61,Revenue!$D75:$DS75) -> -3048.6948 | F71: =lookup(F$57,Revenue!$D$61:$DS$61,Revenue!$D75:$DS75) -> -3048.6948 | G71: =lookup(G$57,Revenue!$D$61:$DS$61,Revenue!$D75:$DS75) -> -3048.6948 | H71: =lookup(H$57,Revenue!$D$61:$DS$61,Revenue!$D75:$DS75) -> -2990.8218 | I71: =lookup(I$57,Revenue!$D$61:$DS$61,Revenue!$D75:$DS75) -> -2995.9021 | J71: =lookup(J$57,Revenue!$D$61:$DS$61,Revenue!$D75:$DS75) -> -3000.9825 | K71: =lookup(K$57,Revenue!$D$61:$DS$61,Revenue!$D75:$DS75) -> -3006.0629 | L71: =lookup(L$57,Revenue!$D$61:$DS$61,Revenue!$D75:$DS75) -> -3011.1433 | ... DT71: =lookup(DT$57,Revenue!$D$61:$DS$61,Revenue!$D75:$DS75) -> -4314.5437
B72: Total Rental Income | E72: =lookup(E$57,Revenue!$D$61:$DS$61,Revenue!$D76:$DS76) -> 237188.46 | F72: =lookup(F$57,Revenue!$D$61:$DS$61,Revenue!$D76:$DS76) -> 237188.46 | G72: =lookup(G$57,Revenue!$D$61:$DS$61,Revenue!$D76:$DS76) -> 237188.46 | H72: =lookup(H$57,Revenue!$D$61:$DS$61,Revenue!$D76:$DS76) -> 232685.93 | I72: =lookup(I$57,Revenue!$D$61:$DS$61,Revenue!$D76:$DS76) -> 233081.19 | J72: =lookup(J$57,Revenue!$D$61:$DS$61,Revenue!$D76:$DS76) -> 233476.44 | K72: =lookup(K$57,Revenue!$D$61:$DS$61,Revenue!$D76:$DS76) -> 233871.69 | L72: =lookup(L$57,Revenue!$D$61:$DS$61,Revenue!$D76:$DS76) -> 234266.95 | ... DT72: =lookup(DT$57,Revenue!$D$61:$DS$61,Revenue!$D76:$DS76) -> 336534.41
B73: Total RUBS Income | E73: =lookup(E$57,Revenue!$D$61:$DS$61,Revenue!$D77:$DS77) -> 15573.76 | F73: =lookup(F$57,Revenue!$D$61:$DS$61,Revenue!$D77:$DS77) -> 15573.76 | G73: =lookup(G$57,Revenue!$D$61:$DS$61,Revenue!$D77:$DS77) -> 15573.76 | H73: =lookup(H$57,Revenue!$D$61:$DS$61,Revenue!$D77:$DS77) -> 15297.76 | I73: =lookup(I$57,Revenue!$D$61:$DS$61,Revenue!$D77:$DS77) -> 15297.76 | J73: =lookup(J$57,Revenue!$D$61:$DS$61,Revenue!$D77:$DS77) -> 15297.76 | K73: =lookup(K$57,Revenue!$D$61:$DS$61,Revenue!$D77:$DS77) -> 15297.76 | L73: =lookup(L$57,Revenue!$D$61:$DS$61,Revenue!$D77:$DS77) -> 15297.76 | ... DT73: =lookup(DT$57,Revenue!$D$61:$DS$61,Revenue!$D77:$DS77) -> 18814.39
B74: Total Other Income | E74: =lookup(E$57,Revenue!$D$61:$DS$61,Revenue!$D78:$DS78) -> 33750 | F74: =lookup(F$57,Revenue!$D$61:$DS$61,Revenue!$D78:$DS78) -> 33750 | G74: =lookup(G$57,Revenue!$D$61:$DS$61,Revenue!$D78:$DS78) -> 33750 | H74: =lookup(H$57,Revenue!$D$61:$DS$61,Revenue!$D78:$DS78) -> 33750 | I74: =lookup(I$57,Revenue!$D$61:$DS$61,Revenue!$D78:$DS78) -> 33750 | J74: =lookup(J$57,Revenue!$D$61:$DS$61,Revenue!$D78:$DS78) -> 33750 | K74: =lookup(K$57,Revenue!$D$61:$DS$61,Revenue!$D78:$DS78) -> 33750 | L74: =lookup(L$57,Revenue!$D$61:$DS$61,Revenue!$D78:$DS78) -> 33750 | ... DT74: =lookup(DT$57,Revenue!$D$61:$DS$61,Revenue!$D78:$DS78) -> 40334.374
B75: Total Revenue | E75: =lookup(E$57,Revenue!$D$61:$DS$61,Revenue!$D79:$DS79) -> 286512.22 | F75: =lookup(F$57,Revenue!$D$61:$DS$61,Revenue!$D79:$DS79) -> 286512.22 | G75: =lookup(G$57,Revenue!$D$61:$DS$61,Revenue!$D79:$DS79) -> 286512.22 | H75: =lookup(H$57,Revenue!$D$61:$DS$61,Revenue!$D79:$DS79) -> 281733.69 | I75: =lookup(I$57,Revenue!$D$61:$DS$61,Revenue!$D79:$DS79) -> 282128.95 | J75: =lookup(J$57,Revenue!$D$61:$DS$61,Revenue!$D79:$DS79) -> 282524.2 | K75: =lookup(K$57,Revenue!$D$61:$DS$61,Revenue!$D79:$DS79) -> 282919.45 | L75: =lookup(L$57,Revenue!$D$61:$DS$61,Revenue!$D79:$DS79) -> 283314.71 | ... DT75: =lookup(DT$57,Revenue!$D$61:$DS$61,Revenue!$D79:$DS79) -> 395683.17
B77: Operating Expenses
B78: Total General & Admin | E78: =lookup(E$56,Expenses!$D$31:$M$31,Expenses!$D32:$M32)/12 -> 10656.667 | F78: =lookup(F$56,Expenses!$D$31:$M$31,Expenses!$D32:$M32)/12 -> 10656.667 | G78: =lookup(G$56,Expenses!$D$31:$M$31,Expenses!$D32:$M32)/12 -> 10656.667 | H78: =lookup(H$56,Expenses!$D$31:$M$31,Expenses!$D32:$M32)/12 -> 10656.667 | I78: =lookup(I$56,Expenses!$D$31:$M$31,Expenses!$D32:$M32)/12 -> 10656.667 | J78: =lookup(J$56,Expenses!$D$31:$M$31,Expenses!$D32:$M32)/12 -> 10656.667 | K78: =lookup(K$56,Expenses!$D$31:$M$31,Expenses!$D32:$M32)/12 -> 10656.667 | L78: =lookup(L$56,Expenses!$D$31:$M$31,Expenses!$D32:$M32)/12 -> 10656.667 | ... DT78: =lookup(DT$56,Expenses!$D$31:$M$31,Expenses!$D32:$M32)/12 -> 13308.716
B79: Total Payroll | E79: =lookup(E$56,Expenses!$D$31:$M$31,Expenses!$D33:$M33)/12 -> 27040 | F79: =lookup(F$56,Expenses!$D$31:$M$31,Expenses!$D33:$M33)/12 -> 27040 | G79: =lookup(G$56,Expenses!$D$31:$M$31,Expenses!$D33:$M33)/12 -> 27040 | H79: =lookup(H$56,Expenses!$D$31:$M$31,Expenses!$D33:$M33)/12 -> 27040 | I79: =lookup(I$56,Expenses!$D$31:$M$31,Expenses!$D33:$M33)/12 -> 27040 | J79: =lookup(J$56,Expenses!$D$31:$M$31,Expenses!$D33:$M33)/12 -> 27040 | K79: =lookup(K$56,Expenses!$D$31:$M$31,Expenses!$D33:$M33)/12 -> 27040 | L79: =lookup(L$56,Expenses!$D$31:$M$31,Expenses!$D33:$M33)/12 -> 27040 | ... DT79: =lookup(DT$56,Expenses!$D$31:$M$31,Expenses!$D33:$M33)/12 -> 33769.255
B80: Total Leasing & Marketing | E80: =lookup(E$56,Expenses!$D$31:$M$31,Expenses!$D34:$M34)/12 -> 7283.3333 | F80: =lookup(F$56,Expenses!$D$31:$M$31,Expenses!$D34:$M34)/12 -> 7283.3333 | G80: =lookup(G$56,Expenses!$D$31:$M$31,Expenses!$D34:$M34)/12 -> 7283.3333 | H80: =lookup(H$56,Expenses!$D$31:$M$31,Expenses!$D34:$M34)/12 -> 7283.3333 | I80: =lookup(I$56,Expenses!$D$31:$M$31,Expenses!$D34:$M34)/12 -> 7283.3333 | J80: =lookup(J$56,Expenses!$D$31:$M$31,Expenses!$D34:$M34)/12 -> 7283.3333 | K80: =lookup(K$56,Expenses!$D$31:$M$31,Expenses!$D34:$M34)/12 -> 7283.3333 | L80: =lookup(L$56,Expenses!$D$31:$M$31,Expenses!$D34:$M34)/12 -> 7283.3333 | ... DT80: =lookup(DT$56,Expenses!$D$31:$M$31,Expenses!$D34:$M34)/12 -> 9095.8853
B81: Total Utilities | E81: =lookup(E$56,Expenses!$D$31:$M$31,Expenses!$D35:$M35)/12 -> 22080 | F81: =lookup(F$56,Expenses!$D$31:$M$31,Expenses!$D35:$M35)/12 -> 22080 | G81: =lookup(G$56,Expenses!$D$31:$M$31,Expenses!$D35:$M35)/12 -> 22080 | H81: =lookup(H$56,Expenses!$D$31:$M$31,Expenses!$D35:$M35)/12 -> 22080 | I81: =lookup(I$56,Expenses!$D$31:$M$31,Expenses!$D35:$M35)/12 -> 22080 | J81: =lookup(J$56,Expenses!$D$31:$M$31,Expenses!$D35:$M35)/12 -> 22080 | K81: =lookup(K$56,Expenses!$D$31:$M$31,Expenses!$D35:$M35)/12 -> 22080 | L81: =lookup(L$56,Expenses!$D$31:$M$31,Expenses!$D35:$M35)/12 -> 22080 | ... DT81: =lookup(DT$56,Expenses!$D$31:$M$31,Expenses!$D35:$M35)/12 -> 27574.894
B82: Total Repairs & Maintenance | E82: =lookup(E$56,Expenses!$D$31:$M$31,Expenses!$D36:$M36)/12 -> 4676.6667 | F82: =lookup(F$56,Expenses!$D$31:$M$31,Expenses!$D36:$M36)/12 -> 4676.6667 | G82: =lookup(G$56,Expenses!$D$31:$M$31,Expenses!$D36:$M36)/12 -> 4676.6667 | H82: =lookup(H$56,Expenses!$D$31:$M$31,Expenses!$D36:$M36)/12 -> 4676.6667 | I82: =lookup(I$56,Expenses!$D$31:$M$31,Expenses!$D36:$M36)/12 -> 4676.6667 | J82: =lookup(J$56,Expenses!$D$31:$M$31,Expenses!$D36:$M36)/12 -> 4676.6667 | K82: =lookup(K$56,Expenses!$D$31:$M$31,Expenses!$D36:$M36)/12 -> 4676.6667 | L82: =lookup(L$56,Expenses!$D$31:$M$31,Expenses!$D36:$M36)/12 -> 4676.6667 | ... DT82: =lookup(DT$56,Expenses!$D$31:$M$31,Expenses!$D36:$M36)/12 -> 5840.5158
B83: Total Supply Expense | E83: =lookup(E$56,Expenses!$D$31:$M$31,Expenses!$D37:$M37)/12 -> 1763.3333 | F83: =lookup(F$56,Expenses!$D$31:$M$31,Expenses!$D37:$M37)/12 -> 1763.3333 | G83: =lookup(G$56,Expenses!$D$31:$M$31,Expenses!$D37:$M37)/12 -> 1763.3333 | H83: =lookup(H$56,Expenses!$D$31:$M$31,Expenses!$D37:$M37)/12 -> 1763.3333 | I83: =lookup(I$56,Expenses!$D$31:$M$31,Expenses!$D37:$M37)/12 -> 1763.3333 | J83: =lookup(J$56,Expenses!$D$31:$M$31,Expenses!$D37:$M37)/12 -> 1763.3333 | K83: =lookup(K$56,Expenses!$D$31:$M$31,Expenses!$D37:$M37)/12 -> 1763.3333 | L83: =lookup(L$56,Expenses!$D$31:$M$31,Expenses!$D37:$M37)/12 -> 1763.3333 | ... DT83: =lookup(DT$56,Expenses!$D$31:$M$31,Expenses!$D37:$M37)/12 -> 2202.1617
B84: Total Turnover Expense | E84: =lookup(E$56,Expenses!$D$31:$M$31,Expenses!$D38:$M38)/12 -> 1916.6667 | F84: =lookup(F$56,Expenses!$D$31:$M$31,Expenses!$D38:$M38)/12 -> 1916.6667 | G84: =lookup(G$56,Expenses!$D$31:$M$31,Expenses!$D38:$M38)/12 -> 1916.6667 | H84: =lookup(H$56,Expenses!$D$31:$M$31,Expenses!$D38:$M38)/12 -> 1916.6667 | I84: =lookup(I$56,Expenses!$D$31:$M$31,Expenses!$D38:$M38)/12 -> 1916.6667 | J84: =lookup(J$56,Expenses!$D$31:$M$31,Expenses!$D38:$M38)/12 -> 1916.6667 | K84: =lookup(K$56,Expenses!$D$31:$M$31,Expenses!$D38:$M38)/12 -> 1916.6667 | L84: =lookup(L$56,Expenses!$D$31:$M$31,Expenses!$D38:$M38)/12 -> 1916.6667 | ... DT84: =lookup(DT$56,Expenses!$D$31:$M$31,Expenses!$D38:$M38)/12 -> 2393.654
B85: Total Contract Services | E85: =lookup(E$56,Expenses!$D$31:$M$31,Expenses!$D39:$M39)/12 -> 3910 | F85: =lookup(F$56,Expenses!$D$31:$M$31,Expenses!$D39:$M39)/12 -> 3910 | G85: =lookup(G$56,Expenses!$D$31:$M$31,Expenses!$D39:$M39)/12 -> 3910 | H85: =lookup(H$56,Expenses!$D$31:$M$31,Expenses!$D39:$M39)/12 -> 3910 | I85: =lookup(I$56,Expenses!$D$31:$M$31,Expenses!$D39:$M39)/12 -> 3910 | J85: =lookup(J$56,Expenses!$D$31:$M$31,Expenses!$D39:$M39)/12 -> 3910 | K85: =lookup(K$56,Expenses!$D$31:$M$31,Expenses!$D39:$M39)/12 -> 3910 | L85: =lookup(L$56,Expenses!$D$31:$M$31,Expenses!$D39:$M39)/12 -> 3910 | ... DT85: =lookup(DT$56,Expenses!$D$31:$M$31,Expenses!$D39:$M39)/12 -> 4883.0542
B86: Total Insurance Expense | E86: =lookup(E$56,Expenses!$D$31:$M$31,Expenses!$D40:$M40)/12 -> 4523.3333 | F86: =lookup(F$56,Expenses!$D$31:$M$31,Expenses!$D40:$M40)/12 -> 4523.3333 | G86: =lookup(G$56,Expenses!$D$31:$M$31,Expenses!$D40:$M40)/12 -> 4523.3333 | H86: =lookup(H$56,Expenses!$D$31:$M$31,Expenses!$D40:$M40)/12 -> 4523.3333 | I86: =lookup(I$56,Expenses!$D$31:$M$31,Expenses!$D40:$M40)/12 -> 4523.3333 | J86: =lookup(J$56,Expenses!$D$31:$M$31,Expenses!$D40:$M40)/12 -> 4523.3333 | K86: =lookup(K$56,Expenses!$D$31:$M$31,Expenses!$D40:$M40)/12 -> 4523.3333 | L86: =lookup(L$56,Expenses!$D$31:$M$31,Expenses!$D40:$M40)/12 -> 4523.3333 | ... DT86: =lookup(DT$56,Expenses!$D$31:$M$31,Expenses!$D40:$M40)/12 -> 4947.103
B87: Total Property Taxes | E87: =lookup(E$56,Expenses!$D$31:$M$31,Expenses!$D41:$M41)/12 -> 12439.35 | F87: =lookup(F$56,Expenses!$D$31:$M$31,Expenses!$D41:$M41)/12 -> 12439.35 | G87: =lookup(G$56,Expenses!$D$31:$M$31,Expenses!$D41:$M41)/12 -> 12439.35 | H87: =lookup(H$56,Expenses!$D$31:$M$31,Expenses!$D41:$M41)/12 -> 12439.35 | I87: =lookup(I$56,Expenses!$D$31:$M$31,Expenses!$D41:$M41)/12 -> 12439.35 | J87: =lookup(J$56,Expenses!$D$31:$M$31,Expenses!$D41:$M41)/12 -> 12439.35 | K87: =lookup(K$56,Expenses!$D$31:$M$31,Expenses!$D41:$M41)/12 -> 12439.35 | L87: =lookup(L$56,Expenses!$D$31:$M$31,Expenses!$D41:$M41)/12 -> 12439.35 | ... DT87: =lookup(DT$56,Expenses!$D$31:$M$31,Expenses!$D41:$M41)/12 -> 17175.034
B88: Total Management Fees | E88: =lookup(E$56,Expenses!$D$31:$M$31,Expenses!$D42:$M42)/12 -> 8523.4225 | F88: =lookup(F$56,Expenses!$D$31:$M$31,Expenses!$D42:$M42)/12 -> 8523.4225 | G88: =lookup(G$56,Expenses!$D$31:$M$31,Expenses!$D42:$M42)/12 -> 8523.4225 | H88: =lookup(H$56,Expenses!$D$31:$M$31,Expenses!$D42:$M42)/12 -> 8523.4225 | I88: =lookup(I$56,Expenses!$D$31:$M$31,Expenses!$D42:$M42)/12 -> 8523.4225 | J88: =lookup(J$56,Expenses!$D$31:$M$31,Expenses!$D42:$M42)/12 -> 8523.4225 | K88: =lookup(K$56,Expenses!$D$31:$M$31,Expenses!$D42:$M42)/12 -> 8523.4225 | L88: =lookup(L$56,Expenses!$D$31:$M$31,Expenses!$D42:$M42)/12 -> 8523.4225 | ... DT88: =lookup(DT$56,Expenses!$D$31:$M$31,Expenses!$D42:$M42)/12 -> 11870.495
B89: Total Operating Expenses | E89: =lookup(E$56,Expenses!$D$31:$M$31,Expenses!$D43:$M43)/12 -> 104812.77 | F89: =lookup(F$56,Expenses!$D$31:$M$31,Expenses!$D43:$M43)/12 -> 104812.77 | G89: =lookup(G$56,Expenses!$D$31:$M$31,Expenses!$D43:$M43)/12 -> 104812.77 | H89: =lookup(H$56,Expenses!$D$31:$M$31,Expenses!$D43:$M43)/12 -> 104812.77 | I89: =lookup(I$56,Expenses!$D$31:$M$31,Expenses!$D43:$M43)/12 -> 104812.77 | J89: =lookup(J$56,Expenses!$D$31:$M$31,Expenses!$D43:$M43)/12 -> 104812.77 | K89: =lookup(K$56,Expenses!$D$31:$M$31,Expenses!$D43:$M43)/12 -> 104812.77 | L89: =lookup(L$56,Expenses!$D$31:$M$31,Expenses!$D43:$M43)/12 -> 104812.77 | ... DT89: =lookup(DT$56,Expenses!$D$31:$M$31,Expenses!$D43:$M43)/12 -> 133060.77
B90: Expense Ratio | E90: =iferror(E89/E75,"") -> 0.36582305 | F90: =iferror(F89/F75,"") -> 0.36582305 | G90: =iferror(G89/G75,"") -> 0.36582305 | H90: =iferror(H89/H75,"") -> 0.37202782 | I90: =iferror(I89/I75,"") -> 0.37150662 | J90: =iferror(J89/J75,"") -> 0.37098688 | K90: =iferror(K89/K75,"") -> 0.37046859 | L90: =iferror(L89/L75,"") -> 0.36995175 | ... DX90: =iferror(DX89/DX75,"")
B92: Net Operating Income | E92: =iferror(E75-E89,"") -> 181699.44 | F92: =iferror(F75-F89,"") -> 181699.44 | G92: =iferror(G75-G89,"") -> 181699.44 | H92: =iferror(H75-H89,"") -> 176920.92 | I92: =iferror(I75-I89,"") -> 177316.17 | J92: =iferror(J75-J89,"") -> 177711.43 | K92: =iferror(K75-K89,"") -> 178106.68 | L92: =iferror(L75-L89,"") -> 178501.94 | ... DT92: =iferror(DT75-DT89,"") -> 262622.4
B94: Asset Management Fees | E94: =iferror(-E75*'Investment Summary'!$F$14,"") -> -5730.2443 | F94: =iferror(-F75*'Investment Summary'!$F$14,"") -> -5730.2443 | G94: =iferror(-G75*'Investment Summary'!$F$14,"") -> -5730.2443 | H94: =iferror(-H75*'Investment Summary'!$F$14,"") -> -5634.6739 | I94: =iferror(-I75*'Investment Summary'!$F$14,"") -> -5642.5789 | J94: =iferror(-J75*'Investment Summary'!$F$14,"") -> -5650.484 | K94: =iferror(-K75*'Investment Summary'!$F$14,"") -> -5658.3891 | L94: =iferror(-L75*'Investment Summary'!$F$14,"") -> -5666.2942 | ... DT94: =iferror(-DT75*'Investment Summary'!$F$14,"") -> -7913.6635
B95: =B42 -> 1000 | E95: =iferror(-$B$95*'Unit Mix & Comps'!$D$34/12,"") -> -15333.333 | F95: =iferror(-$B$95*'Unit Mix & Comps'!$D$34/12,"") -> -15333.333 | G95: =iferror(-$B$95*'Unit Mix & Comps'!$D$34/12,"") -> -15333.333 | H95: =iferror(-$B$95*'Unit Mix & Comps'!$D$34/12,"") -> -15333.333 | I95: =iferror(-$B$95*'Unit Mix & Comps'!$D$34/12,"") -> -15333.333 | J95: =iferror(-$B$95*'Unit Mix & Comps'!$D$34/12,"") -> -15333.333 | K95: =iferror(-$B$95*'Unit Mix & Comps'!$D$34/12,"") -> -15333.333 | L95: =iferror(-$B$95*'Unit Mix & Comps'!$D$34/12,"") -> -15333.333 | ... DT95: =iferror(-$B$95*'Unit Mix & Comps'!$D$34/12,"") -> -15333.333
B96: Operating Cash Flow | E96: =iferror(sum(E92,E94:E95),"") -> 160635.87 | F96: =iferror(sum(F92,F94:F95),"") -> 160635.87 | G96: =iferror(sum(G92,G94:G95),"") -> 160635.87 | H96: =iferror(sum(H92,H94:H95),"") -> 155952.91 | I96: =iferror(sum(I92,I94:I95),"") -> 156340.26 | J96: =iferror(sum(J92,J94:J95),"") -> 156727.61 | K96: =iferror(sum(K92,K94:K95),"") -> 157114.96 | L96: =iferror(sum(L92,L94:L95),"") -> 157502.31 | ... DT96: =iferror(sum(DT92,DT94:DT95),"") -> 239375.41
B98: Acquisition Loan
B99: Analysis Year | D99: =ROUNDUP(D100/12,0) -> 0 | E99: =ROUNDUP(E100/12,0) -> 1 | F99: =ROUNDUP(F100/12,0) -> 1 | G99: =ROUNDUP(G100/12,0) -> 1 | H99: =ROUNDUP(H100/12,0) -> 1 | I99: =ROUNDUP(I100/12,0) -> 1 | J99: =ROUNDUP(J100/12,0) -> 1 | K99: =ROUNDUP(K100/12,0) -> 1 | ... DT99: =ROUNDUP(DT100/12,0) -> 10
B100: Project Month | D100: ='Project Budget'!$I$6 -> 0 | E100: =D100+1 -> 1 | F100: =E100+1 -> 2 | G100: =F100+1 -> 3 | H100: =G100+1 -> 4 | I100: =H100+1 -> 5 | J100: =I100+1 -> 6 | K100: =J100+1 -> 7 | L100: =K100+1 -> 8 | ... DT100: =DS100+1 -> 120
B101: Date | D101: ='Project Budget'!I$7 -> 45838 | E101: ='Project Budget'!J$7 -> 45869 | F101: ='Project Budget'!K$7 -> 45900 | G101: ='Project Budget'!L$7 -> 45930 | H101: ='Project Budget'!M$7 -> 45961 | I101: ='Project Budget'!N$7 -> 45991 | J101: ='Project Budget'!O$7 -> 46022 | K101: ='Project Budget'!P$7 -> 46053 | ... DT101: ='Project Budget'!DY$7 -> 49490
B102: Annual Rate | E102: ='Capital Stack'!$C$11 -> 0.05367 | F102: ='Capital Stack'!$C$11 -> 0.05367 | G102: ='Capital Stack'!$C$11 -> 0.05367 | H102: ='Capital Stack'!$C$11 -> 0.05367 | I102: ='Capital Stack'!$C$11 -> 0.05367 | J102: ='Capital Stack'!$C$11 -> 0.05367 | K102: ='Capital Stack'!$C$11 -> 0.05367 | L102: ='Capital Stack'!$C$11 -> 0.05367 | ... DT102: ='Capital Stack'!$C$11 -> 0.05367
B103: Interest Payments | E103: =if('Investment Summary'!$F$8=0,$D$105*E$102/12,if(E$100>'Investment Summary'!$F$8,0,$D$105*E$102/12)) -> 97947.75 | F103: =if('Investment Summary'!$F$8=0,$D$105*F$102/12,if(F$100>'Investment Summary'!$F$8,0,$D$105*F$102/12)) -> 97947.75 | G103: =if('Investment Summary'!$F$8=0,$D$105*G$102/12,if(G$100>'Investment Summary'!$F$8,0,$D$105*G$102/12)) -> 97947.75 | H103: =if('Investment Summary'!$F$8=0,$D$105*H$102/12,if(H$100>'Investment Summary'!$F$8,0,$D$105*H$102/12)) -> 97947.75 | I103: =if('Investment Summary'!$F$8=0,$D$105*I$102/12,if(I$100>'Investment Summary'!$F$8,0,$D$105*I$102/12)) -> 97947.75 | J103: =if('Investment Summary'!$F$8=0,$D$105*J$102/12,if(J$100>'Investment Summary'!$F$8,0,$D$105*J$102/12)) -> 97947.75 | K103: =if('Investment Summary'!$F$8=0,$D$105*K$102/12,if(K$100>'Investment Summary'!$F$8,0,$D$105*K$102/12)) -> 97947.75 | L103: =if('Investment Summary'!$F$8=0,$D$105*L$102/12,if(L$100>'Investment Summary'!$F$8,0,$D$105*L$102/12)) -> 97947.75 | ... DT103: =if('Investment Summary'!$F$8=0,$D$105*DT$102/12,if(DT$100>'Investment Summary'!$F$8,0,$D$105*DT$102/12)) -> 97947.75
B104: Principal Payments | E104: =if('Investment Summary'!$F$8=0,if(E$100>'Capital Stack'!$C$12,pmt(E$102/12,'Capital Stack'!$C$13*12,-$D$105)-E$103,0),if(E$100>'Investment Summary'!$F$8,0,if(E$100>'Capital Stack'!$C$12,pmt(E$102/12,'Capital Stack'!$C$13*12,-$D$105)-E$103,0))) -> 0 | F104: =if('Investment Summary'!$F$8=0,if(F$100>'Capital Stack'!$C$12,pmt(F$102/12,'Capital Stack'!$C$13*12,-$D$105)-F$103,0),if(F$100>'Investment Summary'!$F$8,0,if(F$100>'Capital Stack'!$C$12,pmt(F$102/12,'Capital Stack'!$C$13*12,-$D$105)-F$103,0))) -> 0 | G104: =if('Investment Summary'!$F$8=0,if(G$100>'Capital Stack'!$C$12,pmt(G$102/12,'Capital Stack'!$C$13*12,-$D$105)-G$103,0),if(G$100>'Investment Summary'!$F$8,0,if(G$100>'Capital Stack'!$C$12,pmt(G$102/12,'Capital Stack'!$C$13*12,-$D$105)-G$103,0))) -> 0 | H104: =if('Investment Summary'!$F$8=0,if(H$100>'Capital Stack'!$C$12,pmt(H$102/12,'Capital Stack'!$C$13*12,-$D$105)-H$103,0),if(H$100>'Investment Summary'!$F$8,0,if(H$100>'Capital Stack'!$C$12,pmt(H$102/12,'Capital Stack'!$C$13*12,-$D$105)-H$103,0))) -> 0 | I104: =if('Investment Summary'!$F$8=0,if(I$100>'Capital Stack'!$C$12,pmt(I$102/12,'Capital Stack'!$C$13*12,-$D$105)-I$103,0),if(I$100>'Investment Summary'!$F$8,0,if(I$100>'Capital Stack'!$C$12,pmt(I$102/12,'Capital Stack'!$C$13*12,-$D$105)-I$103,0))) -> 0 | J104: =if('Investment Summary'!$F$8=0,if(J$100>'Capital Stack'!$C$12,pmt(J$102/12,'Capital Stack'!$C$13*12,-$D$105)-J$103,0),if(J$100>'Investment Summary'!$F$8,0,if(J$100>'Capital Stack'!$C$12,pmt(J$102/12,'Capital Stack'!$C$13*12,-$D$105)-J$103,0))) -> 0 | K104: =if('Investment Summary'!$F$8=0,if(K$100>'Capital Stack'!$C$12,pmt(K$102/12,'Capital Stack'!$C$13*12,-$D$105)-K$103,0),if(K$100>'Investment Summary'!$F$8,0,if(K$100>'Capital Stack'!$C$12,pmt(K$102/12,'Capital Stack'!$C$13*12,-$D$105)-K$103,0))) -> 0 | L104: =if('Investment Summary'!$F$8=0,if(L$100>'Capital Stack'!$C$12,pmt(L$102/12,'Capital Stack'!$C$13*12,-$D$105)-L$103,0),if(L$100>'Investment Summary'!$F$8,0,if(L$100>'Capital Stack'!$C$12,pmt(L$102/12,'Capital Stack'!$C$13*12,-$D$105)-L$103,0))) -> 0 | ... DT104: =if('Investment Summary'!$F$8=0,if(DT$100>'Capital Stack'!$C$12,pmt(DT$102/12,'Capital Stack'!$C$13*12,-$D$105)-DT$103,0),if(DT$100>'Investment Summary'!$F$8,0,if(DT$100>'Capital Stack'!$C$12,pmt(DT$102/12,'Capital Stack'!$C$13*12,-$D$105)-DT$103,0))) -> 24576.751
B105: Loan Balance | D105: ='Capital Stack'!C17 -> 21900000 | E105: =D105-E104+D106 -> 21900000 | F105: =E105-F104+E106 -> 21900000 | G105: =F105-G104+F106 -> 21900000 | H105: =G105-H104+G106 -> 21900000 | I105: =H105-I104+H106 -> 21900000 | J105: =I105-J104+I106 -> 21900000 | K105: =J105-K104+J106 -> 21900000 | L105: =K105-L104+K106 -> 21900000 | ... DT105: =DS105-DT104+DS106 -> -884763.02
B106: Loan Payoff | E106: =if(and('Investment Summary'!$F$8=0,E$100='Investment Summary'!$F$9),-E$105,if(E$100='Investment Summary'!$F$8,-E$105,0)) -> 0 | F106: =if(and('Investment Summary'!$F$8=0,F$100='Investment Summary'!$F$9),-F$105,if(F$100='Investment Summary'!$F$8,-F$105,0)) -> 0 | G106: =if(and('Investment Summary'!$F$8=0,G$100='Investment Summary'!$F$9),-G$105,if(G$100='Investment Summary'!$F$8,-G$105,0)) -> 0 | H106: =if(and('Investment Summary'!$F$8=0,H$100='Investment Summary'!$F$9),-H$105,if(H$100='Investment Summary'!$F$8,-H$105,0)) -> 0 | I106: =if(and('Investment Summary'!$F$8=0,I$100='Investment Summary'!$F$9),-I$105,if(I$100='Investment Summary'!$F$8,-I$105,0)) -> 0 | J106: =if(and('Investment Summary'!$F$8=0,J$100='Investment Summary'!$F$9),-J$105,if(J$100='Investment Summary'!$F$8,-J$105,0)) -> 0 | K106: =if(and('Investment Summary'!$F$8=0,K$100='Investment Summary'!$F$9),-K$105,if(K$100='Investment Summary'!$F$8,-K$105,0)) -> 0 | L106: =if(and('Investment Summary'!$F$8=0,L$100='Investment Summary'!$F$9),-L$105,if(L$100='Investment Summary'!$F$8,-L$105,0)) -> 0 | ... DT106: =if(and('Investment Summary'!$F$8=0,DT$100='Investment Summary'!$F$9),-DT$105,if(DT$100='Investment Summary'!$F$8,-DT$105,0)) -> 0
B107: Cash Flow after Acquisition Loan | E107: =if(E96-sum(E103:E104)<0,0,E96-sum(E103:E104)) -> 62688.116 | F107: =if(F96-sum(F103:F104)<0,0,F96-sum(F103:F104)) -> 62688.116 | G107: =if(G96-sum(G103:G104)<0,0,G96-sum(G103:G104)) -> 62688.116 | H107: =if(H96-sum(H103:H104)<0,0,H96-sum(H103:H104)) -> 58005.163 | I107: =if(I96-sum(I103:I104)<0,0,I96-sum(I103:I104)) -> 58392.512 | J107: =if(J96-sum(J103:J104)<0,0,J96-sum(J103:J104)) -> 58779.86 | K107: =if(K96-sum(K103:K104)<0,0,K96-sum(K103:K104)) -> 59167.209 | L107: =if(L96-sum(L103:L104)<0,0,L96-sum(L103:L104)) -> 59554.558 | ... DT107: =if(DT96-sum(DT103:DT104)<0,0,DT96-sum(DT103:DT104)) -> 116850.91
B108: Reserves Needed - Negative Cash Flow | C108: =sum(E108:DT108) -> 0 | E108: =if(E96-sum(E103:E104)<0,-(E96-sum(E103:E104)),0) -> 0 | F108: =if(F96-sum(F103:F104)<0,-(F96-sum(F103:F104)),0) -> 0 | G108: =if(G96-sum(G103:G104)<0,-(G96-sum(G103:G104)),0) -> 0 | H108: =if(H96-sum(H103:H104)<0,-(H96-sum(H103:H104)),0) -> 0 | I108: =if(I96-sum(I103:I104)<0,-(I96-sum(I103:I104)),0) -> 0 | J108: =if(J96-sum(J103:J104)<0,-(J96-sum(J103:J104)),0) -> 0 | K108: =if(K96-sum(K103:K104)<0,-(K96-sum(K103:K104)),0) -> 0 | L108: =if(L96-sum(L103:L104)<0,-(L96-sum(L103:L104)),0) -> 0 | ... DT108: =if(DT96-sum(DT103:DT104)<0,-(DT96-sum(DT103:DT104)),0) -> 0
B109: Debt Service Coverage Ratio (DSCR) | E109: =iferror(E96/sum(E103:E104),"") -> 1.6400159 | F109: =iferror(F96/sum(F103:F104),"") -> 1.6400159 | G109: =iferror(G96/sum(G103:G104),"") -> 1.6400159 | H109: =iferror(H96/sum(H103:H104),"") -> 1.5922052 | I109: =iferror(I96/sum(I103:I104),"") -> 1.5961598 | J109: =iferror(J96/sum(J103:J104),"") -> 1.6001145 | K109: =iferror(K96/sum(K103:K104),"") -> 1.6040691 | L109: =iferror(L96/sum(L103:L104),"") -> 1.6080237 | ... DT109: =iferror(DT96/sum(DT103:DT104),"") -> 1.9536942
B110: Reserves Needed to meet DSCR | C110: =sum(E110:DT110) -> 0 | E110: =if(sum(E$103:E$104)*'Capital Stack'!$C$16-E$96<0,0,(sum(E$103:E$104)*'Capital Stack'!$C$16)-E$96-E$108) -> 0 | F110: =if(sum(F$103:F$104)*'Capital Stack'!$C$16-F$96<0,0,(sum(F$103:F$104)*'Capital Stack'!$C$16)-F$96-F$108) -> 0 | G110: =if(sum(G$103:G$104)*'Capital Stack'!$C$16-G$96<0,0,(sum(G$103:G$104)*'Capital Stack'!$C$16)-G$96-G$108) -> 0 | H110: =if(sum(H$103:H$104)*'Capital Stack'!$C$16-H$96<0,0,(sum(H$103:H$104)*'Capital Stack'!$C$16)-H$96-H$108) -> 0 | I110: =if(sum(I$103:I$104)*'Capital Stack'!$C$16-I$96<0,0,(sum(I$103:I$104)*'Capital Stack'!$C$16)-I$96-I$108) -> 0 | J110: =if(sum(J$103:J$104)*'Capital Stack'!$C$16-J$96<0,0,(sum(J$103:J$104)*'Capital Stack'!$C$16)-J$96-J$108) -> 0 | K110: =if(sum(K$103:K$104)*'Capital Stack'!$C$16-K$96<0,0,(sum(K$103:K$104)*'Capital Stack'!$C$16)-K$96-K$108) -> 0 | L110: =if(sum(L$103:L$104)*'Capital Stack'!$C$16-L$96<0,0,(sum(L$103:L$104)*'Capital Stack'!$C$16)-L$96-L$108) -> 0 | ... DT110: =if(sum(DT$103:DT$104)*'Capital Stack'!$C$16-DT$96<0,0,(sum(DT$103:DT$104)*'Capital Stack'!$C$16)-DT$96-DT$108) -> 0
B111: Debt Service Coverage Ratio (DSCR) | C111: =min(E111:DT111) -> 1.5922052 | E111: =iferror(sum(E110,E108,E96)/sum(E103:E104),"") -> 1.6400159 | F111: =iferror(sum(F110,F108,F96)/sum(F103:F104),"") -> 1.6400159 | G111: =iferror(sum(G110,G108,G96)/sum(G103:G104),"") -> 1.6400159 | H111: =iferror(sum(H110,H108,H96)/sum(H103:H104),"") -> 1.5922052 | I111: =iferror(sum(I110,I108,I96)/sum(I103:I104),"") -> 1.5961598 | J111: =iferror(sum(J110,J108,J96)/sum(J103:J104),"") -> 1.6001145 | K111: =iferror(sum(K110,K108,K96)/sum(K103:K104),"") -> 1.6040691 | L111: =iferror(sum(L110,L108,L96)/sum(L103:L104),"") -> 1.6080237 | ... DT111: =iferror(sum(DT110,DT108,DT96)/sum(DT103:DT104),"") -> 1.9536942
...

Sheet Waterfall
M2: Waterfall
B3: ='Property Summary'!B3 -> Phoenix, AZ | M3: ='Property Summary'!I3 -> Wind River Group
B5: Total Equity Invested | C5: =sum('Capital Stack'!J8:J9) -> 18617702 | D5: Equity % | E5: Preferred Return | F5: Hurdle Rate | G5: Share up to Hurdle Rate | H5: Share Above Hurdle Rate | J5: Prospective Investor Investment Amount
B6: Limited Partner(s) | C6: ='Capital Stack'!J8 -> 18617702 | D6: ='Investment Summary'!F19 -> 1 | E6: ='Investment Summary'!F20 -> 0.06 | F6: ='Investment Summary'!F21 -> 0.06 | G6: ='Investment Summary'!F22 -> 0.7 | H6: ='Investment Summary'!F23 -> 0.7 | J6: 500000
B7: General Partner(s) | C7: ='Capital Stack'!J9 -> 0 | D7: =1-'Investment Summary'!F19 -> 0
C9: Month | D9: Cap Rate | E9: Gross Sales Price | F9: Selling Costs | G9: Debt Repayment | H9: Proceeds to Equity
B10: Disposition | C10: ='Investment Summary'!F9 -> 84 | D10: ='Investment Summary'!F11 -> 0.05 | E10: =(lookup('Investment Summary'!F9,'Cash Flows'!E57:DT57,'Cash Flows'!E92:DT92)*12)/'Investment Summary'!F11 -> 56406638 | F10: =iferror(-E10*sum(C13:E13),"") -> -846099.56 | G10: =if('Investment Summary'!F8=0,sum('Cash Flows'!E106:DT106),sum('Cash Flows'!E121:DT121)) -> -21900000 | H10: =iferror(sum(E10:G10),"") -> 33660538
C12: Closing Costs | D12: Broker Fee | E12: Disposition Fee
B13: Selling Costs | C13: ='Investment Summary'!H10 -> 0 | D13: ='Investment Summary'!H11 -> 0.01 | E13: ='Investment Summary'!H14 -> 0.005
B15: Total Limited Partner(s) Return | C15: 0 | D15: =C15+1 -> 1 | E15: =D15+1 -> 2 | F15: =E15+1 -> 3 | G15: =F15+1 -> 4 | H15: =G15+1 -> 5 | I15: =H15+1 -> 6 | J15: =I15+1 -> 7 | K15: =J15+1 -> 8 | ... M15: =L15+1 -> 10
B16: Capital Investment | C16: =sumif($C$60:$DS$60,C$15,$C96:$DS96) -> -18617702 | D16: =sumif($C$60:$DS$60,D$15,$C96:$DS96) -> 0 | E16: =sumif($C$60:$DS$60,E$15,$C96:$DS96) -> 0 | F16: =sumif($C$60:$DS$60,F$15,$C96:$DS96) -> 0 | G16: =sumif($C$60:$DS$60,G$15,$C96:$DS96) -> 0 | H16: =sumif($C$60:$DS$60,H$15,$C96:$DS96) -> 0 | I16: =sumif($C$60:$DS$60,I$15,$C96:$DS96) -> 0 | J16: =sumif($C$60:$DS$60,J$15,$C96:$DS96) -> 0 | ... M16: =sumif($C$60:$DS$60,M$15,$C96:$DS96) -> 0
B17: Preferred Return | C17: =sumif($C$60:$DS$60,C$15,$C97:$DS97) -> 0 | D17: =sumif($C$60:$DS$60,D$15,$C97:$DS97) -> 724055.38 | E17: =sumif($C$60:$DS$60,E$15,$C97:$DS97) -> 862577.03 | F17: =sumif($C$60:$DS$60,F$15,$C97:$DS97) -> 1023035.9 | G17: =sumif($C$60:$DS$60,G$15,$C97:$DS97) -> 1106531.8 | H17: =sumif($C$60:$DS$60,H$15,$C97:$DS97) -> 1192914.2 | I17: =sumif($C$60:$DS$60,I$15,$C97:$DS97) -> 1282281.2 | J17: =sumif($C$60:$DS$60,J$15,$C97:$DS97) -> 20527227 | ... M17: =sumif($C$60:$DS$60,M$15,$C97:$DS97) -> 0
B18: Tier 1 Split | C18: =sumif($C$60:$DS$60,C$15,$C98:$DS98) -> 0 | D18: =sumif($C$60:$DS$60,D$15,$C98:$DS98) -> 0 | E18: =sumif($C$60:$DS$60,E$15,$C98:$DS98) -> 0 | F18: =sumif($C$60:$DS$60,F$15,$C98:$DS98) -> 0 | G18: =sumif($C$60:$DS$60,G$15,$C98:$DS98) -> 0 | H18: =sumif($C$60:$DS$60,H$15,$C98:$DS98) -> 0 | I18: =sumif($C$60:$DS$60,I$15,$C98:$DS98) -> 0 | J18: =sumif($C$60:$DS$60,J$15,$C98:$DS98) -> 0.0016100012 | ... M18: =sumif($C$60:$DS$60,M$15,$C98:$DS98) -> 0
B19: Tier 2 Split | C19: =sumif($C$60:$DS$60,C$15,$C99:$DS99) -> 0 | D19: =sumif($C$60:$DS$60,D$15,$C99:$DS99) -> 0 | E19: =sumif($C$60:$DS$60,E$15,$C99:$DS99) -> 0 | F19: =sumif($C$60:$DS$60,F$15,$C99:$DS99) -> 0 | G19: =sumif($C$60:$DS$60,G$15,$C99:$DS99) -> 0 | H19: =sumif($C$60:$DS$60,H$15,$C99:$DS99) -> 0 | I19: =sumif($C$60:$DS$60,I$15,$C99:$DS99) -> 0 | J19: =sumif($C$60:$DS$60,J$15,$C99:$DS99) -> 10155631 | ... M19: =sumif($C$60:$DS$60,M$15,$C99:$DS99) -> 0
B20: Total Return | C20: =sumif($C$60:$DS$60,C$15,$C100:$DS100) -> -18617702 | D20: =sumif($C$60:$DS$60,D$15,$C100:$DS100) -> 724055.38 | E20: =sumif($C$60:$DS$60,E$15,$C100:$DS100) -> 862577.03 | F20: =sumif($C$60:$DS$60,F$15,$C100:$DS100) -> 1023035.9 | G20: =sumif($C$60:$DS$60,G$15,$C100:$DS100) -> 1106531.8 | H20: =sumif($C$60:$DS$60,H$15,$C100:$DS100) -> 1192914.2 | I20: =sumif($C$60:$DS$60,I$15,$C100:$DS100) -> 1282281.2 | J20: =sumif($C$60:$DS$60,J$15,$C100:$DS100) -> 30682858 | ... M20: =sumif($C$60:$DS$60,M$15,$C100:$DS100) -> 0
B21: IRR | C21: =C101 -> 0.11595421
B22: EQM | C22: =C102 -> 1.9806017
B23: Total Capital Invested | C23: =C103 -> 18617702
B24: Total Return | C24: =C104 -> 36874254
B26: Seller's Investment Amount
B27: Capital Investment | C27: =sumif($C$60:$DS$60,C$15,$C107:$DS107) -> -500000 | D27: =sumif($C$60:$DS$60,D$15,$C107:$DS107) -> 0 | E27: =sumif($C$60:$DS$60,E$15,$C107:$DS107) -> 0 | F27: =sumif($C$60:$DS$60,F$15,$C107:$DS107) -> 0 | G27: =sumif($C$60:$DS$60,G$15,$C107:$DS107) -> 0 | H27: =sumif($C$60:$DS$60,H$15,$C107:$DS107) -> 0 | I27: =sumif($C$60:$DS$60,I$15,$C107:$DS107) -> 0 | J27: =sumif($C$60:$DS$60,J$15,$C107:$DS107) -> 0 | ... M27: =sumif($C$60:$DS$60,M$15,$C107:$DS107) -> 0
B28: Preferred Return | C28: =sumif($C$60:$DS$60,C$15,$C108:$DS108) -> 0 | D28: =sumif($C$60:$DS$60,D$15,$C108:$DS108) -> 19445.347 | E28: =sumif($C$60:$DS$60,E$15,$C108:$DS108) -> 23165.507 | F28: =sumif($C$60:$DS$60,F$15,$C108:$DS108) -> 27474.815 | G28: =sumif($C$60:$DS$60,G$15,$C108:$DS108) -> 29717.194 | H28: =sumif($C$60:$DS$60,H$15,$C108:$DS108) -> 32037.096 | I28: =sumif($C$60:$DS$60,I$15,$C108:$DS108) -> 34437.15 | J28: =sumif($C$60:$DS$60,J$15,$C108:$DS108) -> 551282.49 | ... M28: =sumif($C$60:$DS$60,M$15,$C108:$DS108) -> 0
B29: Tier 1 Split | C29: =sumif($C$60:$DS$60,C$15,$C109:$DS109) -> 0 | D29: =sumif($C$60:$DS$60,D$15,$C109:$DS109) -> 0 | E29: =sumif($C$60:$DS$60,E$15,$C109:$DS109) -> 0 | F29: =sumif($C$60:$DS$60,F$15,$C109:$DS109) -> 0 | G29: =sumif($C$60:$DS$60,G$15,$C109:$DS109) -> 0 | H29: =sumif($C$60:$DS$60,H$15,$C109:$DS109) -> 0 | I29: =sumif($C$60:$DS$60,I$15,$C109:$DS109) -> 0 | J29: =sumif($C$60:$DS$60,J$15,$C109:$DS109) -> 4.3238449e-05 | ... M29: =sumif($C$60:$DS$60,M$15,$C109:$DS109) -> 0
B30: Tier 2 Split | C30: =sumif($C$60:$DS$60,C$15,$C110:$DS110) -> 0 | D30: =sumif($C$60:$DS$60,D$15,$C110:$DS110) -> 0 | E30: =sumif($C$60:$DS$60,E$15,$C110:$DS110) -> 0 | F30: =sumif($C$60:$DS$60,F$15,$C110:$DS110) -> 0 | G30: =sumif($C$60:$DS$60,G$15,$C110:$DS110) -> 0 | H30: =sumif($C$60:$DS$60,H$15,$C110:$DS110) -> 0 | I30: =sumif($C$60:$DS$60,I$15,$C110:$DS110) -> 0 | J30: =sumif($C$60:$DS$60,J$15,$C110:$DS110) -> 272741.26 | ... M30: =sumif($C$60:$DS$60,M$15,$C110:$DS110) -> 0
B31: Total Return | C31: =sumif($C$60:$DS$60,C$15,$C111:$DS111) -> -500000 | D31: =sumif($C$60:$DS$60,D$15,$C111:$DS111) -> 19445.347 | E31: =sumif($C$60:$DS$60,E$15,$C111:$DS111) -> 23165.507 | F31: =sumif($C$60:$DS$60,F$15,$C111:$DS111) -> 27474.815 | G31: =sumif($C$60:$DS$60,G$15,$C111:$DS111) -> 29717.194 | H31: =sumif($C$60:$DS$60,H$15,$C111:$DS111) -> 32037.096 | I31: =sumif($C$60:$DS$60,I$15,$C111:$DS111) -> 34437.15 | J31: =sumif($C$60:$DS$60,J$15,$C111:$DS111) -> 824023.75 | ... M31: =sumif($C$60:$DS$60,M$15,$C111:$DS111) -> 0
B32: IRR | C32: =C112 -> 0.11595421
B33: EQM | C33: =C113 -> 1.9806017
B34: Total Capital Invested | C34: =C114 -> 500000
B35: Total Return | C35: =C115 -> 990300.86
B37: Total General Partner(s) Return | C37: 0 | D37: =C37+1 -> 1 | E37: =D37+1 -> 2 | F37: =E37+1 -> 3 | G37: =F37+1 -> 4 | H37: =G37+1 -> 5 | I37: =H37+1 -> 6 | J37: =I37+1 -> 7 | K37: =J37+1 -> 8 | ... M37: =L37+1 -> 10
B38: Capital Investment | C38: =sumif($C$60:$DS$60,C$15,$C118:$DS118) -> 0 | D38: =sumif($C$60:$DS$60,D$15,$C118:$DS118) -> 0 | E38: =sumif($C$60:$DS$60,E$15,$C118:$DS118) -> 0 | F38: =sumif($C$60:$DS$60,F$15,$C118:$DS118) -> 0 | G38: =sumif($C$60:$DS$60,G$15,$C118:$DS118) -> 0 | H38: =sumif($C$60:$DS$60,H$15,$C118:$DS118) -> 0 | I38: =sumif($C$60:$DS$60,I$15,$C118:$DS118) -> 0 | J38: =sumif($C$60:$DS$60,J$15,$C118:$DS118) -> 0 | ... M38: =sumif($C$60:$DS$60,M$15,$C118:$DS118) -> 0
B39: Preferred Return | C39: =sumif($C$60:$DS$60,C$15,$C119:$DS119) -> 0 | D39: =sumif($C$60:$DS$60,D$15,$C119:$DS119) -> 0 | E39: =sumif($C$60:$DS$60,E$15,$C119:$DS119) -> 0 | F39: =sumif($C$60:$DS$60,F$15,$C119:$DS119) -> 0 | G39: =sumif($C$60:$DS$60,G$15,$C119:$DS119) -> 0 | H39: =sumif($C$60:$DS$60,H$15,$C119:$DS119) -> 0 | I39: =sumif($C$60:$DS$60,I$15,$C119:$DS119) -> 0 | J39: =sumif($C$60:$DS$60,J$15,$C119:$DS119) -> 0 | ... M39: =sumif($C$60:$DS$60,M$15,$C119:$DS119) -> 0
B40: Tier 1 Split | C40: =sumif($C$60:$DS$60,C$15,$C120:$DS120) -> 0 | D40: =sumif($C$60:$DS$60,D$15,$C120:$DS120) -> 0 | E40: =sumif($C$60:$DS$60,E$15,$C120:$DS120) -> 0 | F40: =sumif($C$60:$DS$60,F$15,$C120:$DS120) -> 0 | G40: =sumif($C$60:$DS$60,G$15,$C120:$DS120) -> 0 | H40: =sumif($C$60:$DS$60,H$15,$C120:$DS120) -> 0 | I40: =sumif($C$60:$DS$60,I$15,$C120:$DS120) -> 0 | J40: =sumif($C$60:$DS$60,J$15,$C120:$DS120) -> 0.0006900005 | ... M40: =sumif($C$60:$DS$60,M$15,$C120:$DS120) -> 0
B41: Tier 2 Split | C41: =sumif($C$60:$DS$60,C$15,$C121:$DS121) -> 0 | D41: =sumif($C$60:$DS$60,D$15,$C121:$DS121) -> 0 | E41: =sumif($C$60:$DS$60,E$15,$C121:$DS121) -> 0 | F41: =sumif($C$60:$DS$60,F$15,$C121:$DS121) -> 0 | G41: =sumif($C$60:$DS$60,G$15,$C121:$DS121) -> 0 | H41: =sumif($C$60:$DS$60,H$15,$C121:$DS121) -> 0 | I41: =sumif($C$60:$DS$60,I$15,$C121:$DS121) -> 0 | J41: =sumif($C$60:$DS$60,J$15,$C121:$DS121) -> 4352413.4 | ... M41: =sumif($C$60:$DS$60,M$15,$C121:$DS121) -> 0
B42: Total Return | C42: =sumif($C$60:$DS$60,C$15,$C122:$DS122) -> 0 | D42: =sumif($C$60:$DS$60,D$15,$C122:$DS122) -> 0 | E42: =sumif($C$60:$DS$60,E$15,$C122:$DS122) -> 0 | F42: =sumif($C$60:$DS$60,F$15,$C122:$DS122) -> 0 | G42: =sumif($C$60:$DS$60,G$15,$C122:$DS122) -> 0 | H42: =sumif($C$60:$DS$60,H$15,$C122:$DS122) -> 0 | I42: =sumif($C$60:$DS$60,I$15,$C122:$DS122) -> 0 | J42: =sumif($C$60:$DS$60,J$15,$C122:$DS122) -> 4352413.4 | ... M42: =sumif($C$60:$DS$60,M$15,$C122:$DS122) -> 0
B43: IRR | C43: =C123
B44: EQM | C44: =C124 -> #DIV/0!
B45: Total Capital Invested | C45: =C125 -> 0
B46: Total Return | C46: =C126 -> 4352413.4
C47: =C156
B48: Project Level Returns | C48: 0 | D48: =C48+1 -> 1 | E48: =D48+1 -> 2 | F48: =E48+1 -> 3 | G48: =F48+1 -> 4 | H48: =G48+1 -> 5 | I48: =H48+1 -> 6 | J48: =I48+1 -> 7 | K48: =J48+1 -> 8 | ... M48: =L48+1 -> 10
B49: Capital Investment | C49: =sumif($C$60:$DS$60,C$15,$C129:$DS129) -> -18617702 | D49: =sumif($C$60:$DS$60,D$15,$C129:$DS129) -> 0 | E49: =sumif($C$60:$DS$60,E$15,$C129:$DS129) -> 0 | F49: =sumif($C$60:$DS$60,F$15,$C129:$DS129) -> 0 | G49: =sumif($C$60:$DS$60,G$15,$C129:$DS129) -> 0 | H49: =sumif($C$60:$DS$60,H$15,$C129:$DS129) -> 0 | I49: =sumif($C$60:$DS$60,I$15,$C129:$DS129) -> 0 | J49: =sumif($C$60:$DS$60,J$15,$C129:$DS129) -> 0 | ... M49: =sumif($C$60:$DS$60,M$15,$C129:$DS129) -> 0
B50: Preferred Return | C50: =sumif($C$60:$DS$60,C$15,$C130:$DS130) -> 0 | D50: =sumif($C$60:$DS$60,D$15,$C130:$DS130) -> 724055.38 | E50: =sumif($C$60:$DS$60,E$15,$C130:$DS130) -> 862577.03 | F50: =sumif($C$60:$DS$60,F$15,$C130:$DS130) -> 1023035.9 | G50: =sumif($C$60:$DS$60,G$15,$C130:$DS130) -> 1106531.8 | H50: =sumif($C$60:$DS$60,H$15,$C130:$DS130) -> 1192914.2 | I50: =sumif($C$60:$DS$60,I$15,$C130:$DS130) -> 1282281.2 | J50: =sumif($C$60:$DS$60,J$15,$C130:$DS130) -> 20527227 | ... M50: =sumif($C$60:$DS$60,M$15,$C130:$DS130) -> 0
B51: Tier 1 Split | C51: =sumif($C$60:$DS$60,C$15,$C131:$DS131) -> 0 | D51: =sumif($C$60:$DS$60,D$15,$C131:$DS131) -> 0 | E51: =sumif($C$60:$DS$60,E$15,$C131:$DS131) -> 0 | F51: =sumif($C$60:$DS$60,F$15,$C131:$DS131) -> 0 | G51: =sumif($C$60:$DS$60,G$15,$C131:$DS131) -> 0 | H51: =sumif($C$60:$DS$60,H$15,$C131:$DS131) -> 0 | I51: =sumif($C$60:$DS$60,I$15,$C131:$DS131) -> 0 | J51: =sumif($C$60:$DS$60,J$15,$C131:$DS131) -> 0.0023000017 | ... M51: =sumif($C$60:$DS$60,M$15,$C131:$DS131) -> 0
B52: Tier 2 Split | C52: =sumif($C$60:$DS$60,C$15,$C132:$DS132) -> 0 | D52: =sumif($C$60:$DS$60,D$15,$C132:$DS132) -> 0 | E52: =sumif($C$60:$DS$60,E$15,$C132:$DS132) -> 0 | F52: =sumif($C$60:$DS$60,F$15,$C132:$DS132) -> 0 | G52: =sumif($C$60:$DS$60,G$15,$C132:$DS132) -> 0 | H52: =sumif($C$60:$DS$60,H$15,$C132:$DS132) -> 0 | I52: =sumif($C$60:$DS$60,I$15,$C132:$DS132) -> 0 | J52: =sumif($C$60:$DS$60,J$15,$C132:$DS132) -> 14508045 | ... M52: =sumif($C$60:$DS$60,M$15,$C132:$DS132) -> 0
B53: Total Return | C53: =sumif($C$60:$DS$60,C$15,$C133:$DS133) -> -18617702 | D53: =sumif($C$60:$DS$60,D$15,$C133:$DS133) -> 724055.38 | E53: =sumif($C$60:$DS$60,E$15,$C133:$DS133) -> 862577.03 | F53: =sumif($C$60:$DS$60,F$15,$C133:$DS133) -> 1023035.9 | G53: =sumif($C$60:$DS$60,G$15,$C133:$DS133) -> 1106531.8 | H53: =sumif($C$60:$DS$60,H$15,$C133:$DS133) -> 1192914.2 | I53: =sumif($C$60:$DS$60,I$15,$C133:$DS133) -> 1282281.2 | J53: =sumif($C$60:$DS$60,J$15,$C133:$DS133) -> 35035272 | ... M53: =sumif($C$60:$DS$60,M$15,$C133:$DS133) -> 0
B54: IRR | C54: =C134 -> 0.13486029
B55: EQM | C55: =C135 -> 2.2143799
B56: Total Capital Invested | C56: =C136 -> 18617702
B57: Total Return | C57: =C137 -> 41226667
C58: =C167
B60: Analysis Year | C60: =ROUNDUP(C62/12,0) -> 0 | D60: =ROUNDUP(D62/12,0) -> 1 | E60: =ROUNDUP(E62/12,0) -> 1 | F60: =ROUNDUP(F62/12,0) -> 1 | G60: =ROUNDUP(G62/12,0) -> 1 | H60: =ROUNDUP(H62/12,0) -> 1 | I60: =ROUNDUP(I62/12,0) -> 1 | J60: =ROUNDUP(J62/12,0) -> 1 | ... DS60: =ROUNDUP(DS62/12,0) -> 10
B61: Date | C61: ='Cash Flows'!D58 -> 45838 | D61: ='Cash Flows'!E58 -> 45869 | E61: ='Cash Flows'!F58 -> 45900 | F61: ='Cash Flows'!G58 -> 45930 | G61: ='Cash Flows'!H58 -> 45961 | H61: ='Cash Flows'!I58 -> 45991 | I61: ='Cash Flows'!J58 -> 46022 | J61: ='Cash Flows'!K58 -> 46053 | ... DS61: ='Cash Flows'!DT58 -> 49490
B62: Period (Months) | C62: 0 | D62: =C62+1 -> 1 | E62: =D62+1 -> 2 | F62: =E62+1 -> 3 | G62: =F62+1 -> 4 | H62: =G62+1 -> 5 | I62: =H62+1 -> 6 | J62: =I62+1 -> 7 | K62: =J62+1 -> 8 | ... DS62: =DR62+1 -> 120
B63: Net Operating Income | D63: =if(D62>$C$10,0,'Cash Flows'!E$92) -> 181699.44 | E63: =if(E62>$C$10,0,'Cash Flows'!F$92) -> 181699.44 | F63: =if(F62>$C$10,0,'Cash Flows'!G$92) -> 181699.44 | G63: =if(G62>$C$10,0,'Cash Flows'!H$92) -> 176920.92 | H63: =if(H62>$C$10,0,'Cash Flows'!I$92) -> 177316.17 | I63: =if(I62>$C$10,0,'Cash Flows'!J$92) -> 177711.43 | J63: =if(J62>$C$10,0,'Cash Flows'!K$92) -> 178106.68 | K63: =if(K62>$C$10,0,'Cash Flows'!L$92) -> 178501.94 | ... DS63: =if(DS62>$C$10,0,'Cash Flows'!DT$92) -> 0
B65: Net Cash Flow | D65: =if(D62>$C$10,0,'Cash Flows'!E$122) -> 62688.12 | E65: =if(E62>$C$10,0,'Cash Flows'!F$122) -> 62688.12 | F65: =if(F62>$C$10,0,'Cash Flows'!G$122) -> 62688.12 | G65: =if(G62>$C$10,0,'Cash Flows'!H$122) -> 58005.16 | H65: =if(H62>$C$10,0,'Cash Flows'!I$122) -> 58392.51 | I65: =if(I62>$C$10,0,'Cash Flows'!J$122) -> 58779.86 | J65: =if(J62>$C$10,0,'Cash Flows'!K$122) -> 59167.21 | K65: =if(K62>$C$10,0,'Cash Flows'!L$122) -> 59554.56 | ... DS65: =if(DS62>$C$10,0,'Cash Flows'!DT$122) -> 0
B66: Limited Partner(s) | D66: =iferror(D65*$D6,0) -> 62688.12 | E66: =iferror(E65*$D6,0) -> 62688.12 | F66: =iferror(F65*$D6,0) -> 62688.12 | G66: =iferror(G65*$D6,0) -> 58005.16 | H66: =iferror(H65*$D6,0) -> 58392.51 | I66: =iferror(I65*$D6,0) -> 58779.86 | J66: =iferror(J65*$D6,0) -> 59167.21 | K66: =iferror(K65*$D6,0) -> 59554.56 | ... DS66: =iferror(DS65*$D6,0) -> 0
B67: General Partner(s) | D67: =iferror(D66*$D7,0) -> 0 | E67: =iferror(E66*$D7,0) -> 0 | F67: =iferror(F66*$D7,0) -> 0 | G67: =iferror(G66*$D7,0) -> 0 | H67: =iferror(H66*$D7,0) -> 0 | I67: =iferror(I66*$D7,0) -> 0 | J67: =iferror(J66*$D7,0) -> 0 | K67: =iferror(K66*$D7,0) -> 0 | ... DS67: =iferror(DS66*$D7,0) -> 0
B69: Refinance / Disposition Proceeds | D69: ='Cash Flows'!E115-'Cash Flows'!E116-'Cash Flows'!E117+if(D62=$C$10,$H$10,0) -> 0 | E69: ='Cash Flows'!F115-'Cash Flows'!F116-'Cash Flows'!F117+if(E62=$C$10,$H$10,0) -> 0 | F69: ='Cash Flows'!G115-'Cash Flows'!G116-'Cash Flows'!G117+if(F62=$C$10,$H$10,0) -> 0 | G69: ='Cash Flows'!H115-'Cash Flows'!H116-'Cash Flows'!H117+if(G62=$C$10,$H$10,0) -> 0 | H69: ='Cash Flows'!I115-'Cash Flows'!I116-'Cash Flows'!I117+if(H62=$C$10,$H$10,0) -> 0 | I69: ='Cash Flows'!J115-'Cash Flows'!J116-'Cash Flows'!J117+if(I62=$C$10,$H$10,0) -> 0 | J69: ='Cash Flows'!K115-'Cash Flows'!K116-'Cash Flows'!K117+if(J62=$C$10,$H$10,0) -> 0 | K69: ='Cash Flows'!L115-'Cash Flows'!L116-'Cash Flows'!L117+if(K62=$C$10,$H$10,0) -> 0 | ... DS69: ='Cash Flows'!DT115-'Cash Flows'!DT116-'Cash Flows'!DT117+if(DS62=$C$10,$H$10,0) -> 0
B71: IRR Waterfall Pref & Tier 1
B72: Beginning Balance | D72: =C76 -> -18617702 | E72: =D76 -> -18648103 | F72: =E76 -> -18678655 | G72: =F76 -> -18709360 | H72: =G76 -> -18744902 | I72: =H76 -> -18780234 | J72: =I76 -> -18815355 | K72: =J76 -> -18850265 | ... DS72: =DR76 -> 0
B73: Capital Investment | C73: =iferror(-$C$5,0) -> -18617702 | D73: 0 | E73: =$D73 -> 0 | F73: =$D73 -> 0 | G73: =$D73 -> 0 | H73: =$D73 -> 0 | I73: =$D73 -> 0 | J73: =$D73 -> 0 | K73: =$D73 -> 0 | L73: =$D73 -> 0 | ... DS73: =$D73 -> 0
